Workbook

Sheet List Project
A1: No | B1: ID Project | C1: Tahun | D1: Periode | E1: Nama Project | F1: Jenis Project | G1: PMG | H1: PM | I1: Revenue Akhir | J1: Segment Sales | K1: Klasifikasi Project | L1: Nama AM | M1: Tanggal Project Charter | N1: Target | O1: Nama PIC | P1: Status | Q1: Order | R1: Konfigurasi | S1: Integrasi | T1: Tshoot | U1: Keterangan | V1: PM
A2: 1 | B2: P232251-01-00 | C2: 2024 | D2: Januari | E2: Perpanjangan Layanan Omnichannel Untuk PT Inti Cakrawala Citra (Indogrosir) 2023-2025 | F2: CRM | G2: CRM 1 | H2: AGM | I2: 328800000 | J2: Private | K2: C | L2: Robby Kautsar | M2: 45266 | N2: 45294 | O2: Duta | P2: Done
A3: 2 | B3: P232385-03-00 | C3: 2024 | D3: Januari | E3: Layanan Contact Center Voice LKPP Desember 2023 | F3: CRM | G3: CRM 2 | H3: MIH | I3: 85100000 | J3: Telkom Group | K3: C | L3: Alldicka Christvelldy | M3: 45276 | N3: 45303 | O3: Duta | P3: Done
A4: 3 | B4: P232154-03-00 | C4: 2024 | D4: Januari | E4: Pengadaan Jasa Managed Operation Pengelolaan Contact BRI Site Jakarta | F4: CRM | G4: CRM 2 | H4: RGZ | I4: 9980698000 | J4: SOE | K4: A | L4: Artha | M4: 45293 | N4: 45317 | O4: Adi | P4: Done
A5: 4 | B5: P232417-01-00 | C5: 2024 | D5: Januari | E5: Nomor Akses 1500024 Universitas Terbuka | F5: Nomor Akses | G5: =SUM('List Project'!I:I) -> 2.1862641e+12 | H5: ARY | I5: 140460000 | J5: SOE | K5: C | L5: Ricka Winatha | M5: 45300 | N5: 45324 | O5: Dwi | P5: Done
A6: 5 | B6: P232472-02-00 | C6: 2024 | D6: Januari | E6: Nomor Akses 1500158 UNIVERSITAS GUNADARMA | F6: Nomor Akses | G6: CRM 1 | H6: PGP | I6: 88000000 | J6: Private | K6: C | L6: Fadel Bahruraji | M6: 45300 | N6: 45324 | O6: Duta | P6: Done
A7: 6 | B7: P232558-03-00 | C7: 2024 | D7: Januari | E7: Pengadaan Jasa Contact Center Pelayanan Publik pada Ditjen Kekayaan Intelektual-DKI Jakarta TA 2024 | F7: CRM | G7: CRM 2 | H7: MIH | I7: 5060900901 | J7: SME & GOV | K7: A | L7: Alldicka Christvelldy | M7: 45301 | N7: 45351 | O7: Duta | P7: Done
A8: 7 | B8: P232499-03-00 | C8: 2024 | D8: Januari | E8: Jasa Layanan Contact Center Kementerian Investasi (BKPM) Tahun 2024 | F8: CRM | G8: CRM 1 | H8: AGM | I8: 32506539688 | J8: SME & GOV | K8: A | L8: Akhmad Yani | M8: 45302 | N8: 45359 | O8: Duta | P8: Done
A9: 8 | B9: P232329-03-00 | C9: 2024 | D9: Januari | E9: Novasi Layanan Nomor Akses 1500218 PT KSP Sahabat Mitra Sejati | F9: Nomor Akses | G9: CRM 1 | H9: PGP | I9: 89000000 | J9: SME & GOV | K9: C | L9: Rahmatya Dwi Arini Rahadina | M9: 45302 | N9: 45328 | O9: Duta | P9: Done
A10: 9 | B10: P232407-05-00 | C10: 2024 | D10: Januari | E10: Sewa System Digital Contact Center Bank Jateng 2024-2025 | F10: CRM | G10: CRM 2 | H10: ARY | I10: 840000000 | J10: SME & GOV | K10: B | L10: Bagus Afiansah | M10: 45306 | N10: 45342 | O10: Gugum | P10: Done
A11: 10 | B11: P232479-01-00 | C11: 2024 | D11: Januari | E11: Novasi Layanan Nomor Akses 1500985 PT Sompo Insurance Indonesia | F11: Nomor Akses | G11: CRM 1 | H11: PGP | I11: 134000000 | J11: Private | K11: C | L11: Rahmatya Dwi Arini Rahadina | M11: 45308 | N11: 45442 | O11: Duta | P11: Done
A12: 11 | B12: P232343-07-00 | C12: 2024 | D12: Januari | E12: Pengembangan Layanan Voice Digital Asuransi Tokio Marine | F12: CRM | G12: CRM 1 | H12: PGP | I12: 51000000 | J12: Private | K12: C | L12: Bella Gusniri Ht | M12: 45309 | N12: 45349 | O12: Duta | P12: Done
A13: 12 | B13: P232400-02-00 | C13: 2024 | D13: Januari | E13: Perpanjangan Contact Center RS Sardjito dan Nomor Akses 1500705 2023-2024 | F13: CRM | G13: CRM 2 | H13: RGZ | I13: 279540000 | J13: SME & GOV | K13: B | L13: Bagus Afiansah | M13: 45310 | N13: 45342 | O13: Dwi | P13: Done
A14: 13 | B14: P232490-04-00 | C14: 2024 | D14: Januari | E14: Perpanjangan Pekerjaan Sewa Layanan Contact Center BMKG TA 2024 | F14: CRM | G14: CRM 2 | H14: RGZ | I14: 2275675676 | J14: SME & GOV | K14: B | L14: Angga Yudha Pratama | M14: 45315 | N14: 45352 | O14: Duta | P14: Done
A15: 14 | B15: P232120-01-00 | C15: 2024 | D15: Januari | E15: Nomor Akses MORATELINDO - 1500882 | F15: Nomor Akses | G15: CRM 1 | H15: PGP | I15: 2241600000 | J15: Private | K15: C | L15: Fadel Bahruraji | M15: 45317 | N15: 45352 | O15: Duta | P15: Done
A16: 15 | B16: P242580-02-00 | C16: 2024 | D16: Januari | E16: Perpanjangan Masking Outbound 14040 BSI 2023-2024 | F16: Nomor Akses | G16: CRM 2 | H16: IDR | I16: 136800000 | J16: SOE | K16: C | L16: Artha | M16: 45317 | N16: 45351 | O16: Dwi | P16: Done
A17: 16 | B17: P232075-06-00 | C17: 2024 | D17: Januari | E17: Layanan Contact Center Bank BJB Syariah 2023-2024 | F17: CRM | G17: CRM 1 | H17: RSA | I17: 1326306180 | J17: SME & GOV | K17: B | L17: Fuzi Ridwan Firdaus | M17: 45322 | N17: 45343 | O17: Duta | P17: Done
... A64: 63 | B64: P242925-01-00 | C64: 2024 | D64: April | E64: Sewa Layanan License Contact Center KSO Sucofindo Surveyor Indonesia | F64: CRM | G64: CRM 1 | H64: RZS | I64: 91168000 | J64: SOE | K64: C | L64: Yadi Nurcahyadi | M64: 45412 | N64: 45446 | O64: Duta | P64: Done
A65: 64 | B65: P232238-03-00 | C65: 2024 | D65: Mei | E65: Novasi Nomor Akses 1500852 Chubb Life Insurance Indonesia | F65: Nomor Akses | G65: CRM 2 | H65: PPP | I65: 112000000 | J65: Private | K65: C | L65: Yane Anastasia | M65: 45414 | N65: 45447 | O65: Duta | P65: cancel | U65: terkendala pr crossconnect di DCI (dari user tidak mau ada biaya tambahan)
A66: 65 | B66: P242857-03-00 | C66: 2024 | D66: Mei | E66: Layanan Contact Center 150511 Perumda Tirta Kanjuruhan Kabupaten Malang | F66: CRM | G66: CRM 2 | H66: RGZ | I66: 263452000 | J66: SME & GOV | K66: C | L66: Ricka Winatha | M66: 45415 | N66: 45443 | O66: Duta | P66: Done
A67: 66 | B67: P242585-03-00 | C67: 2024 | D67: Mei | E67: Perpanjangan Layanan Contact Center RSUD Tarakan Periode Jan - Des 2024 | F67: Nomor Akses | G67: CRM 2 | H67: RGZ | I67: 843600000 | J67: SME & GOV | K67: B | L67: Giany Nadlillah | M67: 45418 | N67: 45448 | O67: Gugum | P67: Done
A68: 67 | B68: P242711-06-00 | C68: 2024 | D68: Mei | E68: Nomor Akses 1500488 RS Hermina 2024 | F68: Nomor Akses | G68: CRM 1 | H68: RNO | I68: 361387200 | J68: Private | K68: C | L68: Fadel Bahruraji | M68: 45418 | N68: 45467 | O68: Gugum | P68: Done
A69: 68 | B69: P242795-03-00 | C69: 2024 | D69: Mei | E69: Penyediaan Nomor akses 1500988 PT Supra Primatama Nusantara 2024 | F69: Nomor Akses | G69: CRM 1 | H69: RNO | I69: 208460000 | J69: Private | K69: C | L69: Fadel Bahruraji | M69: 45418 | N69: 45448 | O69: Gugum | P69: Done
A70: 69 | B70: P242797-03-00 | C70: 2024 | D70: Mei | E70: Penyediaan Nomor akses 1500933 PT Supra Primatama Nusantara 2024 | F70: Nomor Akses | G70: CRM 1 | H70: RNO | I70: 208460000 | J70: Private | K70: C | L70: Fadel Bahruraji | M70: 45418 | N70: 45448 | O70: Gugum | P70: Done
A71: 70 | B71: P242769-02-00 | C71: 2024 | D71: Mei | E71: Layanan Call Center Bapenda Jabar Tahun 2024 | F71: CRM | G71: CRM 2 | H71: PGP | I71: 2354774775 | J71: SME & GOV | K71: B | L71: Chyntia Insani Dewi | M71: 45420 | N71: 45523 | O71: Duta | P71: Done
A72: 71 | B72: P242891-01-00 | C72: 2024 | D72: Mei | E72: (PNTL) Pekerjaan Pendukung Sales (Fulfillment) Periode April 2024 s/d Maret 2025 | F72: CRM | G72: CRM 2 | H72: EWI | I72: 37602672060 | J72: Telkom Group | K72: B | L72: Ipik Mimbo Busono | M72: 45422 | N72: 45469 | O72: Adi | P72: Done
A73: 72 | B73: P242912-01-00 | C73: 2024 | D73: Mei | E73: Layanan Call Center 14002 Bank Sumut April 2024 - Maret 2027 | F73: CRM | G73: CRM 2 | H73: RGZ | I73: 6150061800 | J73: SME & GOV | K73: B | L73: Kartika Alvianty Aziz | M73: 45425 | N73: 45457 | O73: Duta | P73: Done
A74: 73 | B74: P242916-00-00 | C74: 2024 | D74: Mei | E74: Masking Number Outbond PT Super Bank Indonesia 2024 | F74: Nomor Akses | G74: CRM 1 | H74: RSA | I74: 29000000 | J74: Private | K74: C | L74: Fadhli Fauzi | M74: 45425 | N74: 45443 | O74: Gugum | P74: Done
A75: 74 | B75: P242736-05-00 | C75: 2024 | D75: Mei | E75: [PNTL] SPGDT 119 Dinas Kesehatan Kota Bandung Tahun 2024 | F75: CRM | G75: CRM 1 | H75: YNR | I75: 1480840944 | J75: SME & GOV | K75: C | L75: Chyntia Insani Dewi | M75: 45426 | N75: 45447 | O75: Adi | P75: Done
A76: 75 | B76: P242824-01-00 | C76: 2024 | D76: Mei | E76: Layanan Halo BCA - Inbound Semarang | F76: CRM | G76: CRM 1 | H76: RZS | I76: 9277618000 | J76: Private | K76: C | L76: Ika Nursari | M76: 45430 | N76: 45446 | O76: Dwi | P76: Done
A77: 76 | B77: P242941-01-00 | C77: 2024 | D77: Mei | E77: Masking Number Nomor Akses 1500818 PT EKA MAS REPUBLIK (My Republik) | F77: Nomor Akses | G77: SSO | H77: FAH | I77: 21000000 | J77: Private | K77: C | L77: Fadel Bahruraji | M77: 45432 | N77: 45462 | O77: Gugum | P77: Done
... A95: 94 | B95: P242728-04-00 | C95: 2024 | D95: Juli | E95: Rebranding IVR Bank KB Bukopin | F95: CRM | G95: CRM 2 | H95: ARY | I95: 95000000 | J95: Private | K95: C | L95: Ika Nursari | M95: 45488 | N95: 45530 | O95: Dwi | P95: Done
A96: 95 | B96: P232477-06-00 | C96: 2024 | D96: Juli | E96: Novasi Nomor Akses 1500600 PizzaHut | F96: Nomor Akses | G96: SSO | H96: FAH | I96: 347120000 | J96: Private | K96: C | L96: Yane Anastasia | M96: 45490 | N96: 45520 | O96: Gugum | P96: cancel | U96: terkendala pr crossconnect di dc sigma
A97: 96 | B97: P243087-01-00 | C97: 2024 | D97: Juli | E97: Layanan Omnix dan Whatsapp Business BPD Kalimantan Selatan 2024-2025 | F97: CRM | G97: CRM 1 | H97: RZS | I97: 133600000 | J97: SME & GOV | K97: C | L97: Rachmat Hidayat | M97: 45496 | N97: 45537 | O97: Duta | P97: Done
A98: 97 | B98: P242993-04-00 | C98: 2024 | D98: Juli | E98: Penambahan Masking outbound & nomor akses 1500-654 PNM Tahap 1 | F98: Nomor Akses | G98: CRM 2 | H98: ARY | I98: 109400000 | J98: SOE | K98: C | L98: Rahmatya Dwi Arini Rahadina | M98: 45497 | N98: 45526 | O98: Gugum | P98: Done
A99: 98 | B99: P242904-03-00 | C99: 2024 | D99: Juli | E99: Penyediaan Layanan Call Center SPGDT 119 RSUD Aji Muhammad Parikesit Kab. Kukar 2024 | F99: CRM | G99: CRM 1 | H99: YNR | I99: 97000000 | J99: SME & GOV | K99: C | L99: Taufiq Abdurrahman Hanif | M99: 45498 | N99: 45530 | O99: Duta | P99: Done
A100: 99 | B100: P243122-02-00 | C100: 2024 | D100: Juli | E100: Nomor Akses 150-109 dan 1500-109 PT Patra Logistik | F100: Nomor Akses | G100: SSO | H100: FAH | I100: 202000000 | J100: SOE | K100: C | L100: Ibnu Pradipta | M100: 45502 | N100: 45532 | O100: Gugum | P100: Done
A101: 100 | B101: P242804-01-00 | C101: 2024 | D101: Juli | E101: Pengadaan Manage Operation Call Center Outbound PT Pesonna Optima Jasa Tahun 2024 | F101: Nomor Akses | G101: CRM 1 | H101: RSA | I101: 1052926126 | J101: SOE | K101: B | L101: Eko Winaryo | M101: 45503 | N101: 45553 | O101: Dwi | P101: Done
A102: 101 | B102: P242604-03-00 | C102: 2024 | D102: Agustus | E102: Sewa Nomor Akses Call Center dan Waba Dishub Kota Semarang 2024 | F102: CRM | G102: CRM 1 | H102: RZS | I102: 160480000 | J102: SME & GOV | K102: C | L102: Bagus Afiansah | M102: 45506 | N102: 45537 | O102: Duta | P102: Done
A103: 102 | B103: P243154-02-00 | C103: 2024 | D103: Agustus | E103: Masking Outbound 1500-111 & 1500-399 Bank Permata | F103: Nomor Akses | G103: CRM 1 | H103: RSA | I103: 228000000 | J103: Private | K103: C | L103: Fadhli Fauzi | M103: 45509 | N103: 45537 | O103: Gugum | P103: Done
A104: 103 | B104: P243014-05-00 | C104: 2024 | D104: Agustus | E104: Amandemen ke-4 Pekerjaan Jasa Pengadaan dan Pengelolaan Customer Care Center 135 | F104: CRM | G104: CRM 2 | H104: MIH | I104: 19030000000 | J104: SOE | K104: B | L104: Eko Kurniawan | M104: 45511 | N104: 45548 | O104: Duta | P104: Done
A105: 104 | B105: P243160-01-00 | C105: 2024 | D105: Agustus | E105: Layanan Nomor Akses 1500665 Bank Pembangunan Daerah Jambi 2024 | F105: Nomor Akses | G105: CRM 1 | H105: PGP | I105: 137830000 | J105: SME & GOV | K105: C | L105: Kartika Alvianty Aziz | M105: 45511 | N105: 45537 | O105: Gugum | P105: Done
A106: 105 | B106: P243086-02-00 | C106: 2024 | D106: Agustus | E106: Perpanjangan Asuransi Allianz Life Indonesia - Outbound Call (AZLI) 2024 | F106: CRM | G106: SSO | H106: INW | I106: 11742768000 | J106: Private | K106: B | L106: Agung Rizqie Adhi | M106: 45516 | N106: 45541 | O106: Dwi | P106: Done
A107: 106 | B107: P243085-03-00 | C107: 2024 | D107: Agustus | E107: Perpanjangan Asuransi Allianz Life Syariah Indonesia - Outbound Call (ALLISYA) 2024 | F107: CRM | G107: SSO | H107: INW | I107: 5632776000 | J107: Private | K107: C | L107: Agung Rizqie Adhi | M107: 45516 | N107: 45541 | O107: Dwi | P107: Done
A108: 107 | B108: P243107-02-00 | C108: 2024 | D108: Agustus | E108: Novasi Nomor Akses 1500020 PT Jasa Raharja (Persero) | F108: Nomor Akses | G108: CRM 1 | H108: YNR | I108: 70500000 | J108: SOE | K108: C | L108: Eko Winaryo | M108: 45516 | N108: 45544 | O108: Gugum | P108: Done
... A123: 122 | B123: P232189-02-00 | C123: 2024 | D123: September | E123: Layanan SPGDT 119 Kabupaten Subang Tahun 2024 | F123: CRM | G123: CRM 1 | H123: YNR | I123: 63063063 | J123: SME & GOV | K123: C | L123: Fuzi Ridwan Firdaus | M123: 45552 | N123: 45583 | O123: Duta | P123: Done
A124: 123 | B124: P243165-02-00 | C124: 2024 | D124: September | E124: Nomor Akses Nasabah Prioritas BRI Life 1500518 | G124: CRM 1 | H124: RZS | I124: 112000000 | J124: SOE | K124: C | L124: Rahmatya Dwi Arini Rahadina | M124: 45558 | N124: 45583 | O124: Gugum | P124: Done
A125: 124 | B125: P243136-01-00 | C125: 2024 | D125: September | E125: Nomor Akses 1500780 PT Cyberindo Aditama | F125: Nomor Akses | G125: CRM 1 | H125: AGM | I125: 131400000 | J125: Private | K125: C | L125: Fadel Bahruraji | M125: 45561 | N125: 45593 | O125: Gugum | P125: Done
A126: 125 | B126: P243210-01-00 | C126: 2024 | D126: Oktober | E126: Layanan Contact Center dan E-Pelaporan Otorita Ibu Kota Nusantara 2024 | F126: CRM | G126: CRM 1 | H126: FT | I126: 145200000 | J126: SME & GOV | K126: C | L126: Alldicka Christvelldy | M126: 45566 | N126: 45595 | O126: Dwi | P126: Done
A127: 126 | B127: P243255-01-00 | C127: 2024 | D127: Oktober | E127: Pengadaan Penyediaan Infrastruktur Komunikasi Untuk Call Center EV Ecossystem Periode 2024 PT Haleyora Power | F127: CRM | G127: CRM 2 | H127: PPP | I127: 431000000 | J127: SOE | K127: C | L127: Eko Kurniawan | M127: 45568 | N127: 45595 | O127: Duta | P127: Done
A128: 127 | B128: P243283-01-00 | C128: 2024 | D128: Oktober | E128: Perpanjangan Nomor Akses 1500918 PT Kartika Bina Medika | F128: Nomor Akses | G128: CRM 1 | H128: YNR | I128: 179480000 | J128: Private | K128: C | L128: Rocky Herwindo | M128: 45572 | N128: 45600 | O128: Gugum | P128: Done
A129: 128 | B129: P243175-00-00 | C129: 2024 | D129: Oktober | E129: Perpanjangan Layanan Nomor Akses 1500332 PT MRT Jakarta 2024-2025 | F129: Nomor Akses | G129: CRM 1 | H129: PGP | I129: 148500000 | J129: SME & GOV | K129: C | L129: Rachmat Hidayat | M129: 45572 | N129: 45597 | O129: Gugum | P129: Done
A130: 129 | B130: P243291-02-00 | C130: 2024 | D130: Oktober | E130: Upgrade Omni Channel Bank Jatim Tahun 2024-2025 | F130: CRM | G130: CRM 2 | H130: ARY | I130: 1155000000 | J130: SME & GOV | K130: B | L130: Rizkina Pascawati | M130: 45574 | N130: 45649 | O130: Duta | P130: Done
A131: 130 | B131: P243225-05-00 | C131: 2024 | D131: Oktober | E131: CONTACT CENTER RSUP NGOERAH BALI | F131: CRM | G131: CRM 2 | H131: RGZ | I131: 556000000 | J131: SME & GOV | K131: C | L131: Rizkina Pascawati | M131: 45574 | N131: 45596 | O131: Duta | P131: Done
A132: 131 | B132: P243240-01-00 | C132: 2024 | D132: Oktober | E132: Pengadaan Call center 150280 PT Suiten Inovasi Sukses | F132: CRM | G132: SSO | H132: BTG | I132: 99140000 | J132: Private | K132: C | L132: Fadel Bahruraji | M132: 45575 | N132: 45603 | O132: Dwi | P132: Done
A133: 132 | B133: P243337-01-00 | C133: 2024 | D133: Oktober | E133: Amandemen V Penambahan Jasa Pengadaan & Pengelolaan Costumer Care Center 135 Bandung & Semarang | F133: CRM | G133: CRM 2 | H133: MIH | I133: 29222550763 | J133: SOE | K133: B | L133: Eko Kurniawan | M133: 45583 | N133: 45681 | O133: Dwi | P133: Done | U133: Upload Astinetnya masih blm sesuai dengan Download (100 Mbps) masih FU ke Grey
A134: 133 | B134: P243378-02-00 | C134: 2024 | D134: Oktober | E134: Telemarketing Allo Bank 2024 | F134: CRM | G134: CRM 2 | H134: PPP | I134: 200750600 | J134: Private | K134: C | L134: Ika Nursari | M134: 45592 | N134: 45609 | O134: Dwi | P134: Done
A135: 134 | B135: P243327-02-00 | C135: 2024 | D135: Oktober | E135: Pengadaan Jasa Call Center PT Adhi Karya 2024 | F135: CRM | G135: SSO | H135: INW | I135: 220000000 | J135: SOE | K135: B | L135: Marulitua Sikristo Sitorus | M135: 45594 | N135: 45616 | O135: Duta | P135: Done
A136: 135 | B136: P243282-02-00 | C136: 2024 | D136: November | E136: New Network Number Access 1500-275 Anugerah Pharmindo Lestari (APL) | F136: Nomor Akses | G136: CRM 1 | H136: RZS | I136: 608284000 | J136: Private | K136: C | L136: Fadel Bahruraji | M136: 45597 | N136: 45628 | O136: Dwi | P136: Done
A137: 136 | B137: P243357-01-00 | C137: 2024 | D137: November | E137: Novasi 1500153 Bank Sinarmas | F137: Nomor Akses | G137: SSO | H137: RMT | I137: 513920000 | J137: Private | K137: C | L137: Yane Anastasia | M137: 45601 | N137: 45639 | O137: Gugum | P137: Done
A138: 137 | B138: P243402-02-00 | C138: 2024 | D138: November | E138: Pekerjaan Full Managed Service Contact Center ASDP 191 Tahun 2024-2025 | F138: CRM | G138: CRM 2 | H138: RGZ | I138: 4286742054 | J138: SOE | K138: B | L138: ARTHA | M138: 45611 | N138: 45677 | O138: Dwi | P138: Done
A139: 138 | B139: P243405-02-00 | C139: 2024 | D139: November | E139: Layanan Call Center 1500838 PT KITB | F139: CRM | G139: CRM 1 | H139: RZS | I139: 190400000 | J139: SME & GOV | K139: C | L139: RIZKINA PASCAWATI | M139: 45614 | N139: 45646 | O139: Duta | P139: Done
A140: 139 | B140: NO GPL | C140: 2024 | E140: Perubahan Menu NCC 119 Menu Konsultasi Tekan 8 (Psikolog) | I140: 0 | J140: SME & GOV | K140: - | O140: Duta | P140: Done
A141: 140 | B141: NO GPL | C141: 2024 | E141: Layanan Call Center Garuda Australia | I141: 0 | J141: SOE | K141: - | O141: Dwi | P141: Done
A142: 141 | B142: NO GPL | C142: 2024 | E142: Penambahan Priority Platinum pada Layanan Indihome | I142: 0 | J142: Telkom Group | K142: - | O142: Adi | P142: Done
A143: 142 | B143: NO GPL | C143: 2024 | E143: POC - TPNS Telesurvey Indihome | I143: 0 | J143: Telkom Group | K143: - | O143: Adi | P143: Done
A144: 143 | B144: P243414-01-00 | C144: 2024 | D144: November | E144: Sewa Layanan Inbound Call Nomor Akses 167 | F144: Nomor Akses | G144: CRM 1 | H144: RSA | I144: 19300000 | J144: SME & GOV | K144: C | L144: Alldicka Christvelldy | M144: 45618 | N144: 45613 | O144: Duta | P144: Done
A145: 144 | B145: P243407-01-00 | C145: 2024 | D145: November | E145: Layanan Pekerjaan Upgrade Sistem Omnix CC PGN 2 Bulan | F145: CRM | G145: CRM 1 | H145: AGM | I145: 183580000 | J145: SOE | K145: C | L145: Rahmatya Dwi Arini | M145: 45616 | N145: 20-Des-24 | O145: Duta | P145: Done
A146: 145 | B146: P243390-01-00 | C146: 2024 | D146: Desember | E146: POC Backup Asteriks PT Admedika | F146: CRM | G146: CRM 1 | H146: YNR | J146: Telkom Group | K146: C | L146: Siska Susiloawti | M146: 45618 | N146: 45607 | O146: Duta | P146: Done
A147: 146 | B147: P243355-02-00 | C147: 2024 | D147: November | E147: Penyediaan SBC Layanan Zurich 1500456 | F147: Nomor Akses | G147: SSO | H147: GIN | I147: 237000000 | J147: Private | K147: C | L147: Yane Anastasia | N147: 23-Des-24 | O147: adi | P147: Done
A148: 147 | B148: P243363-02-00 | C148: 2024 | D148: Desember | E148: New Nomor Akses 1500215 PT Pembangunan Deltamas Gedung SFCC | F148: Nomor Akses | G148: SSO | H148: BTG | I148: 97800000 | J148: Private | K148: C | L148: Yane Anastasia | M148: 45631 | N148: 45674 | O148: Gugum | P148: Done | U148: Terkendala di Kawasan Area Deltamas
A149: 148 | B149: P242867-04-00 | C149: 2024 | D149: Desember | E149: Pengadaan Manage Service B2B Aftersales Tahun 2024 | F149: CRM | G149: CRM 1 | H149: PGP | I149: 28189435484 | J149: TELKOM GROUP | K149: B | L149: Indra Gunawan | M149: 45383 | N149: 45663 | O149: Dwi | P149: Done
A150: 149 | B150: P243357-01-00 | C150: 2024 | D150: Desember | E150: Novasi 1500153 Bank Sinarmas | F150: CRM | G150: CRM4 | H150: Erik | I150: 513920000 | J150: Private | K150: C | L150: Yane Anastasia | M150: 45597 | N150: 45639 | O150: Gugum | P150: Done
A151: 150 | B151: P243402-02-00 | C151: 2024 | D151: Desember | E151: Pekerjaan Full Managed Service Contact Center ASDP 191 Tahun 2024-2025 | F151: CRM | G151: CRM2 | H151: RGZ | I151: 4068080609 | J151: SOE | K151: B | L151: ARTHA | M151: 45626 | N151: 45677 | O151: Dwi | P151: Done
A152: 151 | B152: P243449-01-00 | C152: 2024 | D152: Desember | E152: Layanan Call Center 119 Dinas Kesehatan Kabupaten Pandeglang | F152: CRM | G152: CRM 1 | H152: AGM | I152: 150000000 | J152: SME & GOV | K152: C | L152: Ricka Winatha | M152: 12-Des-2024 | N152: 45658 | O152: Duta | P152: Done
A153: 152 | B153: P243440-02-00 | C153: 2024 | D153: Desember | E153: Penyediaan Layanan Call Center RS Awal Bros Pekanbaru Tahun 2024 | F153: CRM | G153: CRM 1 | H153: YNR | I153: 256400000 | J153: SME & GOV | K153: C | L153: Kartika Alvianty | M153: 45633 | N153: 45681 | O153: Duta | P153: Done
A154: 153 | B154: P243375-02-00 | C154: 2025 | D154: Januari | E154: Pengadaan Layanan Seat Management Contact Center PT Citilink Indonesia Tahun 2025 sd 2028 | F154: CRM | G154: SSO | H154: ERW | I154: 24031205935 | K154: B | L154: ADIRIA | M154: 45658 | N154: 45709 | O154: Adi | P154: Done
A155: 154 | B155: P243615-01-00 | C155: 2025 | D155: Januari | E155: Layanan Nomor Akses 1500300 Bank BTPN Syariah | F155: Nomor Akses | G155: SSO | H155: ERM | I155: 521840000 | J155: Private | K155: C | L155: Fadhli Fauzi | M155: 45658 | N155: 45705 | O155: Gugum | P155: Done | U155: Proses Intergrasi disisi BTPN
A156: 155 | B156: P253703-01-00 | C156: 2025 | D156: Januari | E156: Penyediaan SIP Trunk dan Nomor Akses KPPPA Tesa 129 TA 2025 | F156: Nomor Akses | G156: CRM2 | H156: PPP | I156: 379283036 | J156: SME & GOV | K156: C | L156: Kristie Silviana | M156: 45658 | N156: 45702 | O156: Dwi | P156: Done
A157: 156 | B157: P243658-01-00 | C157: 2025 | D157: Januari | E157: Manage Service Operasional CC AHU 2025 | F157: CRM | G157: CRM1 | H157: AGM | I157: 11790144348 | J157: SME & GOV | K157: B | L157: Alldicka ChristVelldy | M157: 45659 | N157: 25-Feb-2-25 | O157: Duta | P157: Done | U157: Proses Downgrade Astinet & Dismentle Metro blm ada no Order dari DWS
A158: 157 | B158: P243549-01-00 | C158: 2025 | D158: Januari | E158: Jasa Layanan Contact Center Kementerian Investasi (BKPM) Tahun 2025 | F158: CRM | G158: CRM1 | H158: AGM | I158: 7240153998 | J158: SME & GOV | K158: B | L158: Akhmad Yani | M158: 45659 | N158: 45691 | O158: Dwi | P158: Done
A159: 158 | B159: F243613-01-00 | C159: 2025 | D159: Januari | E159: Pra PO Layanan Contact Center Kemendiktisaintek TA 2025 | F159: CRM | G159: CRM1 | H159: RZS | I159: 3351133148 | J159: SME & GOV | K159: B | L159: Akhmad Yani | M159: 45658 | N159: 45716 | O159: Gugum | P159: Done
A160: 159 | B160: P243572-03-00 | C160: 2025 | D160: Januari | E160: Nomor Akses dan Platform Omnix LAPS SJK | F160: CRM | G160: CRM1 | H160: RSA | I160: 149000000 | J160: Private | K160: C | L160: Fadhli Fauzi | M160: 45659 | N160: 45709 | O160: Gugum | P160: Done
A161: 160 | B161: P243574-01-00 | C161: 2025 | D161: Januari | E161: Perpanjangan Layanan Contact Center Starbucks untuk PT Sari Coffe Indonesia periode 1 Jan 2025 - 31 Des 2025 | F161: CRM | G161: CRM1 | H161: YNR | I161: 67800000 | J161: Private | K161: C | L161: Yane Anastasia | M161: 45660 | N161: 45688 | O161: Duta | P161: Done
A162: 161 | B162: P243447-02-00 | C162: 2025 | D162: Januari | E162: Layanan Contact Center Allo Fresh Indonesia | F162: CRM | G162: CRM2 | H162: ARY | I162: 829639004 | J162: Private | K162: B | L162: Ika Nursari | M162: 45653 | N162: 45686 | O162: Dwi | P162: Done
A163: 162 | B163: P243439-00-00 | C163: 2025 | D163: Januari | E163: Novasi Nomor Akses 1500-336 PT Shinhan Indo Finance | F163: Nomor Akses | G163: CRM2 | H163: ARY | I163: 99500000 | J163: Private | K163: C | L163: Fadel Bahruaji | M163: 45646 | N163: 45695 | O163: Duta | P163: Done | S163: OGP | U163: Terkendala di SBC CLient
A164: 163 | B164: P243450-02-00 | C164: 2025 | D164: Januari | E164: Migrasi Layanan No Akses 150225 Direktorat Jenderal Bea dan Cukai 2024 | F164: Nomor Akses | G164: SSO | H164: BTG | I164: 9009000 | J164: SME & GOV | K164: C | L164: Alldicka ChristVelldy | M164: 45642 | N164: 45691 | O164: Gugum | P164: done | U164: Proses Order di SP
A165: 164 | B165: P243588-02-00 | C165: 2025 | D165: Januari | E165: Layanan Call Center SPGDT 119 Dinkes Kabupaten Bandung Barat 2025 | F165: CRM | G165: CRM2 | H165: RGZ | I165: 491520000 | J165: SME & GOV | K165: C | L165: Fuzi Ridwan | M165: 45665 | N165: 45702 | O165: Duta | P165: Done
A166: 165 | B166: P243579-01-00 | C166: 2025 | D166: Januari | E166: Pengadaan Connectivity dan Trainning Agent untuk CC JR dengan PT Aru Raharja | F166: Nomor Akses | G166: CRM4 | H166: SDQ | I166: 89100000 | J166: SOE | K166: C | L166: Rahmatya Dwi Arini | M166: 45670 | N166: 45695 | O166: Duta | P166: Done
A167: 166 | B167: P243535-02-00 | C167: 2025 | D167: Januari | E167: Layanan Nomor Akses Perumda Tirta Benteng Kota Tangerang | F167: Nomor Akses | G167: CRM4 | H167: SDQ | I167: 108000000 | J167: SME & GOV | K167: C | L167: Ricka Winatha | M167: 45670 | N167: 45715 | O167: Duta | P167: Done
A168: 167 | B168: P243609-02-00 | C168: 2025 | D168: Januari | E168: Nomor Akses dan Caller ID 1500900 BBKK Tanjung Priok | F168: Nomor Akses | G168: CRM4 | H168: RSA | I168: 80000000 | J168: SME & GOV | K168: C | L168: Eko Winaryo | M168: 45670 | N168: 45707 | O168: Gugum | P168: Done
A169: 168 | B169: P243616-02-00 | C169: 2025 | D169: Januari | E169: Layanan Call Center NOC PT KITB | F169: Nomor Akses | G169: CRM4 | H169: MIH | I169: 148200000 | J169: SME & GOV | K169: C | L169: Rizkina Pancawati | M169: 45670 | N169: 45705 | O169: Duta | P169: Done
A170: 169 | B170: P243429-02-00 | C170: 2025 | D170: Januari | E170: Manage Service CC Bank Ganesha 2025-2026 | F170: CRM | G170: CRM1 | H170: PPP | I170: 1792298000 | J170: Private | K170: C | L170: Fadhli Fauzi | M170: 45659 | N170: 45687 | O170: Duta | P170: Done
A171: 170 | B171: F253743-02-00 | C171: 2025 | D171: Januari | E171: TELEPHONY SISTEM RSUP KEMENKES SURABAYA | F171: Nomor Akses | G171: CRM4 | H171: SDQ | I171: 142980000 | J171: SME & GOV | K171: C | L171: RIZKINA PASCAWATI | M171: 45678 | N171: 45713 | O171: Gugum | P171: Done | U171: Perubahan no Out 031
A172: 171 | B172: P243642-02-00 | C172: 2025 | D172: Januari | E172: Upgrade Call Center Bank Jatim Tahun 2025 dan 2026 | F172: CRM | G172: CRM1 | H172: ARY | I172: 3675676008 | J172: SME & GOV | K172: B | L172: RIZKINA PASCAWATI | M172: 45673 | N172: 45720 | O172: Dwi | P172: Done
A173: 172 | B173: P243682-01-00_x000D_ | C173: 2025 | D173: Januari | E173: Perpanjangan Nomor Akses Koperasi Nusantara Periode 2025 | F173: CRM | G173: CRM1 | H173: RGZ | I173: 161346000 | J173: SME & GOV | K173: C | L173: Masagus Mansyur | M173: 45665 | N173: 45705 | O173: Duta | P173: Done
A174: 173 | B174: P243497-02-00 | C174: 2025 | D174: Februari | E174: Pengadaan Jasa Pengelolaan Customer Care SIG Department Channel & Sales Force Management Tahun 2025 | F174: CRM | G174: CRM4 | H174: MIH | I174: 1300000000 | J174: SOE | K174: B | L174: Adiria | M174: 45658 | N174: 45723 | O174: Dwi | P174: Done
A175: 174 | B175: P253733-01-00 | C175: 2025 | D175: Februari | E175: Pengadaan Layanan Whatsapp Untuk Omnichannel Kontak Terpadu HCM 2025 | F175: CRM | G175: CRM2 | H175: RZS | I175: 50000001 | J175: Telkom Group | K175: B | L175: Roni Gultom | M175: 45683 | N175: 45695 | O175: Duta | P175: Done
A176: 175 | B176: P243565-02-00 | C176: 2025 | D176: Februari | E176: Layanan Contact Center Kemenhub TA 2025 | F176: CRM | G176: CRM1 | H176: PPP
A177: 176 | B177: P243544-02-00 | C177: 2025 | D177: Februari | E177: Penyediaan Nomor Akses 1500199 PT Nusa Prima Pangan (Solaria) | F177: Nomor Akses | G177: CRM2 | H177: YNR | I177: 85000000 | J177: Private | K177: C | L177: Gerry Sunaryo | M177: 45658 | N177: 45741 | O177: Duta | P177: Done
...

Sheet List Order
A1: NO | B1: Periode | C1: Tahun | D1: Tanggal | E1: Order | F1: DASAR ORDER | G1: NO SURAT MODIN | H1: JENIS ORDER | I1: KLASIFIKASI ORDER | J1: PROVIDER | K1: AKHIR KONTRAK | L1: SISA KONTRAK | M1: NO ORDER | N1: SID 1 | O1: SID 2 | P1: IP Address | Q1: KETERANGAN | R1: STATUS | S1: Task | T1: harga | U1: NO BA | V1: TGL BA | W1: File BA
B2: September | C2: 2022 | D2: 44825 | E2: Permohonan percepatan aktivasi 150410 Layanan Bapenda JABAR | H2: Aktivasi | I2: Nomor Akses | J2: Telkom DWS | M2: 2-1789696190 | N2: 888337522249 | R2: Close | V2: 44827 | W2: file
B3: Juni | C3: 2023 | D3: 45090 | E3: Permohonan Aktivasi Astinet Dana di Site Infomedia | H3: Aktivasi | I3: Connectivity | J3: Telkom DWS | M3: 2-1994394079 | N3: 1758576065 | R3: Close | V3: 45111 | W3: file
B4: Juni | C4: 2023 | D4: 45097 | E4: Permohonan link backup metro dan backup internet Graha intan Jogya beda catuan odp | H4: Aktivasi | I4: Connectivity | J4: Telkom DWS | M4: 2-1996205782 | N4: 1761505393 | R4: Close | V4: 45117 | W4: file
B5: Juni | C5: 2023 | D5: 45097 | E5: Permohonan link backup metro dan backup internet Graha intan Jogya beda catuan odp | H5: Aktivasi | I5: Connectivity | J5: Telkom DWS | M5: 2-1996201116 | N5: 1758506619 | O5: 1761507764 | R5: Close | V5: 45117 | W5: file
B6: Juni | C6: 2023 | D6: 45103 | E6: Permohonan Aktivasi Astinet 1 Mbps Layanan Asabri | H6: Aktivasi | I6: Connectivity | J6: Telkom DWS | M6: 2-2002211739 | N6: 1763316563 | R6: Close | V6: 45120 | W6: file
B7: Juli | C7: 2023 | D7: 45110 | E7: Permohonan link Metro p2p 4 mbps interactive DC Infomedia Dan DC Cyber Apjii PT Persada Makmur Indonesia | H7: Aktivasi | I7: Connectivity | J7: Telkom DWS | M7: 2-2003014759 | N7: 1761375294 | O7: 1761162396 | R7: Close | V7: 45117 | W7: file
B8: Juli | C8: 2023 | D8: 45114 | E8: Permohonan Aktivasi Astinet 10 Mbps Layanan BJB | H8: Aktivasi | I8: Connectivity | J8: Telkom DWS | M8: 2-1994372762 | N8: 1758421735 | R8: Close | V8: 45100 | W8: file
B9: Juli | C9: 2023 | D9: 45117 | E9: Permohonan Novasi (Perubahan Nomor Translasi , Nomor Billing dan Channel Berlangganan) Nomor Akses 1500310 PT Zulu Alpha Papa (ZAP) | H9: Novasi | I9: Nomor Akses | J9: Telkom DWS | M9: 2-2006902048 | N9: 3700038-0028505709 | R9: Close | V9: 45121 | W9: file
B10: Desember | C10: 2023 | D10: 45278 | E10: Permohonan PSB Link Metro E Interaktif 2 Mbps dan Masking Outbound 1500989 PT Astra Honda Motor | F10: P232338-03-00 | H10: Aktivasi | I10: Connectivity | J10: Telkom DWS | M10: 2-2122341809 | N10: 1927800876 | O10: 1915062978 | R10: Close | V10: 45349 | W10: file
B11: Desember | C11: 2023 | D11: 45222 | E11: Permohonan PSB link Metro E BRI Ragunan To DC Infomedia Jatinegara | H11: Aktivasi | I11: Connectivity | J11: Telkom DWS | M11: 2-2075528687 | N11: 1787711454 | O11: 1788693609 | R11: Close | V11: 45222 | W11: file
B12: Desember | C12: 2023 | D12: 45267 | E12: Astinet Seamless Tendean | H12: Aktivasi | I12: Connectivity | J12: Telkom DWS | M12: 2-2106897759 | N12: 1883036085 | R12: Close | V12: 45267 | W12: file
A13: 7 | B13: Januari | C13: 2024 | D13: 45300 | E13: Aktivasi Nomor Akses 144 Layanan LKPP | F13: P232385-03-00 | G13: 00020/IN/INF2340122/24 | H13: Aktivasi | I13: Nomor Akses | J13: Telkom DWS | M13: 7000153184 | N13: 3700038-0028304160 | R13: Close | T13: 2500000 | U13: No 64 /YN 000/DR2–11220000/2024 | V13: 45293
A14: 10 | B14: Januari | C14: 2024 | D14: 45302 | E14: Aktivasi Nomor Akses 152 Layanan DJKI | F14: P232558-03-00 | G14: 00025/IN/INF2340122/24 | H14: Aktivasi | I14: Nomor Akses | J14: Telkom DWS | M14: 2-2129927421 | N14: 888389899665 | R14: Close | T14: 2500000 | U14: No: 807/YN 000/DR2–11220000/2024 | V14: 45324
A15: 25 | B15: Januari | C15: 2024 | D15: 45315 | E15: Aktivasi Masking Outbond 1500907 PT Affinity Health Indonesia | F15: P232267-03-00 | G15: 00054/IN/INF2340122/24 | H15: Aktivasi | I15: Nomor Akses | J15: Telkom DWS | M15: 2-2140073973 | N15: 888391471517 | R15: Close | T15: 580000 | U15: No: 812/YN 000/DR2–11220000/2024 | V15: 45324
A16: 30 | B16: Februari | C16: 2024 | D16: 45323 | E16: Aktivasi Nomor Akses 1500882 PT Mora Telematik Indonesia (MORATELINDO) | F16: P232120-01-00 | G16: 00068/IN/INF2340122/24 | H16: Aktivasi | I16: Nomor Akses | J16: Telkom DWS | M16: 2-2143307693 | N16: 888392001897 | R16: Close | T16: 2500000 | U16: No 1092 /YN 000/DR2–11220000/2024 | V16: 45327 | W16: file
A17: 33 | B17: Februari | C17: 2024 | D17: 45323 | E17: aktivasi Masking Nomor Akses 1500275 PT. Anugerah Pharmindo Lestari | F17: P232486-02-00 | G17: 00071/IN/INF2340122/24 | H17: Aktivasi | I17: Nomor Akses | J17: Telkom DWS | M17: 2-2143644304 | N17: 3700038-0029465223 | R17: Close | T17: 580000 | U17: No: 957/YN 000/DR2–11220000/2024 | V17: 45324
A18: 34 | B18: Februari | C18: 2024 | D18: 45323 | E18: Penambahan Nomor Masking Outbound Bank Syariah Indonesia | F18: P242580-02-00 | G18: 00073/IN/INF2340122/24 | H18: Aktivasi | I18: Nomor Akses | J18: Telkom DWS | M18: Masking : 2-2143315186 | N18: 3700038-45259 | R18: Close | T18: 580000 | U18: No 837/YN 000/DR2–11220000/2024 | V18: 45328
A19: 43 | B19: Februari | C19: 2024 | D19: 45341 | E19: Aktivasi Nomor Akses 1500019 Layanan RSIA Cikampek | F19: P232471-04-00 | G19: 00010/IN/INF2430233/24 | H19: Aktivasi | I19: Nomor Akses | J19: Telkom DWS | M19: 2-2149111663 | R19: Close | T19: 2500000 | U19: No 1167/YN 000/DR2–11220000/2024 | V19: 45343 | W19: file
A20: 45 | B20: Februari | C20: 2024 | D20: 45345 | E20: Aktivasi Nomor Akses 150707 Bank India | F20: P232266-01-00 | G20: 00017/IN/INF2430233/24 | H20: Aktivasi | I20: Nomor Akses | J20: Telkom DWS | M20: 2-2153037541 | N20: 888393977136 | R20: Close | T20: 2500000 | U20: No 1377/YN 000/DR2–11220000/2024 | V20: 45349 | W20: file
A21: 57 | B21: Maret | C21: 2024 | D21: 45365 | E21: Aktivasi Nomor Akses 1500211 Layanan BPRKS | F21: P242674-02-00 | G21: 00057/IN/INF2430233/24 | H21: Aktivasi | I21: Nomor Akses | J21: Telkom DWS | M21: 2-2161131461 | R21: Close | T21: 3080000 | W21: file
A22: 59 | B22: Maret | C22: 2024 | D22: 45369 | E22: Aktivasi Nomor Akses 1500598 Adhivasindo | F22: P242716-02-00 | G22: 00060/IN/INF2430233/24 | H22: Aktivasi | I22: Nomor Akses | J22: Telkom DWS | M22: 2-2163078394 | N22: 888396223561 | R22: Close | T22: 2500000 | V22: 45373 | W22: file
A23: 66 | B23: Maret | C23: 2024 | D23: 45376 | E23: aktivasi no akses inbound ,masking outbound 1500217 Layanan BRILIfe | F23: P242801–01-00 | G23: 00084/IN/INF2430233/24 | H23: Aktivasi | I23: Nomor Akses | J23: Telkom DWS | M23: 2-2166294501 | N23: 888396879847 | R23: Close | V23: 45378 | W23: file
B24: Maret | C24: 2024 | D24: 45377 | E24: Aktivasi metro bank fama | H24: Aktivasi | I24: Connectivity | J24: Telkom DWS | M24: 2-2166580141 | N24: 1931773524 | R24: Close | V24: 45377 | W24: file
A25: 88 | B25: Mei | C25: 2024 | D25: 45419 | E25: Aktivasi Nomor Akses 150511 Layanan Perumda Tirta Kanjuruhan Kab Malang | F25: P242857-03-00 | G25: 00131/IN/INF2430233/24 | H25: Aktivasi | I25: Nomor Akses | J25: Telkom DWS | M25: 2-2183638455 | R25: Close | U25: No 2087/YN 000/DR2–11220000/2024 | V25: 45425 | W25: file
A26: 92 | B26: Mei | C26: 2024 | D26: 45426 | E26: Masking Outbound Nomor Akses 1500333 Bank Fama (PT Super Bank Indonesia) | F26: P242916-00-00 | G26: 00139/IN/INF2430233/24 | H26: Aktivasi | I26: Nomor Akses | J26: Telkom DWS | M26: 2-2186074350 | Q26: 24CIN10F0046 - IO PT Super Bank Indonesia 2024 | R26: Close | U26: No 2134/YN 000/DR2–11220000/2024 | V26: 45429 | W26: file
A27: 97 | B27: Mei | C27: 2024 | D27: 45428 | E27: Aktivasi dan Masking Outbound Nomor Akses 1500063 PT Persada Makmur Indonesia | F27: 00147/IN/INF2430233/24 | G27: 00147/IN/INF2430233/24 | H27: Aktivasi | I27: Nomor Akses | J27: Telkom DWS | M27: 2-2186095404 | Q27: 24CIN10F0039 - IO CC 1500063 PT Persada Makmur Indonesia | R27: Close | U27: No: 2722/YN 000/DR2–11220000/2024 | V27: 45477 | W27: file
A28: 99 | B28: Mei | C28: 2024 | D28: 45433 | E28: Masking Outbound Nomor Akses 1500818 PT EKA MAS REPUBLIK (My Republik) | F28: P242941-01-00 | G28: 00154/IN/INF2430233/24 | H28: Aktivasi | I28: Nomor Akses | J28: Telkom DWS | M28: 2-2189531833 | Q28: 24CIN10F0049 - IO Masking Number No Akses 1500818 PT EKA MAS REPUBLIK | R28: Close | U28: No 2179/YN 000/DR2–11220000/2024 | V28: 45437 | W28: file
A29: 100 | B29: Mei | C29: 2024 | D29: 45433 | E29: Masking Outbound Nomor Akses 1500045 PT BNI Life Insurance | F29: P242791-02-00 | G29: 00156/IN/INF2430233/24 | H29: Aktivasi | I29: Nomor Akses | J29: Telkom DWS | M29: 2-2189528724 | Q29: 24CIN10F0041-IOCC1500045 PT BNI LIFE | R29: Close | U29: No 2181/YN 000/DR2–11220000/2024 | V29: 45437 | W29: file
A30: 112 | B30: Mei | C30: 2024 | D30: 45443 | E30: Aktivasi Nomor Akses 1500858 Nasmoco Semarang dan Nomor Akses 1500202 RSUP Dr Kariadi (Kariadi) | F30: 00003/M/INF24251/24 | G30: 00174/IN/INF2430233/24 | H30: Aktivasi | I30: Nomor Akses | J30: Telkom DWS | M30: 2-2194853153 | N30: 888272034303 | R30: Close | W30: file
B31: Mei | C31: 2024 | D31: 45443 | E31: Aktivasi Nomor Akses 1500858 Nasmoco Semarang dan Nomor Akses 1500202 RSUP Dr Kariadi (Nasmoco) | F31: 00003/M/INF24251/24 | G31: 00174/IN/INF2430233/24 | H31: Aktivasi | I31: Nomor Akses | J31: Telkom DWS | M31: 2-2194852752 | R31: Close
A32: 117 | B32: Juni | C32: 2024 | D32: 45453 | E32: Permohonan masking outbound 1500250 Layanan Dinas Telkom TENESA | F32: C.Tel.150/UM 000/SDA-D4050000/2024 | G32: 00182/IN/INF2430233/24 | H32: Aktivasi | I32: Nomor Akses | J32: Telkom DWS | M32: 2-2198168939 | N32: 888110631794 | R32: Close | W32: file
A33: 128 | B33: Juni | C33: 2024 | D33: 45457 | E33: Aktivasi Nomor Akses 1500910 PT Bank Hibank Indonesia | H33: Aktivasi | I33: Nomor Akses | J33: Telkom DWS | M33: 2-2200767238
A34: 144 | B34: Juli | C34: 2024 | D34: 45474 | E34: Aktivasi Nomor Akses 1500629 & Aktivasi Astinet PT HISI (Astinet) | F34: P242965-04-00 | G34: 00223/IN/INF2430233/24 | H34: Aktivasi | I34: Nomor Akses | J34: Telkom DWS | M34: 2-2208395513 | W34: file
A35: 149 | B35: Juli | C35: 2024 | D35: 45482 | E35: Permohonan Aktivasi Nomor Akses 1500699 & Masking Outbond 1500699 Mazuta Group | F35: P243026-04-00 | G35: 00235/IN/INF2430233/24 | H35: Aktivasi | I35: Nomor Akses | J35: Telkom DWS | M35: 2-2213657240 | N35: 888100956954 | R35: Close | W35: file
A36: 152 | B36: Juli | C36: 2024 | D36: 45488 | E36: Aktivasi Nomor Akses 150922 RS NGOERAH | F36: P242931-01-00 | G36: 00240/IN/INF2430233/24 | H36: Aktivasi | I36: Nomor Akses | J36: Telkom DWS | M36: 2-2217798861 | N36: 888151721386 | R36: Close | W36: file
A37: 166 | B37: Juli | C37: 2024 | D37: 30/07/2024 | E37: Masking Outbound Nomor Akses 1500654 PT. PERMODALAN NASIONAL MADANI | F37: P242993-04-00 | G37: 00264/IN/INF2430233/24 | H37: Aktivasi | I37: Nomor Akses | J37: Telkom DWS | M37: 2-2229514103
A38: 168 | B38: Juli | C38: 2024 | D38: 31/07/2024 | E38: PSB Link Metro E 8 Mbps dan Masking Outbound Nomor Akses 1500600 Pizza Hut (Masking) | F38: P232477-06-00 | G38: 00268/IN/INF2430233/24 | H38: Aktivasi | I38: Nomor Akses | J38: Telkom DWS | M38: 2-2231200333
A39: 169 | B39: Juli | C39: 2024 | D39: 31/07/2024 | E39: Masking Outbound Nomor Akses 1500569 PEGADAIAN | F39: P242804-01-00 | G39: 00270/IN/INF2430233/24 | H39: Aktivasi | I39: Nomor Akses | J39: Telkom DWS | M39: 2-2231219080
A40: 173 | B40: Agustus | C40: 2024 | D40: 45299 | E40: Aktivasi Nomor Akses 150109 dan 1500109 PT Patra Logistik | F40: P243122-02-00 | G40: 00275/M/INF2430233/24 | H40: Aktivasi | I40: Connectivity | J40: Telkom DWS
A41: 176 | B41: Agustus | C41: 2024 | D41: 45451 | E41: PSB Link Metro E 8 Mbps dan Masking Outbound Nomor Akses 1500111 dan 1500399 a.n Bank Permata (Metro) | F41: P243154-02-00 | G41: 00279/IN/INF2430233/24 | H41: Aktivasi | I41: Connectivity | J41: Telkom DWS | M41: 2-2234226179 | N41: 2022273984 | O41: 2022274007 | R41: Close | W41: file
A42: 180 | B42: Agustus | C42: 2024 | D42: 13/8/2024 | E42: PSB Metro E Interaktif 1 Mbps Dc Jatinegara ke Site Infomedia Sri Ratu Semarang | F42: P242788-01-00 | G42: 00289/IN/INF2430233/2024 | H42: Aktivasi | I42: Connectivity | J42: Telkom DWS | M42: 2-2237950236
A43: 182 | B43: Agustus | C43: 2024 | D43: 14/8/2024 | E43: PSB Metro E Interaktif 3 Mbps DC PAC BPD Jambi ke DC Infomedia Jatinegara | F43: P243160-01-00 | G43: 00292/IN/INF2430233/2024 | H43: Aktivasi | I43: Connectivity | J43: Telkom DWS
A44: 183 | B44: Agustus | C44: 2024 | D44: 15/8/2024 | E44: PSB Link Metro E 1 Mbps BJB Syariah Site Infomedia TBB ke DC Infomedia Jatinegara | F44: P232075-06-00 | G44: 00296/M/INF2430233/2024 | H44: Aktivasi | I44: Connectivity | J44: Telkom DWS
A45: 184 | B45: Agustus | C45: 2024 | D45: 16/8/2024 | E45: PSB Link Metro E 2 Mbps Allianz DCI CIbitung ke Infomedia Sri Ratu Semarang | F45: P243086-02-00 | G45: 00298/M/INF2430233/2024 | H45: Aktivasi | I45: Connectivity | J45: Telkom DES
A46: 187 | B46: Agustus | C46: 2024 | D46: 21/8/2024 | E46: Aktivasi Metro 2 Mbps Layanan Erajaya | F46: P242564-00-00 | G46: 00302/IN/INF2430233/2024 | H46: Aktivasi | I46: Connectivity | J46: Telkom DWS | M46: 2-2241539297
A47: 188 | B47: Agustus | C47: 2024 | D47: 22/8/2024 | E47: Aktivasi Metro 4 Mbps Layanan Trakindo | F47: P243099-04-00 | G47: 00301/IN/INF2430233/2024 | H47: Aktivasi | I47: Connectivity | J47: Telkom DWS | M47: 2-2242493996
A48: 192 | B48: Agustus | C48: 2024 | D48: 22/8/2024 | E48: Aktivasi Masking Outbond 1500473 Layanan GSD | F48: P243141-03-00 | G48: 00306/IN/INF2430233/2024 | H48: Aktivasi | I48: Nomor Akses | J48: Telkom DWS | M48: 2-2244717646 | N48: 888281347714 | R48: Close | W48: file
A49: 193 | B49: Agustus | C49: 2024 | D49: 23/8/2024 | E49: PSB Infrastruktur Layanan BES Telkomsel Site Infomedia Tendean | F49: 00090/M/INF24322/2024 | G49: 00304/IN/INF2430233/2024 | H49: Upgrade | I49: Connectivity | J49: Telkom DWS | M49: 2-2253635127 | N49: 1714942109 | V49: 45547 | W49: file
A50: 201 | B50: September | C50: 2024 | D50: 45574 | E50: Masking Outbound Nomor Akses 1500525 PT FWD Insurance Indonesia | F50: P243137-02-00 | G50: 00324/IN/INF2430233/2024 | H50: Aktivasi | I50: Nomor Akses | J50: telkom DWS | M50: 2-2254947776
A51: 202 | B51: September | C51: 2024 | D51: 45574 | E51: Masking Outbound Nomor Akses 1500525 PT FWD Insurance Indonesia (Metro) | F51: P243137-02-00 | G51: 00324/IN/INF2430233/2024 | H51: Aktivasi | I51: Connectivity | J51: telkom DWS | M51: 2-2253387394
A52: 206 | B52: September | C52: 2024 | D52: 15/9/2024 | E52: Ubah harga Link Metro E 2 Mbps Allianz DCI CIbitung ke Infomedia Sri Ratu Semarang | F52: P243086-02-00 | G52: 00297/IN/INF2430233/2024 | H52: Aktivasi | I52: Connectivity | J52: telkom DWS
A53: 207 | B53: September | C53: 2024 | D53: 18/9/2024 | E53: Aktivasi Masking Outbond 1500630 Layanan Kemenaker | F53: P2431 70-02-00 | G53: 00330/IN/INF2430233/2024 | H53: Aktivasi | I53: Nomor Akses | J53: telkom DWS
A54: 208 | B54: September | C54: 2024 | D54: 19/9/2024 | E54: PSB Astinet 2 Mbps Layanan Call Center PSC 119 Kabupaten Subang | F54: P232189-02-00 | G54: 00334/M/INF2430233/2024 | H54: Aktivasi | I54: Connectivity | J54: telkom DWS | M54: 2-2279724092 | N54: 2053100300 | P54: 36.88.44.17/29
A55: 211 | B55: September | C55: 2024 | D55: 26/9/2024 | E55: Aktivasi dan Masking Outbound Nomor Akses 1500518 PT BRI Life | F55: P243165-02-00 | G55: 00341/IN/INF2430233/2024 | H55: Aktivasi | I55: Nomor Akses | J55: telkom DWS | M55: 2-2265325668
A56: 212 | B56: September | C56: 2024 | D56: 26/9/2024 | E56: Upgrade Link Metro E 5 Mbps menjadi 10 Mbps PT. Asuransi BRI Life Jakarta | F56: P243165-02-00 | G56: 00342/IN/INF2430233/2024 | H56: Aktivasi | I56: Connectivity | J56: telkom DWS | N56: 1713333767 | O56: 1712918666
A57: 215 | B57: Oktober | C57: 2024 | D57: 45332 | E57: Permohonan Aktivasi Nomor Akses 145 Otorita Ibu Kota Nusantara | F57: P243210-01-00 | G57: 00348/IN/INF2430233/2024 | H57: Aktivasi | I57: Nomor Akses | R57: Close | T57: 2500000
A58: 218 | B58: Oktober | C58: 2024 | D58: 45514 | E58: Masking Outbound Nomor Akses 1500332 PT MRT Jakarta | F58: P243175-00-00 | G58: 00360/IN/INF2430233/2024 | H58: Aktivasi | I58: Nomor Akses | J58: Telkom DWS | M58: 2-2274309253 | N58: 888101654925 | R58: Close | T58: 580000 | W58: file
A59: 221 | B59: Oktober | C59: 2024 | D59: 45575 | E59: Permohonan Masking Outbound Nomor Akses 1500918 PT Kartika Bina Medika | F59: P243283-01-00 | G59: 00368/IN/INF2430233/2024 | H59: Aktivasi | I59: Nomor Akses | R59: Close | T59: 580000
A60: 224 | B60: Oktober | C60: 2024 | D60: 16/10/2024 | E60: Permohonan Aktivasi Nomor Akses150280 PT Suiten Inovasi Sukses | H60: Aktivasi | I60: Nomor Akses | M60: 2-2280671657 | R60: Open | T60: 2500000
A61: 225 | B61: Oktober | C61: 2024 | D61: 16/10/2024 | E61: Permohonan Aktivasi Masking Nomor 150280 PT Suiten Inovasi Sukses | F61: P243240-01-00 | G61: 00372/M/INF2430233/2024 | H61: Aktivasi | I61: Nomor Akses | M61: 2-2280671657 | R61: Open | T61: 580000
A62: 231 | B62: Oktober | C62: 2024 | D62: 24/10/2024 | E62: Aktivasi Nomor Akses & Masking Outbond 1500122 RSUP Ngoerah (Masking) | F62: P243225-05-00 | G62: 00388/IN/INF2430233/2024 | H62: Aktivasi | I62: Nomor Akses | M62: 2-2292550667 | N62: 888311004697 | R62: Close | T62: 2500000 | W62: file
B63: Oktober | C63: 2024 | D63: 30/10/2024 | E63: Permohonan Dismantle Nomor Akses, Masking Outbound dan Link Metro E 1500886 PT Investree Radhika Jaya Tanggal 31 Oktober 2024 | H63: Dismantle | I63: Nomor Akses | J63: Telkom DWS | M63: 2-2292573785 | N63: 888242213601 | R63: Close | W63: file
A64: 234 | B64: Oktober | C64: 2024 | D64: 31/10/2024 | E64: Permohonan Aktivasi Astinet 2 Mbps Layanan Aladin | H64: Aktivasi | I64: Connectivity | J64: Telkom DWS | M64: 2-2296411808 | R64: Close | T64: 449000
A65: 239 | B65: November | C65: 2024 | D65: 45423 | E65: Aktivasi Nomor Akses 150227 dan PSB Link Astinet 3 Mbps PT Adhi Karya (Nomor Akses) | F65: P243327-02-00 | G65: 00406/IN/INF2430233/2024 | H65: Aktivasi | I65: Nomor Akses | J65: Telkom DWS | M65: 2-2457398905 | N65: 8.8825063e+15 | R65: Close | T65: 3078000 | W65: file
A66: 241 | B66: November | C66: 2024 | D66: 45515 | E66: Aktivasi Nomor Akses 191 PT ASDP Indonesia Ferry (Persero) | F66: Surat PT ASDP Nomor UM.003/05591/XI/ASDP-2024 | G66: 00411/IN/INF2430233/2024 | H66: Aktivasi | I66: Nomor Akses | J66: Telkom DWS | M66: 2-2301802223 | N66: 888121546645 | R66: Close | T66: 2500000 | W66: file
A67: 249 | B67: November | C67: 2024 | D67: 21/11/2024 | E67: Aktivasi Astinet 5 Mbps dan Aktivasi 1500838 Layanan PT KITB | F67: P243405-02-00 | G67: 00427/IN/INF2430233/2024 | H67: Aktivasi | I67: Nomor Akses | J67: Telkom DWS | M67: 2-2309753866 | N67: 888251449006 | R67: Close | T67: 2500000 | W67: file
A68: 253 | B68: Desember | C68: 2024 | D68: 45334 | E68: Masking Outbound Nomor Akses 191 PT ASDP Indonesia Ferry (Persero) | F68: P243402-02-00 | G68: 00438/IN/INF2430233/2024 | H68: Aktivasi | I68: Nomor Akses | J68: Telkom DWS | M68: 2-2318345833 | N68: 888091924957 | R68: Close | W68: file
A69: 258 | B69: Desember | C69: 2024 | D69: 45455 | E69: Aktivasi Nomor Akses 1500215 dan PSB Link Metro E Interaktif 1 Mbps PT Pembangunan Deltamas | F69: P243363-02-00 | G69: 00445/IN/INF2430233/2024 | H69: Aktivasi | I69: Nomor Akses | J69: Telkom DWS | M69: 2-2322264419 | R69: Close | T69: 2.500,000 | V69: 16/12/2024 | W69: file
A70: 260 | B70: Desember | C70: 2024 | D70: 45547 | E70: Masking Outbound Nomor Akses 1500456 PT Zurich Asuransi Indonesia | F70: P232197-15-00 | G70: 00449/IN/INF2430233/2024 | H70: Aktivasi | I70: Nomor Akses | J70: Telkom DWS | M70: 2-2322764671 | N70: 888101519229 | R70: Close | T70: 1160000 | W70: file
A71: 268 | B71: Desember | C71: 2024 | D71: 18/12/2024 | F71: P243498-02-0 0 | G71: 00464/M/INF2430233/2024 | H71: Aktivasi | I71: Nomor Akses | J71: Telkom DWS | L71: =K71-TODAY() -> -46258 | T71: 2500000
A72: 269 | B72: Desember | C72: 2024 | D72: 18/12/2024 | F72: P243498-02-0 0 | G72: 00464/M/INF2430233/2024 | H72: Aktivasi | I72: Nomor Akses | J72: Telkom DWS | L72: =K72-TODAY() -> -46258 | T72: 580000
A73: 271 | B73: Desember | C73: 2024 | D73: 19/12/2024 | F73: permohonan aktivasi dari sekjend DENAS kEK | G73: 00466/M/INF2430233/2024 | H73: Aktivasi | I73: Nomor Akses | J73: Telkom DWS | L73: =K73-TODAY() -> -46258 | M73: 2-2304259268 | R73: Open | T73: 2500000
A74: 137 | B74: Juni | C74: 2024 | D74: 45470 | E74: Dismentle link Erajaya | F74: Occupancy di NMS yang sudah menurun | G74: 00219/IN/INF2430233/24 | H74: Connectivity | I74: Dismantle | J74: Telkom DES | N74: astinet:970224544 metro: 923130166 | Q74: Dismentle dan Downgrade link Erajaya
A75: 1 | B75: Januari | C75: 2024 | D75: 45293 | E75: Dismantle Nomor Akses 1500927 PT. Waskita Beton Precast Tbk | F75: 00002/M/INF23342/24 | G75: 00001/IN/INF2340122/24 | H75: Dismantle | I75: Nomor Akses | J75: Telkom DWS | M75: 2-2122343067 | N75: SID: 888336639071 | R75: Close | T75: 2500000 | U75: No: 40/YN 000/DR2–11220000/2024 | V75: 45292
A76: 4 | B76: Januari | C76: 2024 | D76: 45296 | E76: Dismantle Nomor Akses Nomor Akses 1500813 PT Murni Medika Solusindo | F76: 00052/M/INF23242/23 | G76: 00012/IN/INF2340122/24 | H76: Dismantle | I76: Nomor Akses | J76: Telkom DWS | M76: 2-2126446429 | N76: SID: 888288708102 | R76: Close | T76: 2500000 | U76: No: 183/YN 000/DR2–11220000/2024 | V76: 45299
A77: 15 | B77: Januari | C77: 2024 | D77: 45308 | E77: Dismantle Nomor Akses 1500316 PT Teluk Lamong | F77: 00005/M/INF23353/24 | G77: 00035/IN/INF2340122/24 | H77: Dismantle | I77: Nomor Akses | J77: Telkom DWS | M77: 1500316 : 2-2135801669 | N77: 1500316 SID: 888175930006 | R77: Close | T77: 1500000 | U77: No: 539/YN 000/DR2–11220000/2024 | V77: 45314
A78: 16 | B78: Januari | C78: 2024 | D78: 45308 | E78: Dismantle nomor AKSES 1500273 Dinas PM PTSP Kab Badung Denpasar | F78: 00005/M/INF23353/24 | G78: 00035/IN/INF2340122/24 | H78: Dismantle | I78: Nomor Akses | J78: Telkom DWS | M78: 1500273 : 2-2136055209 | N78: 1500273 SID: 3700038-0031905449 | R78: Close | T78: 1500000 | U78: No: 652/YN 000/DR2–11220000/2024 | V78: 45309
A79: 28 | B79: Januari | C79: 2024 | D79: 45322 | E79: Dismentle Astinet Waskita | F79: Layanan Waskita yang telah Churn | G79: 00065/IN/INF2340122/24 | H79: Dismantle | I79: Connectivity | J79: Telkom DWS | M79: 2-2140810324 | N79: SID 1714389102 | R79: Close | T79: 308750 | U79: No: 798/YN 000/DR2–11220000/2024 | V79: 45323
A80: 29 | B80: Februari | C80: 2024 | D80: 45323 | E80: Dismantle Internet Indihome 20 Mbps Layanan Waspang Unjani | F80: Email dari Operasional | G80: 00069/IN/INF2340122/24 | H80: Dismantle | I80: Connectivity | J80: Telkom DES | N80: SID: 131159163579 | R80: Close
A81: 38 | B81: Februari | C81: 2024 | D81: 45334 | E81: Dismantle Internet Indihome 100 Mbps Layanan GRaPARI GTG BSD | F81: Email dari Operasional | G81: 00002/IN/INF2430233/24 | H81: Dismantle | I81: Connectivity | N81: SID: 122432304992 | R81: Close | T81: 60000
A82: 39 | B82: Februari | C82: 2024 | D82: 45337 | E82: Dismentle Astinet Layanan Dana Jakarta | F82: Layanan Dana yang sudah churn | G82: 00003/IN/INF2430233/24 | H82: Dismantle | I82: Connectivity | J82: Telkom DWS | M82: Semarang : 2-2148432338 | R82: Close | T82: 10284300
A83: 40 | B83: Februari | C83: 2024 | D83: 45337 | E83: Dismentle Astinet Layanan Dana Semarang | F83: Layanan Dana yang sudah churn | G83: 00003/IN/INF2430233/24 | H83: Dismantle | I83: Connectivity | J83: Telkom DWS | M83: Jakarta : 2-2148543859 | R83: Close | T83: 56878770
A84: 41 | B84: Februari | C84: 2024 | D84: 45337 | E84: Dismentle Indihome Layanan DANA di Site Infomedia | G84: 00005/IN/INF2430233/24 | H84: Dismantle | I84: Connectivity | J84: Telkom DES | N84: Indihome Dana Smg 142410332983 Indihome Dana Tendean 121202266187 Indihome Dana BSD 121431219464 | R84: Close | T84: 3115000
A85: 46 | B85: Februari | C85: 2024 | D85: 45350 | E85: Dismantle Nomor Akses 126 | F85: 00009/M/INF24382/24 00010/M/INF24382/24 | G85: 00029/IN/INF2430233/24 | H85: Dismantle | I85: Nomor Akses | J85: Telkom DWS | N85: 126 SID = 888154753503 | Q85: Sudah di Proses Dismentle | R85: Close | T85: 580000 | U85: No: 1416/YN 000/DR2–11220000/2024 | V85: 45351
A86: 47 | B86: Februari | C86: 2024 | D86: 45350 | E86: Dismantle Nomor Akses 1500117 | F86: 00009/M/INF24382/24 00010/M/INF24382/24 | G86: 00029/IN/INF2430233/24 | H86: Dismantle | I86: Nomor Akses | J86: Telkom DWS | N86: 1500117 SID = 888200424788 | Q86: tidak di proses oleh DWS | R86: Close | T86: 1500000
A87: 48 | B87: Februari | C87: 2024 | D87: 45350 | E87: Dismantle Nomor Akses 1500221 | F87: 00009/M/INF24382/24 00010/M/INF24382/24 | G87: 00029/IN/INF2430233/24 | H87: Dismantle | I87: Nomor Akses | J87: Telkom DWS | N87: 1500221 SID = 888359740642 | Q87: tidak di proses oleh DWS | R87: Close | T87: 2500000
A88: 50 | B88: Maret | C88: 2024 | D88: 45352 | E88: Permohonan Dismantle Nomor Akses 1500174 PT Global Urban Esensial dan 1500462 Global Urban Estential | F88: 00001/M/INF24382/24 | G88: 00038/IN/INF2430233/24 | H88: Dismantle | I88: Nomor Akses | J88: Telkom DWS | M88: 2-2183673289 - 1500174 2-2183673844 - 1500462 | N88: 1500174 SID: 3700038-0031882147 1500462 SID: 3700038-0029637113 | R88: Close | T88: 3000000
A89: 58 | B89: Maret | C89: 2024 | D89: 45365 | E89: Dismantle Nomor Akses 1500114 CC Kafe & Resto Pampalass | F89: 00014/M/INF24382/24 | G89: 00058/IN/INF2430233/24 | H89: Dismantle | I89: Nomor Akses | J89: Telkom DWS | M89: 2-2161074774 | N89: SID: 3700038-0026410602 | R89: Close | T89: 1500000
A90: 61 | B90: Maret | C90: 2024 | D90: 45371 | E90: Dismantle Infrastruktur Infomedia Hasil Rekon Bersama Telkom DWS | F90: rekon Jarkom | G90: 00072/IN/INF2430233/24 | H90: Dismantle | I90: Connectivity | J90: Telkom DWS | M90: 2-2169614631 | Q90: Permohonan Dismantle Infrastruktur Infomedia Sri Ratu Semarang => Permintaan ke DWS tgl 19 Mar 2024 | R90: Close | T90: 4230000 | U90: No: 1839/YN 000/DR2–11220000/2024 | V90: 45383
B91: Maret | C91: 2024 | D91: 45371 | E91: Dismantle Infrastruktur Infomedia Hasil Rekon Bersama Telkom DWS | F91: rekon Jarkom | G91: 00072/IN/INF2430233/24 | H91: Dismantle | I91: Connectivity | J91: Telkom DWS | M91: 2-2169615572 | Q91: Permohonan Dismantle Infrastruktur Infomedia Sri Ratu Semarang => Permintaan ke DWS tgl 19 Mar 2024 | R91: Close | T91: 4230000 | U91: No: 1839/YN 000/DR2–11220000/2024 | V91: 45383
B92: Maret | C92: 2024 | D92: 45371 | E92: Dismantle Infrastruktur Infomedia Hasil Rekon Bersama Telkom DWS | F92: rekon Jarkom | G92: 00072/IN/INF2430233/24 | H92: Dismantle | I92: Connectivity | J92: Telkom DWS | M92: 2-2169699114 | N92: 1191627431 | O92: 1252546791 | Q92: Permohonan Dismantle Infrastruktur Infomedia Sri Ratu Semarang => Permintaan ke DWS tgl 19 Mar 2024 | R92: Close | T92: 4230000 | U92: No: 1839/YN 000/DR2–11220000/2024 | V92: 45383 | W92: file
A93: 72 | B93: April | C93: 2024 | D93: 45389 | E93: Dismantle Nomor Akses 1500450 PT. Asuransi Adira Dinamika | F93: 00025/M/1NF24382/24 | G93: 00101/IN/INF2430233/24 | H93: Dismantle | I93: Connectivity | J93: Telkom DWS | N93: AO: 2-345131123 SID: 3700038-0029465987 | R93: Close | T93: 2325000 | U93: No: 1840/YN 000/DR2–11220000/2024 | V93: 45389
A94: 74 | B94: April | C94: 2024 | D94: 45399 | E94: Dismantle Nomor Akses 1500450 PT. Asuransi Adira Dinamika | F94: 00025/M/1NF24382/24 | G94: 00101/IN/INF2430233/24 | H94: Dismantle | I94: Nomor Akses | J94: Telkom DWS | M94: 2-2173619059 | N94: SID: 3700038-0029465987 | R94: Close | T94: 2325000 | U94: No: 1840/YN 000/DR2–11220000/2024 | V94: 45399
A95: 77 | B95: April | C95: 2024 | D95: 45401 | E95: Dismantle Sip Trunk Layanan Rumah Zakat | F95: 0032/M/INF24344/24 | G95: 00103/IN/INF2430233/24 | H95: Dismantle | I95: IPPBX | J95: Telkom DWS | M95: 2-2175281894 | N95: ao = 2-650220149 SID- 888235260987, | R95: Close | T95: 2300000 | U95: Nomor: Tel. 293/YN.000/DR3-11220000/2024 | V95: 45404
A96: 82 | B96: Mei | C96: 2024 | D96: 45415 | E96: Dismantle Nomor Akses 1500220 PT RICHEESE KULINER INDONESIA | F96: 00026/WINF24382/24 | G96: 00122/IN/INF2430233/24 | H96: Dismantle | I96: Nomor Akses | J96: Telkom DWS | M96: 2-2181109760 | N96: AO: 2-317932665 SID: 3700038-0025181924 | R96: Close | T96: 1500000 | U96: No: 2041/YN 000/DR2–11220000/2024 | V96: 45418
A97: 83 | B97: Mei | C97: 2024 | D97: 45415 | E97: Dismantle Nomor Akses 1500XYZ Bulai Mei 2024 | F97: 00027/M/1NF24382/24 | G97: 00121/IN/INF2430233/24 | H97: Dismantle | I97: Nomor Akses | J97: Telkom DWS | M97: 1500058 : 2-2181159301 1500074 : 2-2181159658 1500262 : 2-2181170195 1500612 : 2-2181170737 | N97: 1500058 SID: 3700038-0029732413 1500074 SID: 3700038-0029694053 1500262 SID: 3700038-0029732416 1500612 SID: 3700038-0032211374 | Q97: 1500262 : 2-2181170195 1500612 : 2-2181170737 | R97: Close | T97: 6000000 | U97: No: 2041/YN 000/DR2–11220000/2024 | V97: 45418
A98: 84 | B98: Mei | C98: 2024 | D98: 45415 | E98: Dismantle Nomor Akses 0804-1001000 Rumah Zakat | F98: 00025/M/1NF24382/24 | G98: 00123/IN/INF2430233/24 | H98: Dismantle | I98: Nomor Akses | J98: Telkom DWS | N98: SID: 3700038-0031604403 | R98: Close | T98: 1500000
A99: 85 | B99: Mei | C99: 2024 | D99: 45418 | E99: Dismantle VPN IP Domestik RBB | F99: sudah tidak digunakan | G99: 00124/IN/INF2430233/24 | H99: Dismantle | I99: Connectivity | J99: Telkom DWS | N99: AO: 2-2164404374 SID 1965736158 | R99: Close
A100: 86 | B100: Mei | C100: 2024 | D100: 45418 | E100: Dismantle Infrastruktur Layanan CC Bakti Site Infomedia Tendean | F100: CC Bakti yang sudah Churn | G100: 00125/IN/INF2430233/24 | H100: Dismantle | I100: Connectivity | J100: Telkom DWS | M100: CC Bhakti 2-2183638787 Tendean 2-2183640325 | N100: Metro e SID: 1737641703 Astinet SID: 1737877128 | R100: Close | T100: 2614000 | U100: No: 2708/YN 000/DR2–11220000/2024 | V100: 45425
...

Sheet Sum 2024
AF1: Januari | AG1: Februari | AH1: Maret | AI1: April | AJ1: Mei | AK1: Juni | AL1: Juli | AM1: Agustus | AN1: September | AO1: Oktober | AP1: November | AQ1: Desember | AU1: 2024 | AV1: JANUARI | AX1: FEBRUARI | AZ1: MARET | BB1: APRIL | BD1: MAY | BF1: JUNI | BH1: JULI | BJ1: AGUSTUS | BL1: SEPTEMBER | BN1: OKTOBER | BP1: NOVEMBER | BR1: Desember
B2: Total Project | D2: =COUNTIFS('List Project'!C:C,"2024",'List Project'!P:P,"Done")+COUNTIFS('List Project'!C:C,"2024",'List Project'!P:P,"OGP") -> 150 | AE2: Revenue Project | AF2: =SUMIF('List Project'!D:D,"Januari",'List Project'!I:I) -> 1.5323832e+11 | AG2: =SUMIF('List Project'!D:D,"Februari",'List Project'!I:I) -> 1.0706982e+11 | AH2: =SUMIF('List Project'!D:D,"Maret",'List Project'!I:I) -> 158846645854 | AI2: =SUMIF('List Project'!D:D,"April",'List Project'!I:I) -> 21145067274 | AJ2: =SUMIF('List Project'!D:D,"Mei",'List Project'!I:I) -> 117613354628 | AK2: =SUMIF('List Project'!D:D,"Juni",'List Project'!I:I) -> 24387249911 | AL2: =SUMIF('List Project'!D:D,"Juli",'List Project'!I:I) -> 25193979370 | AM2: =SUMIF('List Project'!D:D,"Agustus",'List Project'!I:I) -> 95140991295 | AN2: =SUMIF('List Project'!D:D,"September",'List Project'!I:I) -> 1.3015875e+11 | AO2: =SUMIF('List Project'!D:D,"Oktober",'List Project'!I:I) -> 3.0147039e+11 | AP2: =SUMIF('List Project'!D:D,"November",'List Project'!I:I) -> 46006119761 | AQ2: =SUMIF('List Project'!D:D,"Desember",'List Project'!I:I) -> 1005993372947 | AR2: =SUM(AF2:AQ2) -> 2.1862641e+12 | AU2: Klasifikasi order | AV2: JUMLAH | AW2: TOTAL TAGIHAN | AX2: JUMLAH | AY2: TOTAL TAGIHAN | AZ2: JUMLAH | BA2: TOTAL TAGIHAN | BB2: JUMLAH | BC2: TOTAL TAGIHAN | BD2: JUMLAH | BE2: TOTAL TAGIHAN | BF2: JUMLAH | BG2: TOTAL TAGIHAN | BH2: JUMLAH | BI2: TOTAL TAGIHAN | BJ2: JUMLAH | BK2: TOTAL TAGIHAN | BL2: JUMLAH | BM2: TOTAL TAGIHAN | BN2: JUMLAH | BO2: TOTAL TAGIHAN | BP2: JUMLAH | BQ2: TOTAL TAGIHAN | BR2: JUMLAH | BS2: TOTAL TAGIHAN
AE3: Adi | AF3: =COUNTIFS('List Project'!D:D,"Januari",'List Project'!O:O,"Adi") -> 2 | AG3: =COUNTIFS('List Project'!D:D,"Februari",'List Project'!O:O,"Adi") -> 2 | AH3: =COUNTIFS('List Project'!D:D,"Maret",'List Project'!O:O,"Adi") -> 1 | AI3: =COUNTIFS('List Project'!D:D,"April",'List Project'!O:O,"Adi") -> 1 | AJ3: =COUNTIFS('List Project'!D:D,"Mei",'List Project'!O:O,"Adi") -> 2 | AK3: =COUNTIFS('List Project'!D:D,"Juni",'List Project'!O:O,"Adi") -> 0 | AL3: =COUNTIFS('List Project'!D:D,"Juli",'List Project'!O:O,"Adi") -> 0 | AM3: =COUNTIFS('List Project'!D:D,"Agustus",'List Project'!O:O,"Adi") -> 0 | AN3: =COUNTIFS('List Project'!D:D,"September",'List Project'!O:O,"Adi") -> 1 | AO3: =COUNTIFS('List Project'!D:D,"Oktober",'List Project'!O:O,"Adi") -> 2 | AP3: =COUNTIFS('List Project'!D:D,"November",'List Project'!O:O,"Adi") -> 1 | AQ3: =COUNTIFS('List Project'!D:D,"Desember",'List Project'!O:O,"Adi") -> 0 | AR3: =SUM(AF3:AQ3) -> 12 | AS3: =SUMIF('List Project'!O:O,"Adi",'List Project'!I:I) -> 124082524515 | AU3: NOMOR AKSES | AV3: =COUNTIFS('List Order'!B:B,"Januari",'List Order'!I:I,"Nomor Akses",'List Order'!C:C,"2024") -> 16 | AW3: =SUM(AW4:AW6) -> 21777500 | AX3: =COUNTIFS('List Order'!B:B,"Februari",'List Order'!I:I,"Nomor Akses",'List Order'!C:C,"2024") -> 10 | AY3: =SUM(AY4:AY6) -> 10160000 | AZ3: =COUNTIFS('List Order'!B:B,"Maret",'List Order'!I:I,"Nomor Akses",'List Order'!C:C,"2024") -> 7 | BA3: =SUM(BA4:BA6) -> 7080000 | BB3: =COUNTIFS('List Order'!B:B,"April",'List Order'!I:I,"Nomor Akses",'List Order'!C:C,"2024") -> 2 | BC3: =SUM(BC4:BC6) -> 1500000 | BD3: =COUNTIFS('List Order'!B:B,"Mei",'List Order'!I:I,"Nomor Akses",'List Order'!C:C,"2024") -> 19 | BE3: =SUM(BE4:BE6) -> 0 | BF3: =COUNTIFS('List Order'!B:B,"Juni",'List Order'!I:I,"Nomor Akses",'List Order'!C:C,"2024") -> 4 | BG3: =SUM(BG4:BG6) -> 0 | BH3: =COUNTIFS('List Order'!B:B,"Juli",'List Order'!I:I,"Nomor Akses",'List Order'!C:C,"2024") -> 23 | BI3: =SUM(BI4:BI6) -> 0 | BJ3: =COUNTIFS('List Order'!B:B,"Agustus",'List Order'!I:I,"Nomor Akses",'List Order'!C:C,"2024") -> 5 | BK3: =SUM(BK4:BK6) -> 0 | BL3: =COUNTIFS('List Order'!B:B,"September",'List Order'!I:I,"Nomor Akses",'List Order'!C:C,"2024") -> 8 | BM3: =SUM(BM4:BM6) -> 0 | BN3: =COUNTIFS('List Order'!B:B,"Oktober",'List Order'!I:I,"Nomor Akses",'List Order'!C:C,"2024") -> 12 | BO3: =SUM(BO4:BO6) -> 9240000 | BP3: =COUNTIFS('List Order'!B:B,"November",'List Order'!I:I,"Nomor Akses",'List Order'!C:C,"2024") -> 8 | BQ3: =SUM(BQ4:BQ6) -> 8078000 | BR3: =COUNTIFS('List Order'!B:B,"Desember",'List Order'!I:I,"Nomor Akses",'List Order'!C:C,"2024") -> 12 | BS3: =SUM(BS4:BS6) -> 6740000
B4: Total Revenue | D4: =SUMIF('List Project'!C:C,"2024",'List Project'!I:I) -> 407539404275 | AE4: Dwi | AF4: =COUNTIFS('List Project'!D:D,"Januari",'List Project'!O:O,"Dwi") -> 12 | AG4: =COUNTIFS('List Project'!D:D,"Februari",'List Project'!O:O,"Dwi") -> 12 | AH4: =COUNTIFS('List Project'!D:D,"Maret",'List Project'!O:O,"Dwi") -> 10 | AI4: =COUNTIFS('List Project'!D:D,"April",'List Project'!O:O,"Dwi") -> 7 | AJ4: =COUNTIFS('List Project'!D:D,"Mei",'List Project'!O:O,"Dwi") -> 4 | AK4: =COUNTIFS('List Project'!D:D,"Juni",'List Project'!O:O,"Dwi") -> 5 | AL4: =COUNTIFS('List Project'!D:D,"Juli",'List Project'!O:O,"Dwi") -> 9 | AM4: =COUNTIFS('List Project'!D:D,"Agustus",'List Project'!O:O,"Dwi") -> 4 | AN4: =COUNTIFS('List Project'!D:D,"September",'List Project'!O:O,"Dwi") -> 3 | AO4: =COUNTIFS('List Project'!D:D,"Oktober",'List Project'!O:O,"Dwi") -> 6 | AP4: =COUNTIFS('List Project'!D:D,"November",'List Project'!O:O,"Dwi") -> 9 | AQ4: =COUNTIFS('List Project'!D:D,"Desember",'List Project'!O:O,"Dwi") -> 4 | AR4: =SUM(AF4:AQ4) -> 85 | AS4: =SUMIF('List Project'!O:O,"Dwi",'List Project'!I:I) -> 4.398677e+11 | AU4: Aktivasi | AV4: =COUNTIFS('List Order'!C:C,"2024",'List Order'!B:B,"Januari",'List Order'!H:H,"Aktivasi",'List Order'!I:I,"Nomor Akses") -> 3 | AW4: =SUMIFS('List Order'!T:T,'List Order'!C:C,"2024",'List Order'!B:B,"Januari",'List Order'!H:H,"Aktivasi",'List Order'!I:I,"Nomor Akses") -> 5580000 | AX4: =COUNTIFS('List Order'!C:C,"2024",'List Order'!B:B,"Februari",'List Order'!H:H,"Aktivasi",'List Order'!I:I,"Nomor Akses") -> 6 | AY4: =SUMIFS('List Order'!T:T,'List Order'!C:C,"2024",'List Order'!B:B,"Februari",'List Order'!H:H,"Aktivasi",'List Order'!I:I,"Nomor Akses") -> 8660000 | AZ4: =COUNTIFS('List Order'!C:C,"2024",'List Order'!B:B,"Maret",'List Order'!H:H,"Aktivasi",'List Order'!I:I,"Nomor Akses") -> 3 | BA4: =SUMIFS('List Order'!T:T,'List Order'!C:C,"2024",'List Order'!B:B,"Maret",'List Order'!H:H,"Aktivasi",'List Order'!I:I,"Nomor Akses") -> 5580000 | BB4: =COUNTIFS('List Order'!C:C,"2024",'List Order'!B:B,"April",'List Order'!H:H,"Aktivasi",'List Order'!I:I,"Nomor Akses") -> 0 | BC4: =SUMIFS('List Order'!T:T,'List Order'!C:C,"2024",'List Order'!B:B,"April",'List Order'!H:H,"Aktivasi",'List Order'!I:I,"Nomor Akses") -> 0 | BD4: =COUNTIFS('List Order'!C:C,"2024",'List Order'!B:B,"Mei",'List Order'!H:H,"Aktivasi",'List Order'!I:I,"Nomor Akses") -> 7 | BE4: =SUMIFS('List Order'!T:T,'List Order'!C:C,"2024",'List Order'!B:B,"Mei",'List Order'!H:H,"Aktivasi",'List Order'!I:I,"Nomor Akses") -> 0 | BF4: =COUNTIFS('List Order'!C:C,"2024",'List Order'!B:B,"Juni",'List Order'!H:H,"Aktivasi",'List Order'!I:I,"Nomor Akses") -> 2 | BG4: =SUMIFS('List Order'!T:T,'List Order'!C:C,"2024",'List Order'!B:B,"Juni",'List Order'!H:H,"Aktivasi",'List Order'!I:I,"Nomor Akses") -> 0 | BH4: =COUNTIFS('List Order'!C:C,"2024",'List Order'!B:B,"Juli",'List Order'!H:H,"Aktivasi",'List Order'!I:I,"Nomor Akses") -> 18 | BI4: =SUMIFS('List Order'!T:T,'List Order'!C:C,"2024",'List Order'!B:B,"Juli",'List Order'!H:H,"Aktivasi",'List Order'!I:I,"Nomor Akses") -> 0 | BJ4: =COUNTIFS('List Order'!C:C,"2024",'List Order'!B:B,"Agustus",'List Order'!H:H,"Aktivasi",'List Order'!I:I,"Nomor Akses") -> 1 | BK4: =SUMIFS('List Order'!T:T,'List Order'!C:C,"2024",'List Order'!B:B,"Agustus",'List Order'!H:H,"Aktivasi",'List Order'!I:I,"Nomor Akses") -> 0 | BL4: =COUNTIFS('List Order'!C:C,"2024",'List Order'!B:B,"September",'List Order'!H:H,"Aktivasi",'List Order'!I:I,"Nomor Akses") -> 3 | BM4: =SUMIFS('List Order'!T:T,'List Order'!C:C,"2024",'List Order'!B:B,"September",'List Order'!H:H,"Aktivasi",'List Order'!I:I,"Nomor Akses") -> 0 | BN4: =COUNTIFS('List Order'!C:C,"2024",'List Order'!B:B,"Oktober",'List Order'!H:H,"Aktivasi",'List Order'!I:I,"Nomor Akses") -> 7 | BO4: =SUMIFS('List Order'!T:T,'List Order'!C:C,"2024",'List Order'!B:B,"Oktober",'List Order'!H:H,"Aktivasi",'List Order'!I:I,"Nomor Akses") -> 9240000 | BP4: =COUNTIFS('List Order'!C:C,"2024",'List Order'!B:B,"November",'List Order'!H:H,"Aktivasi",'List Order'!I:I,"Nomor Akses") -> 4 | BQ4: =SUMIFS('List Order'!T:T,'List Order'!C:C,"2024",'List Order'!B:B,"November",'List Order'!H:H,"Aktivasi",'List Order'!I:I,"Nomor Akses") -> 8078000 | BR4: =COUNTIFS('List Order'!C:C,"2024",'List Order'!B:B,"Desember",'List Order'!H:H,"Aktivasi",'List Order'!I:I,"Nomor Akses") -> 8 | BS4: =SUMIFS('List Order'!T:T,'List Order'!C:C,"2024",'List Order'!B:B,"Desember",'List Order'!H:H,"Aktivasi") -> 6740000
AE5: Duta | AF5: =COUNTIFS('List Project'!D:D,"Januari",'List Project'!O:O,"Duta") -> 26 | AG5: =COUNTIFS('List Project'!D:D,"Februari",'List Project'!O:O,"Duta") -> 14 | AH5: =COUNTIFS('List Project'!D:D,"Maret",'List Project'!O:O,"Duta") -> 11 | AI5: =COUNTIFS('List Project'!D:D,"April",'List Project'!O:O,"Duta") -> 8 | AJ5: =COUNTIFS('List Project'!D:D,"Mei",'List Project'!O:O,"Duta") -> 10 | AK5: =COUNTIFS('List Project'!D:D,"Juni",'List Project'!O:O,"Duta") -> 7 | AL5: =COUNTIFS('List Project'!D:D,"Juli",'List Project'!O:O,"Duta") -> 6 | AM5: =COUNTIFS('List Project'!D:D,"Agustus",'List Project'!O:O,"Duta") -> 12 | AN5: =COUNTIFS('List Project'!D:D,"September",'List Project'!O:O,"Duta") -> 5 | AO5: =COUNTIFS('List Project'!D:D,"Oktober",'List Project'!O:O,"Duta") -> 8 | AP5: =COUNTIFS('List Project'!D:D,"November",'List Project'!O:O,"Duta") -> 9 | AQ5: =COUNTIFS('List Project'!D:D,"Desember",'List Project'!O:O,"Duta") -> 5 | AR5: =SUM(AF5:AQ5) -> 121 | AS5: =SUMIF('List Project'!O:O,"Duta",'List Project'!I:I) -> 3.317266e+11 | AU5: Novasi | AV5: =COUNTIFS('List Order'!C:C,"2024",'List Order'!B:B,"Januari",'List Order'!H:H,"Novasi",'List Order'!I:I,"Nomor Akses") -> 8 | AW5: =SUMIFS('List Order'!T:T,'List Order'!C:C,"2024",'List Order'!B:B,"Januari",'List Order'!H:H,"Novasi",'List Order'!I:I,"Nomor Akses") -> 14697500 | AX5: =COUNTIFS('List Order'!C:C,"2024",'List Order'!B:B,"Februari",'List Order'!H:H,"Novasi",'List Order'!I:I,"Nomor Akses") -> 1 | AY5: =SUMIFS('List Order'!T:T,'List Order'!C:C,"2024",'List Order'!B:B,"Februari",'List Order'!H:H,"Novasi",'List Order'!I:I,"Nomor Akses") -> 1500000 | AZ5: =COUNTIFS('List Order'!C:C,"2024",'List Order'!B:B,"Maret",'List Order'!H:H,"Novasi",'List Order'!I:I,"Nomor Akses") -> 2 | BA5: =SUMIFS('List Order'!T:T,'List Order'!C:C,"2024",'List Order'!B:B,"Maret",'List Order'!H:H,"Novasi",'List Order'!I:I,"Nomor Akses") -> 1500000 | BB5: =COUNTIFS('List Order'!C:C,"2024",'List Order'!B:B,"April",'List Order'!H:H,"Novasi",'List Order'!I:I,"Nomor Akses") -> 1 | BC5: =SUMIFS('List Order'!T:T,'List Order'!C:C,"2024",'List Order'!B:B,"April",'List Order'!H:H,"Novasi",'List Order'!I:I,"Nomor Akses") -> 1500000 | BD5: =COUNTIFS('List Order'!C:C,"2024",'List Order'!B:B,"Mei",'List Order'!H:H,"Novasi",'List Order'!I:I,"Nomor Akses") -> 5 | BE5: =SUMIFS('List Order'!T:T,'List Order'!C:C,"2024",'List Order'!B:B,"Mei",'List Order'!H:H,"Novasi",'List Order'!I:I,"Nomor Akses") -> 0 | BF5: =COUNTIFS('List Order'!C:C,"2024",'List Order'!B:B,"Juni",'List Order'!H:H,"Novasi",'List Order'!I:I,"Nomor Akses") -> 0 | BG5: =SUMIFS('List Order'!T:T,'List Order'!C:C,"2024",'List Order'!B:B,"Juni",'List Order'!H:H,"Novasi",'List Order'!I:I,"Nomor Akses") -> 0 | BH5: =COUNTIFS('List Order'!C:C,"2024",'List Order'!B:B,"Juli",'List Order'!H:H,"Novasi",'List Order'!I:I,"Nomor Akses") -> 1 | BI5: =SUMIFS('List Order'!T:T,'List Order'!C:C,"2024",'List Order'!B:B,"Juli",'List Order'!H:H,"Novasi",'List Order'!I:I,"Nomor Akses") -> 0 | BJ5: =COUNTIFS('List Order'!C:C,"2024",'List Order'!B:B,"Agustus",'List Order'!H:H,"Novasi",'List Order'!I:I,"Nomor Akses") -> 2 | BK5: =SUMIFS('List Order'!T:T,'List Order'!C:C,"2024",'List Order'!B:B,"Agustus",'List Order'!H:H,"Novasi",'List Order'!I:I,"Nomor Akses") -> 0 | BL5: =COUNTIFS('List Order'!C:C,"2024",'List Order'!B:B,"September",'List Order'!H:H,"Novasi",'List Order'!I:I,"Nomor Akses") -> 1 | BM5: =SUMIFS('List Order'!T:T,'List Order'!C:C,"2024",'List Order'!B:B,"September",'List Order'!H:H,"Novasi",'List Order'!I:I,"Nomor Akses") -> 0 | BN5: =COUNTIFS('List Order'!C:C,"2024",'List Order'!B:B,"Oktober",'List Order'!H:H,"Novasi",'List Order'!I:I,"Nomor Akses") -> 1 | BO5: =SUMIFS('List Order'!T:T,'List Order'!C:C,"2024",'List Order'!B:B,"Oktober",'List Order'!H:H,"Novasi",'List Order'!I:I,"Nomor Akses") -> 0 | BP5: =COUNTIFS('List Order'!C:C,"2024",'List Order'!B:B,"November",'List Order'!H:H,"Novasi",'List Order'!I:I,"Nomor Akses") -> 0 | BQ5: =SUMIFS('List Order'!T:T,'List Order'!C:C,"2024",'List Order'!B:B,"November",'List Order'!H:H,"Novasi",'List Order'!I:I,"Nomor Akses") -> 0 | BR5: =COUNTIFS('List Order'!C:C,"2024",'List Order'!B:B,"Desember",'List Order'!H:H,"Novasi",'List Order'!I:I,"Nomor Akses") -> 1 | BS5: =SUMIFS('List Order'!T:T,'List Order'!C:C,"2024",'List Order'!B:B,"Desember",'List Order'!H:H,"Novasi") -> 0
AE6: Gugum | AF6: =COUNTIFS('List Project'!D:D,"Januari",'List Project'!O:O,"Gugum") -> 9 | AG6: =COUNTIFS('List Project'!D:D,"Februari",'List Project'!O:O,"Gugum") -> 6 | AH6: =COUNTIFS('List Project'!D:D,"Maret",'List Project'!O:O,"Gugum") -> 9 | AI6: =COUNTIFS('List Project'!D:D,"April",'List Project'!O:O,"Gugum") -> 5 | AJ6: =COUNTIFS('List Project'!D:D,"Mei",'List Project'!O:O,"Gugum") -> 11 | AK6: =COUNTIFS('List Project'!D:D,"Juni",'List Project'!O:O,"Gugum") -> 5 | AL6: =COUNTIFS('List Project'!D:D,"Juli",'List Project'!O:O,"Gugum") -> 20 | AM6: =COUNTIFS('List Project'!D:D,"Agustus",'List Project'!O:O,"Gugum") -> 10 | AN6: =COUNTIFS('List Project'!D:D,"September",'List Project'!O:O,"Gugum") -> 8 | AO6: =COUNTIFS('List Project'!D:D,"Oktober",'List Project'!O:O,"Gugum") -> 6 | AP6: =COUNTIFS('List Project'!D:D,"November",'List Project'!O:O,"Gugum") -> 1 | AQ6: =COUNTIFS('List Project'!D:D,"Desember",'List Project'!O:O,"Gugum") -> 7 | AR6: =SUM(AF6:AQ6) -> 97 | AS6: =SUMIF('List Project'!O:O,"Gugum",'List Project'!I:I) -> 1.2903765e+12 | AU6: Modified | AV6: =COUNTIFS('List Order'!C:C,"2024",'List Order'!B:B,"Januari",'List Order'!H:H,"Modified",'List Order'!I:I,"Nomor Akses") -> 1 | AW6: =SUMIFS('List Order'!T:T,'List Order'!C:C,"2024",'List Order'!B:B,"Januari",'List Order'!H:H,"Modified",'List Order'!I:I,"Nomor Akses") -> 1500000 | AX6: =COUNTIFS('List Order'!C:C,"2024",'List Order'!B:B,"Februari",'List Order'!H:H,"Modified",'List Order'!I:I,"Nomor Akses") -> 0 | AY6: =SUMIFS('List Order'!T:T,'List Order'!C:C,"2024",'List Order'!B:B,"Februari",'List Order'!H:H,"Modified",'List Order'!I:I,"Nomor Akses") -> 0 | AZ6: =COUNTIFS('List Order'!C:C,"2024",'List Order'!B:B,"Maret",'List Order'!H:H,"Modified",'List Order'!I:I,"Nomor Akses") -> 0 | BA6: =SUMIFS('List Order'!T:T,'List Order'!C:C,"2024",'List Order'!B:B,"Maret",'List Order'!H:H,"Modified",'List Order'!I:I,"Nomor Akses") -> 0 | BB6: =COUNTIFS('List Order'!C:C,"2024",'List Order'!B:B,"April",'List Order'!H:H,"Modified",'List Order'!I:I,"Nomor Akses") -> 0 | BC6: =SUMIFS('List Order'!T:T,'List Order'!C:C,"2024",'List Order'!B:B,"April",'List Order'!H:H,"Modified",'List Order'!I:I,"Nomor Akses") -> 0 | BD6: =COUNTIFS('List Order'!C:C,"2024",'List Order'!B:B,"Mei",'List Order'!H:H,"Modified",'List Order'!I:I,"Nomor Akses") -> 1 | BE6: =SUMIFS('List Order'!T:T,'List Order'!C:C,"2024",'List Order'!B:B,"Mei",'List Order'!H:H,"Modified",'List Order'!I:I,"Nomor Akses") -> 0 | BF6: =COUNTIFS('List Order'!C:C,"2024",'List Order'!B:B,"Juni",'List Order'!H:H,"Modified",'List Order'!I:I,"Nomor Akses") -> 1 | BG6: =SUMIFS('List Order'!T:T,'List Order'!C:C,"2024",'List Order'!B:B,"Juni",'List Order'!H:H,"Modified",'List Order'!I:I,"Nomor Akses") -> 0 | BH6: =COUNTIFS('List Order'!C:C,"2024",'List Order'!B:B,"Juni",'List Order'!H:H,"Modified",'List Order'!I:I,"Nomor Akses") -> 1 | BI6: =SUMIFS('List Order'!T:T,'List Order'!C:C,"2024",'List Order'!B:B,"Juli",'List Order'!H:H,"Modified",'List Order'!I:I,"Nomor Akses") -> 0 | BJ6: =COUNTIFS('List Order'!C:C,"2024",'List Order'!B:B,"Agustus",'List Order'!H:H,"Modified",'List Order'!I:I,"Nomor Akses") -> 0 | BK6: =SUMIFS('List Order'!T:T,'List Order'!C:C,"2024",'List Order'!B:B,"Agustus",'List Order'!H:H,"Modified",'List Order'!I:I,"Nomor Akses") -> 0 | BL6: =COUNTIFS('List Order'!C:C,"2024",'List Order'!B:B,"September",'List Order'!H:H,"Modified",'List Order'!I:I,"Nomor Akses") -> 0 | BM6: =SUMIFS('List Order'!T:T,'List Order'!C:C,"2024",'List Order'!B:B,"September",'List Order'!H:H,"Modified",'List Order'!I:I,"Nomor Akses") -> 0 | BN6: =COUNTIFS('List Order'!C:C,"2024",'List Order'!B:B,"Oktober",'List Order'!H:H,"Modified",'List Order'!I:I,"Nomor Akses") -> 2 | BO6: =SUMIFS('List Order'!T:T,'List Order'!C:C,"2024",'List Order'!B:B,"Oktober",'List Order'!H:H,"Modified",'List Order'!I:I,"Nomor Akses") -> 0 | BP6: =COUNTIFS('List Order'!C:C,"2024",'List Order'!B:B,"November",'List Order'!H:H,"Modified",'List Order'!I:I,"Nomor Akses") -> 0 | BQ6: =SUMIFS('List Order'!T:T,'List Order'!C:C,"2024",'List Order'!B:B,"November",'List Order'!H:H,"Modified",'List Order'!I:I,"Nomor Akses") -> 0 | BR6: =COUNTIFS('List Order'!C:C,"2024",'List Order'!B:B,"Desember",'List Order'!H:H,"Modified",'List Order'!I:I,"Nomor Akses") -> 0 | BS6: =SUMIFS('List Order'!T:T,'List Order'!C:C,"2024",'List Order'!B:B,"Desember",'List Order'!H:H,"Modified") -> 0
AE7: CRM Revenue | AF7: =SUMIFS('List Project'!I:I,'List Project'!D:D,"Januari",'List Project'!F:F,"CRM") -> 1.4836587e+11 | AG7: =SUMIFS('List Project'!I:I,'List Project'!D:D,"Februari",'List Project'!F:F,"CRM") -> 8.7567997e+10 | AH7: =SUMIFS('List Project'!I:I,'List Project'!D:D,"Maret",'List Project'!F:F,"CRM") -> 145799747591 | AI7: =SUMIFS('List Project'!I:I,'List Project'!D:D,"April",'List Project'!F:F,"CRM") -> 8682353274 | AJ7: =SUMIFS('List Project'!I:I,'List Project'!D:D,"Mei",'List Project'!F:F,"CRM") -> 113902049174 | AK7: =SUMIFS('List Project'!I:I,'List Project'!D:D,"Juni",'List Project'!F:F,"CRM") -> 23771281911 | AL7: =SUMIFS('List Project'!I:I,'List Project'!D:D,"Juli",'List Project'!F:F,"CRM") -> 21863193244 | AM7: =SUMIFS('List Project'!I:I,'List Project'!D:D,"Agustus",'List Project'!F:F,"CRM") -> 91198761295 | AN7: =SUMIFS('List Project'!I:I,'List Project'!D:D,"September",'List Project'!F:F,"CRM") -> 1.2913041e+11 | AO7: =SUMIFS('List Project'!I:I,'List Project'!D:D,"Oktober",'List Project'!F:F,"CRM") -> 3.0048593e+11 | AP7: =SUMIFS('List Project'!I:I,'List Project'!D:D,"November",'List Project'!F:F,"CRM") -> 44627615761 | AQ7: =SUMIFS('List Project'!I:I,'List Project'!D:D,"Desember",'List Project'!F:F,"CRM") -> 1005724372947 | AR7: =SUM(AF7:AQ7) -> 2.1211196e+12 | AU7: Dismentle | AV7: =COUNTIFS('List Order'!C:C,"2024",'List Order'!B:B,"Januari",'List Order'!H:H,"Dismantle",'List Order'!I:I,"Nomor Akses") -> 4 | AW7: =SUMIFS('List Order'!T:T,'List Order'!C:C,"2024",'List Order'!B:B,"Januari",'List Order'!H:H,"Dismantle",'List Order'!I:I,"Nomor Akses") -> 8000000 | AX7: =COUNTIFS('List Order'!C:C,"2024",'List Order'!B:B,"Februari",'List Order'!H:H,"Dismantle",'List Order'!I:I,"Nomor Akses") -> 3 | AY7: =SUMIFS('List Order'!T:T,'List Order'!C:C,"2024",'List Order'!B:B,"Februari",'List Order'!H:H,"Dismantle",'List Order'!I:I,"Nomor Akses") -> 4580000 | AZ7: =COUNTIFS('List Order'!C:C,"2024",'List Order'!B:B,"Maret",'List Order'!H:H,"Dismantle",'List Order'!I:I,"Nomor Akses") -> 2 | BA7: =SUMIFS('List Order'!T:T,'List Order'!C:C,"2024",'List Order'!B:B,"Maret",'List Order'!H:H,"Dismantle",'List Order'!I:I,"Nomor Akses") -> 4500000 | BB7: =COUNTIFS('List Order'!C:C,"2024",'List Order'!B:B,"April",'List Order'!H:H,"Dismantle",'List Order'!I:I,"Nomor Akses") -> 1 | BC7: =SUMIFS('List Order'!T:T,'List Order'!C:C,"2024",'List Order'!B:B,"April",'List Order'!H:H,"Dismantle",'List Order'!I:I,"Nomor Akses") -> 2325000 | BD7: =COUNTIFS('List Order'!C:C,"2024",'List Order'!B:B,"Mei",'List Order'!H:H,"Dismantle",'List Order'!I:I,"Nomor Akses") -> 6 | BE7: =SUMIFS('List Order'!T:T,'List Order'!C:C,"2024",'List Order'!B:B,"Mei",'List Order'!H:H,"Dismantle",'List Order'!I:I,"Nomor Akses") -> 9000000 | BF7: =COUNTIFS('List Order'!C:C,"2024",'List Order'!B:B,"Juni",'List Order'!H:H,"Dismantle",'List Order'!I:I,"Nomor Akses") -> 1 | BG7: =SUMIFS('List Order'!T:T,'List Order'!C:C,"2024",'List Order'!B:B,"Juni",'List Order'!H:H,"Dismantle",'List Order'!I:I,"Nomor Akses") -> 0 | BH7: =COUNTIFS('List Order'!C:C,"2024",'List Order'!B:B,"Juli",'List Order'!H:H,"Dismantle",'List Order'!I:I,"Nomor Akses") -> 4 | BI7: =SUMIFS('List Order'!T:T,'List Order'!C:C,"2024",'List Order'!B:B,"Juli",'List Order'!H:H,"Dismantle",'List Order'!I:I,"Nomor Akses") -> 0 | BJ7: =COUNTIFS('List Order'!C:C,"2024",'List Order'!B:B,"Agustus",'List Order'!H:H,"Dismantle",'List Order'!I:I,"Nomor Akses") -> 2 | BK7: =SUMIFS('List Order'!T:T,'List Order'!C:C,"2024",'List Order'!B:B,"Agustus",'List Order'!H:H,"Dismantle",'List Order'!I:I,"Nomor Akses") -> 0 | BL7: =COUNTIFS('List Order'!C:C,"2024",'List Order'!B:B,"September",'List Order'!H:H,"Dismantle",'List Order'!I:I,"Nomor Akses") -> 4 | BM7: =SUMIFS('List Order'!T:T,'List Order'!C:C,"2024",'List Order'!B:B,"September",'List Order'!H:H,"Dismantle",'List Order'!I:I,"Nomor Akses") -> 0 | BN7: =COUNTIFS('List Order'!C:C,"2024",'List Order'!B:B,"Oktober",'List Order'!H:H,"Dismantle",'List Order'!I:I,"Nomor Akses") -> 2 | BO7: =SUMIFS('List Order'!T:T,'List Order'!C:C,"2024",'List Order'!B:B,"Oktober",'List Order'!H:H,"Dismantle",'List Order'!I:I,"Nomor Akses") -> 29000000 | BP7: =COUNTIFS('List Order'!C:C,"2024",'List Order'!B:B,"November",'List Order'!H:H,"Dismantle",'List Order'!I:I,"Nomor Akses") -> 4 | BQ7: =SUMIFS('List Order'!T:T,'List Order'!C:C,"2024",'List Order'!B:B,"November",'List Order'!H:H,"Dismantle",'List Order'!I:I,"Nomor Akses") -> 3000000 | BR7: =COUNTIFS('List Order'!C:C,"2024",'List Order'!B:B,"Desember",'List Order'!H:H,"Dismantle",'List Order'!I:I,"Nomor Akses") -> 3 | BS7: =SUMIFS('List Order'!T:T,'List Order'!C:C,"2024",'List Order'!B:B,"Desember",'List Order'!H:H,"Dismantle") -> 1160000
AE8: SSO Revenue | AF8: =SUMIFS('List Project'!I:I,'List Project'!D:D,"Januari",'List Project'!F:F,"SSO") -> 0 | AG8: =SUMIFS('List Project'!I:I,'List Project'!D:D,"Februari",'List Project'!F:F,"SSO") -> 15923259005 | AH8: =SUMIFS('List Project'!I:I,'List Project'!D:D,"Maret",'List Project'!F:F,"SSO") -> 0 | AI8: =SUMIFS('List Project'!I:I,'List Project'!D:D,"April",'List Project'!F:F,"SSO") -> 0 | AJ8: =SUMIFS('List Project'!I:I,'List Project'!D:D,"Mei",'List Project'!F:F,"SSO") -> 0 | AK8: =SUMIFS('List Project'!I:I,'List Project'!D:D,"Juni",'List Project'!F:F,"SSO") -> 0 | AL8: =SUMIFS('List Project'!I:I,'List Project'!D:D,"Juli",'List Project'!F:F,"SSO") -> 0 | AM8: =SUMIFS('List Project'!I:I,'List Project'!D:D,"Agustus",'List Project'!F:F,"SSO") -> 0 | AN8: =SUMIFS('List Project'!I:I,'List Project'!D:D,"September",'List Project'!F:F,"SSO") -> 0 | AO8: =SUMIFS('List Project'!I:I,'List Project'!D:D,"Oktober",'List Project'!F:F,"SSO") -> 0 | AP8: =SUMIFS('List Project'!I:I,'List Project'!D:D,"November",'List Project'!F:F,"SSO") -> 0 | AQ8: =SUMIFS('List Project'!I:I,'List Project'!D:D,"Desember",'List Project'!F:F,"SSO") -> 0 | AR8: =SUM(AF8:AQ8) -> 15923259005 | AU8: CONNECTIVITY | AV8: =COUNTIFS('List Order'!B:B,"Januari",'List Order'!I:I,"Connectivity",'List Order'!C:C,"2024") -> 13 | AW8: =SUM(AW9:AW10) -> 78037527 | AX8: =COUNTIFS('List Order'!B:B,"Februari",'List Order'!I:I,"Connectivity",'List Order'!C:C,"2024") -> 15 | AY8: =SUM(AY9:AY10) -> 25330500 | AZ8: =COUNTIFS('List Order'!B:B,"Maret",'List Order'!I:I,"Connectivity",'List Order'!C:C,"2024") -> 14 | BA8: =SUM(BA9:BA10) -> 319788030 | BB8: =COUNTIFS('List Order'!B:B,"April",'List Order'!I:I,"Connectivity",'List Order'!C:C,"2024") -> 11 | BC8: =SUM(BC9:BC10) -> 138805130 | BD8: =COUNTIFS('List Order'!B:B,"Mei",'List Order'!I:I,"Connectivity",'List Order'!C:C,"2024") -> 14 | BE8: =SUM(BE9:BE10) -> 3993000 | BF8: =COUNTIFS('List Order'!B:B,"Juni",'List Order'!I:I,"Connectivity",'List Order'!C:C,"2024") -> 22 | BG8: =SUM(BG9:BG10) -> 0 | BH8: =COUNTIFS('List Order'!B:B,"Juli",'List Order'!I:I,"Connectivity",'List Order'!C:C,"2024") -> 41 | BI8: =SUM(BI9:BI10) -> 0 | BJ8: =COUNTIFS('List Order'!B:B,"Agustus",'List Order'!I:I,"Connectivity",'List Order'!C:C,"2024") -> 14 | BK8: =SUM(BK9:BK10) -> 0 | BL8: =COUNTIFS('List Order'!B:B,"September",'List Order'!I:I,"Connectivity",'List Order'!C:C,"2024") -> 7 | BM8: =SUM(BM9:BM10) -> 0 | BN8: =COUNTIFS('List Order'!B:B,"Oktober",'List Order'!I:I,"Connectivity",'List Order'!C:C,"2024") -> 14 | BO8: =SUM(BO9:BO10) -> 35345000 | BP8: =COUNTIFS('List Order'!B:B,"November",'List Order'!I:I,"Connectivity",'List Order'!C:C,"2024") -> 12 | BQ8: =SUM(BQ9:BQ10) -> 8811100 | BR8: =COUNTIFS('List Order'!B:B,"Desember",'List Order'!I:I,"Connectivity",'List Order'!C:C,"2024") -> 13 | BS8: =SUM(BS9:BS10) -> 24803400
AE9: Nomor Akses Revenue | AF9: =SUMIFS('List Project'!I:I,'List Project'!D:D,"Januari",'List Project'!F:F,"Nomor Akses") -> 4872456036 | AG9: =SUMIFS('List Project'!I:I,'List Project'!D:D,"Februari",'List Project'!F:F,"Nomor Akses") -> 3578559600 | AH9: =SUMIFS('List Project'!I:I,'List Project'!D:D,"Maret",'List Project'!F:F,"Nomor Akses") -> 13046898263 | AI9: =SUMIFS('List Project'!I:I,'List Project'!D:D,"April",'List Project'!F:F,"Nomor Akses") -> 12462714000 | AJ9: =SUMIFS('List Project'!I:I,'List Project'!D:D,"Mei",'List Project'!F:F,"Nomor Akses") -> 3711305454 | AK9: =SUMIFS('List Project'!I:I,'List Project'!D:D,"Juni",'List Project'!F:F,"Nomor Akses") -> 615968000 | AL9: =SUMIFS('List Project'!I:I,'List Project'!D:D,"Juli",'List Project'!F:F,"Nomor Akses") -> 3330786126 | AM9: =SUMIFS('List Project'!I:I,'List Project'!D:D,"Agustus",'List Project'!F:F,"Nomor Akses") -> 3942230000 | AN9: =SUMIFS('List Project'!I:I,'List Project'!D:D,"September",'List Project'!F:F,"Nomor Akses") -> 916340000 | AO9: =SUMIFS('List Project'!I:I,'List Project'!D:D,"Oktober",'List Project'!F:F,"Nomor Akses") -> 984468000 | AP9: =SUMIFS('List Project'!I:I,'List Project'!D:D,"November",'List Project'!F:F,"Nomor Akses") -> 1378504000 | AQ9: =SUMIFS('List Project'!I:I,'List Project'!D:D,"Desember",'List Project'!F:F,"Nomor Akses") -> 269000000 | AR9: =SUM(AF9:AQ9) -> 49109229479 | AU9: PSB | AV9: =COUNTIFS('List Order'!C:C,"2024",'List Order'!B:B,"Januari",'List Order'!H:H,"PSB",'List Order'!I:I,"Connectivity") -> 9 | AW9: =SUMIFS('List Order'!T:T,'List Order'!C:C,"2024",'List Order'!B:B,"Januari",'List Order'!H:H,"PSB",'List Order'!I:I,"Connectivity") -> 41652567 | AX9: =COUNTIFS('List Order'!C:C,"2024",'List Order'!B:B,"Februari",'List Order'!H:H,"PSB",'List Order'!I:I,"Connectivity") -> 7 | AY9: =SUMIFS('List Order'!T:T,'List Order'!C:C,"2024",'List Order'!B:B,"Februari",'List Order'!H:H,"PSB",'List Order'!I:I,"Connectivity") -> 13332500 | AZ9: =COUNTIFS('List Order'!C:C,"2024",'List Order'!B:B,"Maret",'List Order'!H:H,"PSB",'List Order'!I:I,"Connectivity") -> 4 | BA9: =SUMIFS('List Order'!T:T,'List Order'!C:C,"2024",'List Order'!B:B,"Maret",'List Order'!H:H,"PSB",'List Order'!I:I,"Connectivity") -> 9067000 | BB9: =COUNTIFS('List Order'!C:C,"2024",'List Order'!B:B,"April",'List Order'!H:H,"PSB",'List Order'!I:I,"Connectivity") -> 4 | BC9: =SUMIFS('List Order'!T:T,'List Order'!C:C,"2024",'List Order'!B:B,"April",'List Order'!H:H,"PSB",'List Order'!I:I,"Connectivity") -> 8327613 | BD9: =COUNTIFS('List Order'!C:C,"2024",'List Order'!B:B,"Mei",'List Order'!H:H,"PSB",'List Order'!I:I,"Connectivity") -> 6 | BE9: =SUMIFS('List Order'!T:T,'List Order'!C:C,"2024",'List Order'!B:B,"Mei",'List Order'!H:H,"PSB",'List Order'!I:I,"Connectivity") -> 3993000 | BF9: =COUNTIFS('List Order'!C:C,"2024",'List Order'!B:B,"Juni",'List Order'!H:H,"PSB",'List Order'!I:I,"Connectivity") -> 7 | BG9: =SUMIFS('List Order'!T:T,'List Order'!C:C,"2024",'List Order'!B:B,"Juni",'List Order'!H:H,"PSB",'List Order'!I:I,"Connectivity") -> 0 | BH9: =COUNTIFS('List Order'!C:C,"2024",'List Order'!B:B,"Juli",'List Order'!H:H,"PSB",'List Order'!I:I,"Connectivity") -> 12 | BI9: =SUMIFS('List Order'!T:T,'List Order'!C:C,"2024",'List Order'!B:B,"Juli",'List Order'!H:H,"PSB",'List Order'!I:I,"Connectivity") -> 0 | BJ9: =COUNTIFS('List Order'!C:C,"2024",'List Order'!B:B,"Agustus",'List Order'!H:H,"PSB",'List Order'!I:I,"Connectivity") -> 1 | BK9: =SUMIFS('List Order'!T:T,'List Order'!C:C,"2024",'List Order'!B:B,"Agustus",'List Order'!H:H,"PSB",'List Order'!I:I,"Connectivity") -> 0 | BL9: =COUNTIFS('List Order'!C:C,"2024",'List Order'!B:B,"September",'List Order'!H:H,"PSB",'List Order'!I:I,"Connectivity") -> 0 | BM9: =SUMIFS('List Order'!T:T,'List Order'!C:C,"2024",'List Order'!B:B,"September",'List Order'!H:H,"PSB",'List Order'!I:I,"Connectivity") -> 0 | BN9: =COUNTIFS('List Order'!C:C,"2024",'List Order'!B:B,"Oktober",'List Order'!H:H,"PSB",'List Order'!I:I,"Connectivity") -> 5 | BO9: =SUMIFS('List Order'!T:T,'List Order'!C:C,"2024",'List Order'!B:B,"Oktober",'List Order'!H:H,"PSB",'List Order'!I:I,"Connectivity") -> 35345000 | BP9: =COUNTIFS('List Order'!C:C,"2024",'List Order'!B:B,"November",'List Order'!H:H,"PSB",'List Order'!I:I,"Connectivity") -> 6 | BQ9: =SUMIFS('List Order'!T:T,'List Order'!C:C,"2024",'List Order'!B:B,"November",'List Order'!H:H,"PSB",'List Order'!I:I,"Connectivity") -> 5731100 | BR9: =COUNTIFS('List Order'!C:C,"2024",'List Order'!B:B,"Desember",'List Order'!H:H,"PSB",'List Order'!I:I,"Connectivity") -> 9 | BS9: =SUMIFS('List Order'!T:T,'List Order'!C:C,"2024",'List Order'!B:B,"Desember",'List Order'!H:H,"PSB",'List Order'!I:I,"Connectivity") -> 22196800
AU10: Upgrade | AV10: =COUNTIFS('List Order'!C:C,"2024",'List Order'!B:B,"Januari",'List Order'!H:H,"Upgrade",'List Order'!I:I,"Connectivity") -> 3 | AW10: =SUMIFS('List Order'!T:T,'List Order'!C:C,"2024",'List Order'!B:B,"Januari",'List Order'!H:H,"Upgrade",'List Order'!I:I,"Connectivity") -> 36384960 | AX10: =COUNTIFS('List Order'!C:C,"2024",'List Order'!B:B,"Februari",'List Order'!H:H,"Upgrade",'List Order'!I:I,"Connectivity") -> 3 | AY10: =SUMIFS('List Order'!T:T,'List Order'!C:C,"2024",'List Order'!B:B,"Februari",'List Order'!H:H,"Upgrade",'List Order'!I:I,"Connectivity") -> 11998000 | AZ10: =COUNTIFS('List Order'!C:C,"2024",'List Order'!B:B,"Maret",'List Order'!H:H,"Upgrade",'List Order'!I:I,"Connectivity") -> 5 | BA10: =SUMIFS('List Order'!T:T,'List Order'!C:C,"2024",'List Order'!B:B,"Maret",'List Order'!H:H,"Upgrade",'List Order'!I:I,"Connectivity") -> 310721030 | BB10: =COUNTIFS('List Order'!C:C,"2024",'List Order'!B:B,"April",'List Order'!H:H,"Upgrade",'List Order'!I:I,"Connectivity") -> 5 | BC10: =SUMIFS('List Order'!T:T,'List Order'!C:C,"2024",'List Order'!B:B,"April",'List Order'!H:H,"Upgrade",'List Order'!I:I,"Connectivity") -> 130477517 | BD10: =COUNTIFS('List Order'!C:C,"2024",'List Order'!B:B,"Mei",'List Order'!H:H,"Upgrade",'List Order'!I:I,"Connectivity") -> 3 | BE10: =SUMIFS('List Order'!T:T,'List Order'!C:C,"2024",'List Order'!B:B,"Mei",'List Order'!H:H,"Upgrade",'List Order'!I:I,"Connectivity") -> 0 | BF10: =COUNTIFS('List Order'!C:C,"2024",'List Order'!B:B,"Juni",'List Order'!H:H,"Upgrade",'List Order'!I:I,"Connectivity") -> 2 | BG10: =SUMIFS('List Order'!T:T,'List Order'!C:C,"2024",'List Order'!B:B,"Juni",'List Order'!H:H,"Upgrade",'List Order'!I:I,"Connectivity") -> 0 | BH10: =COUNTIFS('List Order'!C:C,"2024",'List Order'!B:B,"Juli",'List Order'!H:H,"Upgrade",'List Order'!I:I,"Connectivity") -> 0 | BI10: =SUMIFS('List Order'!T:T,'List Order'!C:C,"2024",'List Order'!B:B,"Juli",'List Order'!H:H,"Upgrade",'List Order'!I:I,"Connectivity") -> 0 | BJ10: =COUNTIFS('List Order'!C:C,"2024",'List Order'!B:B,"Agustus",'List Order'!H:H,"Upgrade",'List Order'!I:I,"Connectivity") -> 1 | BK10: =SUMIFS('List Order'!T:T,'List Order'!C:C,"2024",'List Order'!B:B,"Agustus",'List Order'!H:H,"Upgrade",'List Order'!I:I,"Connectivity") -> 0 | BL10: =COUNTIFS('List Order'!C:C,"2024",'List Order'!B:B,"September",'List Order'!H:H,"Upgrade",'List Order'!I:I,"Connectivity") -> 3 | BM10: =SUMIFS('List Order'!T:T,'List Order'!C:C,"2024",'List Order'!B:B,"September",'List Order'!H:H,"Upgrade",'List Order'!I:I,"Connectivity") -> 0 | BN10: =COUNTIFS('List Order'!C:C,"2024",'List Order'!B:B,"Oktober",'List Order'!H:H,"Upgrade",'List Order'!I:I,"Connectivity") -> 3 | BO10: =SUMIFS('List Order'!T:T,'List Order'!C:C,"2024",'List Order'!B:B,"Oktober",'List Order'!H:H,"Upgrade",'List Order'!I:I,"Connectivity") -> 0 | BP10: =COUNTIFS('List Order'!C:C,"2024",'List Order'!B:B,"November",'List Order'!H:H,"Upgrade",'List Order'!I:I,"Connectivity") -> 3 | BQ10: =SUMIFS('List Order'!T:T,'List Order'!C:C,"2024",'List Order'!B:B,"November",'List Order'!H:H,"Upgrade",'List Order'!I:I,"Connectivity") -> 3080000 | BR10: =COUNTIFS('List Order'!C:C,"2024",'List Order'!B:B,"Desember",'List Order'!H:H,"Upgrade",'List Order'!I:I,"Connectivity") -> 2 | BS10: =SUMIFS('List Order'!T:T,'List Order'!C:C,"2024",'List Order'!B:B,"Desember",'List Order'!H:H,"Upgrade",'List Order'!I:I,"Connectivity") -> 2606600
AF11: Januari | AG11: Februari | AH11: Maret | AI11: April | AJ11: Mei | AK11: Juni | AL11: Juli | AM11: Agustus | AN11: September | AO11: Oktober | AP11: November | AQ11: Desember | AU11: Downgrade | AV11: =COUNTIFS('List Order'!C:C,"2024",'List Order'!B:B,"Januari",'List Order'!H:H,"Downgrade",'List Order'!I:I,"Connectivity") -> 0 | AW11: =SUMIFS('List Order'!T:T,'List Order'!C:C,"2024",'List Order'!B:B,"Januari",'List Order'!H:H,"Downgrade",'List Order'!I:I,"Connectivity") -> 0 | AX11: =COUNTIFS('List Order'!C:C,"2024",'List Order'!B:B,"Februari",'List Order'!H:H,"Downgrade",'List Order'!I:I,"Connectivity") -> 0 | AY11: =SUMIFS('List Order'!T:T,'List Order'!C:C,"2024",'List Order'!B:B,"Februari",'List Order'!H:H,"Downgrade",'List Order'!I:I,"Connectivity") -> 0 | AZ11: =COUNTIFS('List Order'!C:C,"2024",'List Order'!B:B,"Maret",'List Order'!H:H,"Downgrade",'List Order'!I:I,"Connectivity") -> 1 | BA11: =SUMIFS('List Order'!T:T,'List Order'!C:C,"2024",'List Order'!B:B,"Maret",'List Order'!H:H,"Downgrade",'List Order'!I:I,"Connectivity") -> 108600000 | BB11: =COUNTIFS('List Order'!C:C,"2024",'List Order'!B:B,"April",'List Order'!H:H,"Downgrade",'List Order'!I:I,"Connectivity") -> 1 | BC11: =SUMIFS('List Order'!T:T,'List Order'!C:C,"2024",'List Order'!B:B,"April",'List Order'!H:H,"Downgrade",'List Order'!I:I,"Connectivity") -> 0 | BD11: =COUNTIFS('List Order'!C:C,"2024",'List Order'!B:B,"Mei",'List Order'!H:H,"Downgrade",'List Order'!I:I,"Connectivity") -> 0 | BE11: =SUMIFS('List Order'!T:T,'List Order'!C:C,"2024",'List Order'!B:B,"Mei",'List Order'!H:H,"Downgrade",'List Order'!I:I,"Connectivity") -> 0 | BF11: =COUNTIFS('List Order'!C:C,"2024",'List Order'!B:B,"Juni",'List Order'!H:H,"Downgrade",'List Order'!I:I,"Connectivity") -> 9 | BG11: =SUMIFS('List Order'!T:T,'List Order'!C:C,"2024",'List Order'!B:B,"Juni",'List Order'!H:H,"Downgrade",'List Order'!I:I,"Connectivity") -> 0 | BH11: =COUNTIFS('List Order'!C:C,"2024",'List Order'!B:B,"Juli",'List Order'!H:H,"Downgrade",'List Order'!I:I,"Connectivity") -> 2 | BI11: =SUMIFS('List Order'!T:T,'List Order'!C:C,"2024",'List Order'!B:B,"Juli",'List Order'!H:H,"Downgrade",'List Order'!I:I,"Connectivity") -> 384210277 | BJ11: =COUNTIFS('List Order'!C:C,"2024",'List Order'!B:B,"Agustus",'List Order'!H:H,"Downgrade",'List Order'!I:I,"Connectivity") -> 0 | BK11: =SUMIFS('List Order'!T:T,'List Order'!C:C,"2024",'List Order'!B:B,"Agustus",'List Order'!H:H,"Downgrade",'List Order'!I:I,"Connectivity") -> 0 | BL11: =COUNTIFS('List Order'!C:C,"2024",'List Order'!B:B,"September",'List Order'!H:H,"Downgrade",'List Order'!I:I,"Connectivity") -> 0 | BM11: =SUMIFS('List Order'!T:T,'List Order'!C:C,"2024",'List Order'!B:B,"September",'List Order'!H:H,"Downgrade",'List Order'!I:I,"Connectivity") -> 0 | BN11: =COUNTIFS('List Order'!C:C,"2024",'List Order'!B:B,"Oktober",'List Order'!H:H,"Downgrade",'List Order'!I:I,"Connectivity") -> 1 | BO11: =SUMIFS('List Order'!T:T,'List Order'!C:C,"2024",'List Order'!B:B,"Oktober",'List Order'!H:H,"Downgrade",'List Order'!I:I,"Connectivity") -> 0 | BP11: =COUNTIFS('List Order'!C:C,"2024",'List Order'!B:B,"November",'List Order'!H:H,"Downgrade",'List Order'!I:I,"Connectivity") -> 0 | BQ11: =SUMIFS('List Order'!T:T,'List Order'!C:C,"2024",'List Order'!B:B,"November",'List Order'!H:H,"Downgrade",'List Order'!I:I,"Connectivity") -> 0 | BR11: =COUNTIFS('List Order'!C:C,"2024",'List Order'!B:B,"Desember",'List Order'!H:H,"Downgrade",'List Order'!I:I,"Connectivity") -> 0 | BS11: =SUMIFS('List Order'!T:T,'List Order'!C:C,"2024",'List Order'!B:B,"Desember",'List Order'!H:H,"Downgrade",'List Order'!I:I,"Connectivity") -> 0
AE12: Revenue Project | AF12: =SUMIF('List Project'!D:D,"Januari",'List Project'!I:I) -> 1.5323832e+11 | AG12: =SUMIF('List Project'!D:D,"Februari",'List Project'!I:I) -> 1.0706982e+11 | AH12: =SUMIF('List Project'!D:D,"Maret",'List Project'!I:I) -> 158846645854 | AI12: =SUMIF('List Project'!D:D,"April",'List Project'!I:I) -> 21145067274 | AJ12: =SUMIF('List Project'!D:D,"Mei",'List Project'!I:I) -> 117613354628 | AK12: =SUMIF('List Project'!D:D,"Juni",'List Project'!I:I) -> 24387249911 | AL12: =SUMIF('List Project'!D:D,"Juli",'List Project'!I:I) -> 25193979370 | AM12: =SUMIF('List Project'!D:D,"Agustus",'List Project'!I:I) -> 95140991295 | AN12: =SUMIF('List Project'!D:D,"September",'List Project'!I:I) -> 1.3015875e+11 | AO12: =SUMIF('List Project'!D:D,"Oktober",'List Project'!I:I) -> 3.0147039e+11 | AP12: =SUMIF('List Project'!D:D,"November",'List Project'!I:I) -> 46006119761 | AQ12: =SUMIF('List Project'!D:D,"Desember",'List Project'!I:I) -> 1005993372947 | AU12: Dismentle | AV12: =COUNTIFS('List Order'!C:C,"2024",'List Order'!B:B,"Januari",'List Order'!H:H,"Dismantle",'List Order'!I:I,"Connectivity") -> 1 | AW12: =SUMIFS('List Order'!T:T,'List Order'!C:C,"2024",'List Order'!B:B,"Januari",'List Order'!H:H,"Dismantle",'List Order'!I:I,"Connectivity") -> 308750 | AX12: =COUNTIFS('List Order'!C:C,"2024",'List Order'!B:B,"Februari",'List Order'!H:H,"Dismantle",'List Order'!I:I,"Connectivity") -> 5 | AY12: =SUMIFS('List Order'!T:T,'List Order'!C:C,"2024",'List Order'!B:B,"Februari",'List Order'!H:H,"Dismantle",'List Order'!I:I,"Connectivity") -> 70338070 | AZ12: =COUNTIFS('List Order'!C:C,"2024",'List Order'!B:B,"Maret",'List Order'!H:H,"Dismantle",'List Order'!I:I,"Connectivity") -> 3 | BA12: =SUMIFS('List Order'!T:T,'List Order'!C:C,"2024",'List Order'!B:B,"Maret",'List Order'!H:H,"Dismantle",'List Order'!I:I,"Connectivity") -> 12690000 | BB12: =COUNTIFS('List Order'!C:C,"2024",'List Order'!B:B,"April",'List Order'!H:H,"Dismantle",'List Order'!I:I,"Connectivity") -> 1 | BC12: =SUMIFS('List Order'!T:T,'List Order'!C:C,"2024",'List Order'!B:B,"April",'List Order'!H:H,"Dismantle",'List Order'!I:I,"Connectivity") -> 2325000 | BD12: =COUNTIFS('List Order'!C:C,"2024",'List Order'!B:B,"Mei",'List Order'!H:H,"Dismantle",'List Order'!I:I,"Connectivity") -> 5 | BE12: =SUMIFS('List Order'!T:T,'List Order'!C:C,"2024",'List Order'!B:B,"Mei",'List Order'!H:H,"Dismantle",'List Order'!I:I,"Connectivity") -> 4522000 | BF12: =COUNTIFS('List Order'!C:C,"2024",'List Order'!B:B,"Januari",'List Order'!H:H,"Dismantle",'List Order'!I:I,"Connectivity") -> 1 | BG12: =SUMIFS('List Order'!T:T,'List Order'!C:C,"2024",'List Order'!B:B,"Juni",'List Order'!H:H,"Dismantle",'List Order'!I:I,"Connectivity") -> 0 | BH12: =COUNTIFS('List Order'!C:C,"2024",'List Order'!B:B,"Juli",'List Order'!H:H,"Dismantle",'List Order'!I:I,"Connectivity") -> 6 | BI12: =SUMIFS('List Order'!T:T,'List Order'!C:C,"2024",'List Order'!B:B,"Juli",'List Order'!H:H,"Dismantle",'List Order'!I:I,"Connectivity") -> 0 | BJ12: =COUNTIFS('List Order'!C:C,"2024",'List Order'!B:B,"Agustus",'List Order'!H:H,"Dismantle",'List Order'!I:I,"Connectivity") -> 3 | BK12: =SUMIFS('List Order'!T:T,'List Order'!C:C,"2024",'List Order'!B:B,"Agustus",'List Order'!H:H,"Dismantle",'List Order'!I:I,"Connectivity") -> 0 | BL12: =COUNTIFS('List Order'!C:C,"2024",'List Order'!B:B,"September",'List Order'!H:H,"Dismantle",'List Order'!I:I,"Connectivity") -> 0 | BM12: =SUMIFS('List Order'!T:T,'List Order'!C:C,"2024",'List Order'!B:B,"September",'List Order'!H:H,"Dismantle",'List Order'!I:I,"Connectivity") -> 0 | BN12: =COUNTIFS('List Order'!C:C,"2024",'List Order'!B:B,"Oktober",'List Order'!H:H,"Dismantle",'List Order'!I:I,"Connectivity") -> 4 | BO12: =SUMIFS('List Order'!T:T,'List Order'!C:C,"2024",'List Order'!B:B,"Oktober",'List Order'!H:H,"Dismantle",'List Order'!I:I,"Connectivity") -> 12074523 | BP12: =COUNTIFS('List Order'!C:C,"2024",'List Order'!B:B,"November",'List Order'!H:H,"Dismantle",'List Order'!I:I,"Connectivity") -> 3 | BQ12: =SUMIFS('List Order'!T:T,'List Order'!C:C,"2024",'List Order'!B:B,"November",'List Order'!H:H,"Dismantle",'List Order'!I:I,"Connectivity") -> 10466450 | BR12: =COUNTIFS('List Order'!C:C,"2024",'List Order'!B:B,"Desember",'List Order'!H:H,"Dismantle",'List Order'!I:I,"Connectivity") -> 1 | BS12: =SUMIFS('List Order'!T:T,'List Order'!C:C,"2024",'List Order'!B:B,"Desember",'List Order'!H:H,"Dismantle",'List Order'!I:I,"Connectivity") -> 0
AE13: CRM | AF13: =COUNTIFS('List Project'!C:C,"2024",'List Project'!D:D,"Januari",'List Project'!F:F,"CRM") -> 10 | AG13: =COUNTIFS('List Project'!C:C,"2024",'List Project'!D:D,"Februari",'List Project'!F:F,"CRM") -> 11 | AH13: =COUNTIFS('List Project'!C:C,"2024",'List Project'!D:D,"Maret",'List Project'!F:F,"CRM") -> 10 | AI13: =COUNTIFS('List Project'!C:C,"2024",'List Project'!D:D,"April",'List Project'!F:F,"CRM") -> 4 | AJ13: =COUNTIFS('List Project'!C:C,"2024",'List Project'!D:D,"Mei",'List Project'!F:F,"CRM") -> 11 | AK13: =COUNTIFS('List Project'!C:C,"2024",'List Project'!D:D,"Juni",'List Project'!F:F,"CRM") -> 3 | AL13: =COUNTIFS('List Project'!C:C,"2024",'List Project'!D:D,"Juli",'List Project'!F:F,"CRM") -> 6 | AM13: =COUNTIFS('List Project'!C:C,"2024",'List Project'!D:D,"Agustus",'List Project'!F:F,"CRM") -> 9 | AN13: =COUNTIFS('List Project'!C:C,"2024",'List Project'!D:D,"September",'List Project'!F:F,"CRM") -> 5 | AO13: =COUNTIFS('List Project'!C:C,"2024",'List Project'!D:D,"Oktober",'List Project'!F:F,"CRM") -> 8 | AP13: =COUNTIFS('List Project'!C:C,"2024",'List Project'!D:D,"November",'List Project'!F:F,"CRM") -> 3 | AQ13: =COUNTIFS('List Project'!C:C,"2024",'List Project'!D:D,"Desember",'List Project'!F:F,"CRM") -> 6 | AU13: IPPBX SIP TRUNK | AV13: =COUNTIFS('List Order'!B:B,"Januari",'List Order'!I:I,"IPPBX",'List Order'!C:C,"2024") -> 0 | AX13: =COUNTIFS('List Order'!B:B,"Februari",'List Order'!I:I,"IPPBX",'List Order'!C:C,"2024") -> 0 | AZ13: =COUNTIFS('List Order'!B:B,"Maret",'List Order'!I:I,"IPPBX",'List Order'!C:C,"2024") -> 0 | BB13: =COUNTIFS('List Order'!B:B,"April",'List Order'!I:I,"IPPBX",'List Order'!C:C,"2024") -> 1 | BD13: =COUNTIFS('List Order'!B:B,"Mei",'List Order'!I:I,"IPPBX",'List Order'!C:C,"2024") -> 0 | BF13: =COUNTIFS('List Order'!B:B,"Juni",'List Order'!I:I,"IPPBX",'List Order'!C:C,"2024") -> 2 | BH13: =COUNTIFS('List Order'!B:B,"Juli",'List Order'!I:I,"IPPBX",'List Order'!C:C,"2024") -> 0 | BJ13: =COUNTIFS('List Order'!B:B,"Agustus",'List Order'!I:I,"IPPBX",'List Order'!C:C,"2024") -> 0 | BL13: =COUNTIFS('List Order'!B:B,"September",'List Order'!I:I,"IPPBX",'List Order'!C:C,"2024") -> 1 | BN13: =COUNTIFS('List Order'!B:B,"Oktober",'List Order'!I:I,"IPPBX",'List Order'!C:C,"2024") -> 1 | BP13: =COUNTIFS('List Order'!B:B,"November",'List Order'!I:I,"IPPBX",'List Order'!C:C,"2024") -> 0 | BR13: =COUNTIFS('List Order'!B:B,"Desember",'List Order'!I:I,"IPPBX",'List Order'!C:C,"2024") -> 0
AE14: SSO | AF14: =COUNTIFS('List Project'!C:C,"2024",'List Project'!D:D,"Januari",'List Project'!F:F,"SSO") -> 0 | AG14: =COUNTIFS('List Project'!C:C,"2024",'List Project'!D:D,"Februari",'List Project'!F:F,"SSO") -> 1 | AH14: =COUNTIFS('List Project'!C:C,"2024",'List Project'!D:D,"Maret",'List Project'!F:F,"SSO") -> 0 | AI14: =COUNTIFS('List Project'!C:C,"2024",'List Project'!D:D,"April",'List Project'!F:F,"SSO") -> 0 | AJ14: =COUNTIFS('List Project'!C:C,"2024",'List Project'!D:D,"Mei",'List Project'!F:F,"SSO") -> 0 | AK14: =COUNTIFS('List Project'!C:C,"2024",'List Project'!D:D,"Juni",'List Project'!F:F,"SSO") -> 0 | AL14: =COUNTIFS('List Project'!C:C,"2024",'List Project'!D:D,"Juli",'List Project'!F:F,"SSO") -> 0 | AM14: =COUNTIFS('List Project'!C:C,"2024",'List Project'!D:D,"Agustus",'List Project'!F:F,"SSO") -> 0 | AN14: =COUNTIFS('List Project'!C:C,"2024",'List Project'!D:D,"September",'List Project'!F:F,"SSO") -> 0 | AO14: =COUNTIFS('List Project'!C:C,"2024",'List Project'!D:D,"Oktober",'List Project'!F:F,"SSO") -> 0 | AP14: =COUNTIFS('List Project'!C:C,"2024",'List Project'!D:D,"November",'List Project'!F:F,"SSO") -> 0 | AQ14: =COUNTIFS('List Project'!C:C,"2024",'List Project'!D:D,"Desember",'List Project'!F:F,"SSO") -> 0 | AU14: PSB | AV14: =COUNTIFS('List Order'!C:C,"2024",'List Order'!B:B,"Januari",'List Order'!H:H,"PSB",'List Order'!I:I,"IPPBX") -> 0 | AW14: =SUMIFS('List Order'!T:T,'List Order'!C:C,"2024",'List Order'!B:B,"Januari",'List Order'!H:H,"PSB",'List Order'!I:I,"IPPBX") -> 0 | AX14: =COUNTIFS('List Order'!C:C,"2024",'List Order'!B:B,"Februari",'List Order'!H:H,"PSB",'List Order'!I:I,"IPPBX") -> 0 | AY14: =SUMIFS('List Order'!T:T,'List Order'!C:C,"2024",'List Order'!B:B,"Februari",'List Order'!H:H,"PSB",'List Order'!I:I,"IPPBX") -> 0 | AZ14: =COUNTIFS('List Order'!C:C,"2024",'List Order'!B:B,"Maret",'List Order'!H:H,"PSB",'List Order'!I:I,"IPPBX") -> 0 | BA14: =SUMIFS('List Order'!T:T,'List Order'!C:C,"2024",'List Order'!B:B,"Maret",'List Order'!H:H,"PSB",'List Order'!I:I,"IPPBX") -> 0 | BB14: =COUNTIFS('List Order'!C:C,"2024",'List Order'!B:B,"April",'List Order'!H:H,"PSB",'List Order'!I:I,"IPPBX") -> 0 | BC14: =SUMIFS('List Order'!T:T,'List Order'!C:C,"2024",'List Order'!B:B,"April",'List Order'!H:H,"PSB",'List Order'!I:I,"IPPBX") -> 0 | BD14: =COUNTIFS('List Order'!C:C,"2024",'List Order'!B:B,"Mei",'List Order'!H:H,"PSB",'List Order'!I:I,"IPPBX") -> 0 | BE14: =SUMIFS('List Order'!T:T,'List Order'!C:C,"2024",'List Order'!B:B,"Mei",'List Order'!H:H,"PSB",'List Order'!I:I,"IPPBX") -> 0 | BF14: =COUNTIFS('List Order'!C:C,"2024",'List Order'!B:B,"Juni",'List Order'!H:H,"PSB",'List Order'!I:I,"IPPBX") -> 2 | BG14: =SUMIFS('List Order'!T:T,'List Order'!C:C,"2024",'List Order'!B:B,"Juni",'List Order'!H:H,"PSB",'List Order'!I:I,"IPPBX") -> 0 | BH14: =COUNTIFS('List Order'!C:C,"2024",'List Order'!B:B,"Juli",'List Order'!H:H,"PSB",'List Order'!I:I,"IPPBX") -> 0 | BI14: =SUMIFS('List Order'!T:T,'List Order'!C:C,"2024",'List Order'!B:B,"Juli",'List Order'!H:H,"PSB",'List Order'!I:I,"IPPBX") -> 0 | BJ14: =COUNTIFS('List Order'!C:C,"2024",'List Order'!B:B,"Agustus",'List Order'!H:H,"PSB",'List Order'!I:I,"IPPBX") -> 0 | BK14: =SUMIFS('List Order'!T:T,'List Order'!C:C,"2024",'List Order'!B:B,"Agustus",'List Order'!H:H,"PSB",'List Order'!I:I,"IPPBX") -> 0 | BL14: =COUNTIFS('List Order'!C:C,"2024",'List Order'!B:B,"September",'List Order'!H:H,"PSB",'List Order'!I:I,"IPPBX") -> 0 | BM14: =SUMIFS('List Order'!T:T,'List Order'!C:C,"2024",'List Order'!B:B,"September",'List Order'!H:H,"PSB",'List Order'!I:I,"IPPBX") -> 0 | BN14: =COUNTIFS('List Order'!C:C,"2024",'List Order'!B:B,"Oktober",'List Order'!H:H,"PSB",'List Order'!I:I,"IPPBX") -> 1 | BO14: =SUMIFS('List Order'!T:T,'List Order'!C:C,"2024",'List Order'!B:B,"Oktober",'List Order'!H:H,"PSB",'List Order'!I:I,"IPPBX") -> 4115000 | BP14: =COUNTIFS('List Order'!C:C,"2024",'List Order'!B:B,"November",'List Order'!H:H,"PSB",'List Order'!I:I,"IPPBX") -> 0 | BQ14: =SUMIFS('List Order'!T:T,'List Order'!C:C,"2024",'List Order'!B:B,"November",'List Order'!H:H,"PSB",'List Order'!I:I,"IPPBX") -> 0 | BR14: =COUNTIFS('List Order'!C:C,"2024",'List Order'!B:B,"Desember",'List Order'!H:H,"PSB",'List Order'!I:I,"IPPBX") -> 0 | BS14: =SUMIFS('List Order'!T:T,'List Order'!C:C,"2024",'List Order'!B:B,"Desember",'List Order'!H:H,"PSB",'List Order'!I:I,"IPPBX") -> 0
AE15: Nomor Akses | AF15: =COUNTIFS('List Project'!C:C,"2024",'List Project'!D:D,"Januari",'List Project'!F:F,"Nomor Akses") -> 8 | AG15: =COUNTIFS('List Project'!C:C,"2024",'List Project'!D:D,"Februari",'List Project'!F:F,"Nomor Akses") -> 5 | AH15: =COUNTIFS('List Project'!C:C,"2024",'List Project'!D:D,"Maret",'List Project'!F:F,"Nomor Akses") -> 7 | AI15: =COUNTIFS('List Project'!C:C,"2024",'List Project'!D:D,"April",'List Project'!F:F,"Nomor Akses") -> 7 | AJ15: =COUNTIFS('List Project'!C:C,"2024",'List Project'!D:D,"Mei",'List Project'!F:F,"Nomor Akses") -> 9 | AK15: =COUNTIFS('List Project'!C:C,"2024",'List Project'!D:D,"Juni",'List Project'!F:F,"Nomor Akses") -> 3 | AL15: =COUNTIFS('List Project'!C:C,"2024",'List Project'!D:D,"Juli",'List Project'!F:F,"Nomor Akses") -> 5 | AM15: =COUNTIFS('List Project'!C:C,"2024",'List Project'!D:D,"Agustus",'List Project'!F:F,"Nomor Akses") -> 6 | AN15: =COUNTIFS('List Project'!C:C,"2024",'List Project'!D:D,"September",'List Project'!F:F,"Nomor Akses") -> 3 | AO15: =COUNTIFS('List Project'!C:C,"2024",'List Project'!D:D,"Oktober",'List Project'!F:F,"Nomor Akses") -> 2 | AP15: =COUNTIFS('List Project'!C:C,"2024",'List Project'!D:D,"November",'List Project'!F:F,"Nomor Akses") -> 4 | AQ15: =COUNTIFS('List Project'!C:C,"2024",'List Project'!D:D,"Desember",'List Project'!F:F,"Nomor Akses") -> 1 | AU15: Upgrade | AV15: =COUNTIFS('List Order'!C:C,"2024",'List Order'!B:B,"Januari",'List Order'!H:H,"Upgrade",'List Order'!I:I,"IPPBX") -> 0 | AW15: =SUMIFS('List Order'!T:T,'List Order'!C:C,"2024",'List Order'!B:B,"Januari",'List Order'!H:H,"Upgrade",'List Order'!I:I,"IPPBX") -> 0 | AX15: =COUNTIFS('List Order'!C:C,"2024",'List Order'!B:B,"Februari",'List Order'!H:H,"Upgrade",'List Order'!I:I,"IPPBX") -> 0 | AY15: =SUMIFS('List Order'!T:T,'List Order'!C:C,"2024",'List Order'!B:B,"Februari",'List Order'!H:H,"Upgrade",'List Order'!I:I,"IPPBX") -> 0 | AZ15: =COUNTIFS('List Order'!C:C,"2024",'List Order'!B:B,"Maret",'List Order'!H:H,"Upgrade",'List Order'!I:I,"IPPBX") -> 0 | BA15: =SUMIFS('List Order'!T:T,'List Order'!C:C,"2024",'List Order'!B:B,"Maret",'List Order'!H:H,"Upgrade",'List Order'!I:I,"IPPBX") -> 0 | BB15: =COUNTIFS('List Order'!C:C,"2024",'List Order'!B:B,"April",'List Order'!H:H,"Upgrade",'List Order'!I:I,"IPPBX") -> 0 | BC15: =SUMIFS('List Order'!T:T,'List Order'!C:C,"2024",'List Order'!B:B,"April",'List Order'!H:H,"Upgrade",'List Order'!I:I,"IPPBX") -> 0 | BD15: =COUNTIFS('List Order'!C:C,"2024",'List Order'!B:B,"Mei",'List Order'!H:H,"Upgrade",'List Order'!I:I,"IPPBX") -> 0 | BE15: =SUMIFS('List Order'!T:T,'List Order'!C:C,"2024",'List Order'!B:B,"Mei",'List Order'!H:H,"Upgrade",'List Order'!I:I,"IPPBX") -> 0 | BF15: =COUNTIFS('List Order'!C:C,"2024",'List Order'!B:B,"Juni",'List Order'!H:H,"Upgrade",'List Order'!I:I,"IPPBX") -> 0 | BG15: =SUMIFS('List Order'!T:T,'List Order'!C:C,"2024",'List Order'!B:B,"Juni",'List Order'!H:H,"Upgrade",'List Order'!I:I,"IPPBX") -> 0 | BH15: =COUNTIFS('List Order'!C:C,"2024",'List Order'!B:B,"Juli",'List Order'!H:H,"Upgrade",'List Order'!I:I,"IPPBX") -> 0 | BI15: =SUMIFS('List Order'!T:T,'List Order'!C:C,"2024",'List Order'!B:B,"Juli",'List Order'!H:H,"Upgrade",'List Order'!I:I,"IPPBX") -> 0 | BJ15: =COUNTIFS('List Order'!C:C,"2024",'List Order'!B:B,"Agustus",'List Order'!H:H,"Upgrade",'List Order'!I:I,"IPPBX") -> 0 | BK15: =SUMIFS('List Order'!T:T,'List Order'!C:C,"2024",'List Order'!B:B,"Agustus",'List Order'!H:H,"Upgrade",'List Order'!I:I,"IPPBX") -> 0 | BL15: =COUNTIFS('List Order'!C:C,"2024",'List Order'!B:B,"September",'List Order'!H:H,"Upgrade",'List Order'!I:I,"IPPBX") -> 0 | BM15: =SUMIFS('List Order'!T:T,'List Order'!C:C,"2024",'List Order'!B:B,"September",'List Order'!H:H,"Upgrade",'List Order'!I:I,"IPPBX") -> 0 | BN15: =COUNTIFS('List Order'!C:C,"2024",'List Order'!B:B,"Oktober",'List Order'!H:H,"Upgrade",'List Order'!I:I,"IPPBX") -> 0 | BO15: =SUMIFS('List Order'!T:T,'List Order'!C:C,"2024",'List Order'!B:B,"Oktober",'List Order'!H:H,"Upgrade",'List Order'!I:I,"IPPBX") -> 0 | BP15: =COUNTIFS('List Order'!C:C,"2024",'List Order'!B:B,"November",'List Order'!H:H,"Upgrade",'List Order'!I:I,"IPPBX") -> 0 | BQ15: =SUMIFS('List Order'!T:T,'List Order'!C:C,"2024",'List Order'!B:B,"November",'List Order'!H:H,"Upgrade",'List Order'!I:I,"IPPBX") -> 0 | BR15: =COUNTIFS('List Order'!C:C,"2024",'List Order'!B:B,"Desember",'List Order'!H:H,"Upgrade",'List Order'!I:I,"IPPBX") -> 0 | BS15: =SUMIFS('List Order'!T:T,'List Order'!C:C,"2024",'List Order'!B:B,"Desember",'List Order'!H:H,"Upgrade",'List Order'!I:I,"IPPBX") -> 0
AU16: Downgrade | AV16: =COUNTIFS('List Order'!C:C,"2024",'List Order'!B:B,"Januari",'List Order'!H:H,"Downgrade",'List Order'!I:I,"IPPBX") -> 0 | AW16: =SUMIFS('List Order'!T:T,'List Order'!C:C,"2024",'List Order'!B:B,"Januari",'List Order'!H:H,"Downgrade",'List Order'!I:I,"IPPBX") -> 0 | AX16: =COUNTIFS('List Order'!C:C,"2024",'List Order'!B:B,"Februari",'List Order'!H:H,"Downgrade",'List Order'!I:I,"IPPBX") -> 0 | AY16: =SUMIFS('List Order'!T:T,'List Order'!C:C,"2024",'List Order'!B:B,"Februari",'List Order'!H:H,"Downgrade",'List Order'!I:I,"IPPBX") -> 0 | AZ16: =COUNTIFS('List Order'!C:C,"2024",'List Order'!B:B,"Maret",'List Order'!H:H,"Downgrade",'List Order'!I:I,"IPPBX") -> 0 | BA16: =SUMIFS('List Order'!T:T,'List Order'!C:C,"2024",'List Order'!B:B,"Maret",'List Order'!H:H,"Downgrade",'List Order'!I:I,"IPPBX") -> 0 | BB16: =COUNTIFS('List Order'!C:C,"2024",'List Order'!B:B,"April",'List Order'!H:H,"Downgrade",'List Order'!I:I,"IPPBX") -> 0 | BC16: =SUMIFS('List Order'!T:T,'List Order'!C:C,"2024",'List Order'!B:B,"April",'List Order'!H:H,"Downgrade",'List Order'!I:I,"IPPBX") -> 0 | BD16: =COUNTIFS('List Order'!C:C,"2024",'List Order'!B:B,"Mei",'List Order'!H:H,"Downgrade",'List Order'!I:I,"IPPBX") -> 0 | BE16: =SUMIFS('List Order'!T:T,'List Order'!C:C,"2024",'List Order'!B:B,"Mei",'List Order'!H:H,"Downgrade",'List Order'!I:I,"IPPBX") -> 0 | BF16: =COUNTIFS('List Order'!C:C,"2024",'List Order'!B:B,"Juni",'List Order'!H:H,"Downgrade",'List Order'!I:I,"IPPBX") -> 0 | BG16: =SUMIFS('List Order'!T:T,'List Order'!C:C,"2024",'List Order'!B:B,"Juni",'List Order'!H:H,"Downgrade",'List Order'!I:I,"IPPBX") -> 0 | BH16: =COUNTIFS('List Order'!C:C,"2024",'List Order'!B:B,"Juli",'List Order'!H:H,"Downgrade",'List Order'!I:I,"IPPBX") -> 0 | BI16: =SUMIFS('List Order'!T:T,'List Order'!C:C,"2024",'List Order'!B:B,"Juli",'List Order'!H:H,"Downgrade",'List Order'!I:I,"IPPBX") -> 0 | BJ16: =COUNTIFS('List Order'!C:C,"2024",'List Order'!B:B,"Agustus",'List Order'!H:H,"Downgrade",'List Order'!I:I,"IPPBX") -> 0 | BK16: =SUMIFS('List Order'!T:T,'List Order'!C:C,"2024",'List Order'!B:B,"Agustus",'List Order'!H:H,"Downgrade",'List Order'!I:I,"IPPBX") -> 0 | BL16: =COUNTIFS('List Order'!C:C,"2024",'List Order'!B:B,"September",'List Order'!H:H,"Downgrade",'List Order'!I:I,"IPPBX") -> 0 | BM16: =SUMIFS('List Order'!T:T,'List Order'!C:C,"2024",'List Order'!B:B,"September",'List Order'!H:H,"Downgrade",'List Order'!I:I,"IPPBX") -> 0 | BN16: =COUNTIFS('List Order'!C:C,"2024",'List Order'!B:B,"Oktober",'List Order'!H:H,"Downgrade",'List Order'!I:I,"IPPBX") -> 0 | BO16: =SUMIFS('List Order'!T:T,'List Order'!C:C,"2024",'List Order'!B:B,"Oktober",'List Order'!H:H,"Downgrade",'List Order'!I:I,"IPPBX") -> 0 | BP16: =COUNTIFS('List Order'!C:C,"2024",'List Order'!B:B,"November",'List Order'!H:H,"Downgrade",'List Order'!I:I,"IPPBX") -> 0 | BQ16: =SUMIFS('List Order'!T:T,'List Order'!C:C,"2024",'List Order'!B:B,"November",'List Order'!H:H,"Downgrade",'List Order'!I:I,"IPPBX") -> 0 | BR16: =COUNTIFS('List Order'!C:C,"2024",'List Order'!B:B,"Desember",'List Order'!H:H,"Downgrade",'List Order'!I:I,"IPPBX") -> 0 | BS16: =SUMIFS('List Order'!T:T,'List Order'!C:C,"2024",'List Order'!B:B,"Desember",'List Order'!H:H,"Downgrade",'List Order'!I:I,"IPPBX") -> 0
AF17: Total Project | AG17: Done | AH17: OGP | AI17: Revenue | AL17: Adi | AM17: Dwi | AN17: Duta | AO17: Gugum | AU17: Dismentle | AV17: =COUNTIFS('List Order'!C:C,"2024",'List Order'!B:B,"Januari",'List Order'!H:H,"Dismantle",'List Order'!I:I,"IPPBX") -> 0 | AW17: =SUMIFS('List Order'!T:T,'List Order'!C:C,"2024",'List Order'!B:B,"Januari",'List Order'!H:H,"Dismantle",'List Order'!I:I,"IPPBX") -> 0 | AX17: =COUNTIFS('List Order'!C:C,"2024",'List Order'!B:B,"Februari",'List Order'!H:H,"Dismantle",'List Order'!I:I,"IPPBX") -> 0 | AY17: =SUMIFS('List Order'!T:T,'List Order'!C:C,"2024",'List Order'!B:B,"Februari",'List Order'!H:H,"Dismantle",'List Order'!I:I,"IPPBX") -> 0 | AZ17: =COUNTIFS('List Order'!C:C,"2024",'List Order'!B:B,"Maret",'List Order'!H:H,"Dismantle",'List Order'!I:I,"IPPBX") -> 0 | BA17: =SUMIFS('List Order'!T:T,'List Order'!C:C,"2024",'List Order'!B:B,"Maret",'List Order'!H:H,"Dismantle",'List Order'!I:I,"IPPBX") -> 0 | BB17: =COUNTIFS('List Order'!C:C,"2024",'List Order'!B:B,"April",'List Order'!H:H,"Dismantle",'List Order'!I:I,"IPPBX") -> 1 | BC17: =SUMIFS('List Order'!T:T,'List Order'!C:C,"2024",'List Order'!B:B,"April",'List Order'!H:H,"Dismantle",'List Order'!I:I,"IPPBX") -> 2300000 | BD17: =COUNTIFS('List Order'!C:C,"2024",'List Order'!B:B,"Mei",'List Order'!H:H,"Dismantle",'List Order'!I:I,"IPPBX") -> 0 | BE17: =SUMIFS('List Order'!T:T,'List Order'!C:C,"2024",'List Order'!B:B,"Mei",'List Order'!H:H,"Dismantle",'List Order'!I:I,"IPPBX") -> 0 | BF17: =COUNTIFS('List Order'!C:C,"2024",'List Order'!B:B,"Juni",'List Order'!H:H,"Dismantle",'List Order'!I:I,"IPPBX") -> 0 | BG17: =SUMIFS('List Order'!T:T,'List Order'!C:C,"2024",'List Order'!B:B,"Juni",'List Order'!H:H,"Dismantle",'List Order'!I:I,"IPPBX") -> 0 | BH17: =COUNTIFS('List Order'!C:C,"2024",'List Order'!B:B,"Juli",'List Order'!H:H,"Dismantle",'List Order'!I:I,"IPPBX") -> 0 | BI17: =SUMIFS('List Order'!T:T,'List Order'!C:C,"2024",'List Order'!B:B,"Juli",'List Order'!H:H,"Dismantle",'List Order'!I:I,"IPPBX") -> 0 | BJ17: =COUNTIFS('List Order'!C:C,"2024",'List Order'!B:B,"Agustus",'List Order'!H:H,"Dismantle",'List Order'!I:I,"IPPBX") -> 0 | BK17: =SUMIFS('List Order'!T:T,'List Order'!C:C,"2024",'List Order'!B:B,"Agustus",'List Order'!H:H,"Dismantle",'List Order'!I:I,"IPPBX") -> 0 | BL17: =COUNTIFS('List Order'!C:C,"2024",'List Order'!B:B,"September",'List Order'!H:H,"Dismantle",'List Order'!I:I,"IPPBX") -> 1 | BM17: =SUMIFS('List Order'!T:T,'List Order'!C:C,"2024",'List Order'!B:B,"September",'List Order'!H:H,"Dismantle",'List Order'!I:I,"IPPBX") -> 0 | BN17: =COUNTIFS('List Order'!C:C,"2024",'List Order'!B:B,"Oktober",'List Order'!H:H,"Dismantle",'List Order'!I:I,"IPPBX") -> 0 | BO17: =SUMIFS('List Order'!T:T,'List Order'!C:C,"2024",'List Order'!B:B,"Oktober",'List Order'!H:H,"Dismantle",'List Order'!I:I,"IPPBX") -> 0 | BP17: =COUNTIFS('List Order'!C:C,"2024",'List Order'!B:B,"November",'List Order'!H:H,"Dismantle",'List Order'!I:I,"IPPBX") -> 0 | BQ17: =SUMIFS('List Order'!T:T,'List Order'!C:C,"2024",'List Order'!B:B,"November",'List Order'!H:H,"Dismantle",'List Order'!I:I,"IPPBX") -> 0 | BR17: =COUNTIFS('List Order'!C:C,"2024",'List Order'!B:B,"Desember",'List Order'!H:H,"Dismantle",'List Order'!I:I,"IPPBX") -> 0 | BS17: =SUMIFS('List Order'!T:T,'List Order'!C:C,"2024",'List Order'!B:B,"Desember",'List Order'!H:H,"Dismantle",'List Order'!I:I,"IPPBX") -> 0
AE18: Adi | AF18: =SUM(AF3:AQ3) -> 12 | AG18: =COUNTIFS('List Project'!C:C,"2024",'List Project'!P:P,"Done",'List Project'!O:O,"Adi") -> 10 | AH18: =COUNTIFS('List Project'!C:C,"2024",'List Project'!P:P,"OGP",'List Project'!O:O,"Adi") -> 0 | AI18: =SUMIF('List Project'!O:O,"Adi",'List Project'!I:I) -> 124082524515 | AK18: Project | AL18: =AF18 -> 12 | AM18: =AF19 -> 85 | AN18: =AF20 -> 121 | AO18: =AF21 -> 97 | AU18: Colocation/ cndc | AV18: =COUNTIFS('List Order'!B:B,"Januari",'List Order'!I:I,"Colocation",'List Order'!C:C,"2024") -> 0 | AX18: =COUNTIFS('List Order'!B:B,"Februari",'List Order'!I:I,"Colocation",'List Order'!C:C,"2024") -> 0 | AZ18: =COUNTIFS('List Order'!B:B,"Maret",'List Order'!I:I,"Colocation",'List Order'!C:C,"2024") -> 0 | BB18: =COUNTIFS('List Order'!B:B,"April",'List Order'!I:I,"Colocation",'List Order'!C:C,"2024") -> 0 | BD18: =COUNTIFS('List Order'!B:B,"Mei",'List Order'!I:I,"Colocation",'List Order'!C:C,"2024") -> 1 | BF18: =COUNTIFS('List Order'!B:B,"Juni",'List Order'!I:I,"Colocation",'List Order'!C:C,"2024") -> 2 | BH18: =COUNTIFS('List Order'!B:B,"Juli",'List Order'!I:I,"Colocation",'List Order'!C:C,"2024") -> 0 | BJ18: =COUNTIFS('List Order'!B:B,"Agustus",'List Order'!I:I,"Colocation",'List Order'!C:C,"2024") -> 0 | BL18: =COUNTIFS('List Order'!B:B,"September",'List Order'!I:I,"Colocation",'List Order'!C:C,"2024") -> 0 | BN18: =COUNTIFS('List Order'!B:B,"Oktober",'List Order'!I:I,"Colocation",'List Order'!C:C,"2024") -> 0 | BP18: =COUNTIFS('List Order'!B:B,"November",'List Order'!I:I,"Colocation",'List Order'!C:C,"2024") -> 0 | BR18: =COUNTIFS('List Order'!B:B,"Desember",'List Order'!I:I,"Colocation",'List Order'!C:C,"2024") -> 0
AE19: Dwi | AF19: =SUM(AF4:AQ4) -> 85 | AG19: =COUNTIFS('List Project'!C:C,"2024",'List Project'!P:P,"Done",'List Project'!O:O,"Dwi") -> 38 | AH19: =COUNTIFS('List Project'!C:C,"2024",'List Project'!P:P,"OGP",'List Project'!O:O,"Dwi") -> 0 | AI19: =SUMIF('List Project'!O:O,"Dwi",'List Project'!I:I) -> 4.398677e+11 | AK19: Project Done | AL19: =AG18 -> 10 | AM19: =AG19 -> 38 | AN19: =AG20 -> 62 | AO19: =AG21 -> 40 | AU19: PSB | AV19: =COUNTIFS('List Order'!C:C,"2024",'List Order'!B:B,"Januari",'List Order'!H:H,"PSB",'List Order'!I:I,"Colocation") -> 0 | AW19: =SUMIFS('List Order'!T:T,'List Order'!C:C,"2024",'List Order'!B:B,"Januari",'List Order'!H:H,"PSB",'List Order'!I:I,"Colocation") -> 0 | AX19: =COUNTIFS('List Order'!C:C,"2024",'List Order'!B:B,"Februari",'List Order'!H:H,"PSB",'List Order'!I:I,"Colocation") -> 0 | AY19: =SUMIFS('List Order'!T:T,'List Order'!C:C,"2024",'List Order'!B:B,"Februari",'List Order'!H:H,"PSB",'List Order'!I:I,"Colocation") -> 0 | AZ19: =COUNTIFS('List Order'!C:C,"2024",'List Order'!B:B,"Maret",'List Order'!H:H,"PSB",'List Order'!I:I,"Colocation") -> 0 | BA19: =SUMIFS('List Order'!T:T,'List Order'!C:C,"2024",'List Order'!B:B,"Maret",'List Order'!H:H,"PSB",'List Order'!I:I,"Colocation") -> 0 | BB19: =COUNTIFS('List Order'!C:C,"2024",'List Order'!B:B,"April",'List Order'!H:H,"PSB",'List Order'!I:I,"Colocation") -> 0 | BC19: =SUMIFS('List Order'!T:T,'List Order'!C:C,"2024",'List Order'!B:B,"April",'List Order'!H:H,"PSB",'List Order'!I:I,"Colocation") -> 0 | BD19: =COUNTIFS('List Order'!C:C,"2024",'List Order'!B:B,"Mei",'List Order'!H:H,"PSB",'List Order'!I:I,"Colocation") -> 0 | BE19: =SUMIFS('List Order'!T:T,'List Order'!C:C,"2024",'List Order'!B:B,"Mei",'List Order'!H:H,"PSB",'List Order'!I:I,"Colocation") -> 0 | BF19: =COUNTIFS('List Order'!C:C,"2024",'List Order'!B:B,"Juni",'List Order'!H:H,"PSB",'List Order'!I:I,"Colocation") -> 1 | BG19: =SUMIFS('List Order'!T:T,'List Order'!C:C,"2024",'List Order'!B:B,"Juni",'List Order'!H:H,"PSB",'List Order'!I:I,"Colocation") -> 0 | BH19: =COUNTIFS('List Order'!C:C,"2024",'List Order'!B:B,"Juli",'List Order'!H:H,"PSB",'List Order'!I:I,"Colocation") -> 0 | BI19: =SUMIFS('List Order'!T:T,'List Order'!C:C,"2024",'List Order'!B:B,"Juli",'List Order'!H:H,"PSB",'List Order'!I:I,"Colocation") -> 0 | BJ19: =COUNTIFS('List Order'!C:C,"2024",'List Order'!B:B,"Agustus",'List Order'!H:H,"PSB",'List Order'!I:I,"Colocation") -> 0 | BK19: =SUMIFS('List Order'!T:T,'List Order'!C:C,"2024",'List Order'!B:B,"Agustus",'List Order'!H:H,"PSB",'List Order'!I:I,"Colocation") -> 0 | BL19: =COUNTIFS('List Order'!C:C,"2024",'List Order'!B:B,"September",'List Order'!H:H,"PSB",'List Order'!I:I,"Colocation") -> 0 | BM19: =SUMIFS('List Order'!T:T,'List Order'!C:C,"2024",'List Order'!B:B,"September",'List Order'!H:H,"PSB",'List Order'!I:I,"Colocation") -> 0 | BN19: =COUNTIFS('List Order'!C:C,"2024",'List Order'!B:B,"Oktober",'List Order'!H:H,"PSB",'List Order'!I:I,"Colocation") -> 0 | BO19: =SUMIFS('List Order'!T:T,'List Order'!C:C,"2024",'List Order'!B:B,"Oktober",'List Order'!H:H,"PSB",'List Order'!I:I,"Colocation") -> 0 | BP19: =COUNTIFS('List Order'!C:C,"2024",'List Order'!B:B,"November",'List Order'!H:H,"PSB",'List Order'!I:I,"Colocation") -> 0 | BQ19: =SUMIFS('List Order'!T:T,'List Order'!C:C,"2024",'List Order'!B:B,"November",'List Order'!H:H,"PSB",'List Order'!I:I,"Colocation") -> 0 | BR19: =COUNTIFS('List Order'!C:C,"2024",'List Order'!B:B,"Desember",'List Order'!H:H,"PSB",'List Order'!I:I,"Colocation") -> 0 | BS19: =SUMIFS('List Order'!T:T,'List Order'!C:C,"2024",'List Order'!B:B,"Desember",'List Order'!H:H,"PSB",'List Order'!I:I,"Colocation") -> 0
AE20: Duta | AF20: =SUM(AF5:AQ5) -> 121 | AG20: =COUNTIFS('List Project'!C:C,"2024",'List Project'!P:P,"Done",'List Project'!O:O,"Duta") -> 62 | AH20: =COUNTIFS('List Project'!C:C,"2024",'List Project'!P:P,"OGP",'List Project'!O:O,"Duta") -> 0 | AI20: =SUMIF('List Project'!O:O,"Duta",'List Project'!I:I) -> 3.317266e+11 | AK20: Project OGP | AL20: =AH18 -> 0 | AM20: =AH19 -> 0 | AN20: =AH20 -> 0 | AO20: =AH21 -> 0 | AU20: Dismentle | AV20: =COUNTIFS('List Order'!C:C,"2024",'List Order'!B:B,"Januari",'List Order'!H:H,"Dismantle",'List Order'!I:I,"Colocation") -> 0 | AW20: =SUMIFS('List Order'!T:T,'List Order'!C:C,"2024",'List Order'!B:B,"Januari",'List Order'!H:H,"Dismantle",'List Order'!I:I,"Colocation") -> 0 | AX20: =COUNTIFS('List Order'!C:C,"2024",'List Order'!B:B,"Februari",'List Order'!H:H,"Dismantle",'List Order'!I:I,"Colocation") -> 0 | AY20: =SUMIFS('List Order'!T:T,'List Order'!C:C,"2024",'List Order'!B:B,"Februari",'List Order'!H:H,"Dismantle",'List Order'!I:I,"Colocation") -> 0 | AZ20: =COUNTIFS('List Order'!C:C,"2024",'List Order'!B:B,"Maret",'List Order'!H:H,"Dismantle",'List Order'!I:I,"Colocation") -> 0 | BA20: =SUMIFS('List Order'!T:T,'List Order'!C:C,"2024",'List Order'!B:B,"Maret",'List Order'!H:H,"Dismantle",'List Order'!I:I,"Colocation") -> 0 | BB20: =COUNTIFS('List Order'!C:C,"2024",'List Order'!B:B,"April",'List Order'!H:H,"Dismantle",'List Order'!I:I,"Colocation") -> 0 | BC20: =SUMIFS('List Order'!T:T,'List Order'!C:C,"2024",'List Order'!B:B,"April",'List Order'!H:H,"Dismantle",'List Order'!I:I,"Colocation") -> 0 | BD20: =COUNTIFS('List Order'!C:C,"2024",'List Order'!B:B,"Mei",'List Order'!H:H,"Dismantle",'List Order'!I:I,"Colocation") -> 1 | BE20: =SUMIFS('List Order'!T:T,'List Order'!C:C,"2024",'List Order'!B:B,"Mei",'List Order'!H:H,"Dismantle",'List Order'!I:I,"Colocation") -> 0 | BF20: =COUNTIFS('List Order'!C:C,"2024",'List Order'!B:B,"Juni",'List Order'!H:H,"Dismantle",'List Order'!I:I,"Colocation") -> 1 | BG20: =SUMIFS('List Order'!T:T,'List Order'!C:C,"2024",'List Order'!B:B,"Juni",'List Order'!H:H,"Dismantle",'List Order'!I:I,"Colocation") -> 0 | BH20: =COUNTIFS('List Order'!C:C,"2024",'List Order'!B:B,"Juli",'List Order'!H:H,"Dismantle",'List Order'!I:I,"Colocation") -> 0 | BI20: =SUMIFS('List Order'!T:T,'List Order'!C:C,"2024",'List Order'!B:B,"Juli",'List Order'!H:H,"Dismantle",'List Order'!I:I,"Colocation") -> 0 | BJ20: =COUNTIFS('List Order'!C:C,"2024",'List Order'!B:B,"Agustus",'List Order'!H:H,"Dismantle",'List Order'!I:I,"Colocation") -> 0 | BK20: =SUMIFS('List Order'!T:T,'List Order'!C:C,"2024",'List Order'!B:B,"Agustus",'List Order'!H:H,"Dismantle",'List Order'!I:I,"Colocation") -> 0 | BL20: =COUNTIFS('List Order'!C:C,"2024",'List Order'!B:B,"September",'List Order'!H:H,"Dismantle",'List Order'!I:I,"Colocation") -> 0 | BM20: =SUMIFS('List Order'!T:T,'List Order'!C:C,"2024",'List Order'!B:B,"September",'List Order'!H:H,"Dismantle",'List Order'!I:I,"Colocation") -> 0 | BN20: =COUNTIFS('List Order'!C:C,"2024",'List Order'!B:B,"Oktober",'List Order'!H:H,"Dismantle",'List Order'!I:I,"Colocation") -> 0 | BO20: =SUMIFS('List Order'!T:T,'List Order'!C:C,"2024",'List Order'!B:B,"Oktober",'List Order'!H:H,"Dismantle",'List Order'!I:I,"Colocation") -> 0 | BP20: =COUNTIFS('List Order'!C:C,"2024",'List Order'!B:B,"November",'List Order'!H:H,"Dismantle",'List Order'!I:I,"Colocation") -> 0 | BQ20: =SUMIFS('List Order'!T:T,'List Order'!C:C,"2024",'List Order'!B:B,"November",'List Order'!H:H,"Dismantle",'List Order'!I:I,"Colocation") -> 0 | BR20: =COUNTIFS('List Order'!C:C,"2024",'List Order'!B:B,"Desember",'List Order'!H:H,"Dismantle",'List Order'!I:I,"Colocation") -> 0 | BS20: =SUMIFS('List Order'!T:T,'List Order'!C:C,"2024",'List Order'!B:B,"Desember",'List Order'!H:H,"Dismantle",'List Order'!I:I,"Colocation") -> 0
AE21: Gugum | AF21: =SUM(AF6:AQ6) -> 97 | AG21: =COUNTIFS('List Project'!C:C,"2024",'List Project'!P:P,"Done",'List Project'!O:O,"Gugum") -> 40 | AH21: =COUNTIFS('List Project'!C:C,"2024",'List Project'!P:P,"OGP",'List Project'!O:O,"Gugum") -> 0 | AI21: =SUMIF('List Project'!O:O,"Gugum",'List Project'!I:I) -> 1.2903765e+12 | AK21: Revenue | AL21: =AI18 -> 124082524515 | AM21: =AI19 -> 4.398677e+11 | AN21: =AI20 -> 3.317266e+11 | AO21: =AI21 -> 1.2903765e+12 | AU21: Jumlah Order | AV21: =AV18+AV13+AV8+AV3 -> 29 | AX21: =AX18+AX13+AX8+AX3 -> 25 | AZ21: =AZ18+AZ13+AZ8+AZ3 -> 21 | BB21: =BB18+BB13+BB8+BB3 -> 14 | BD21: =BD18+BD13+BD8+BD3 -> 34 | BF21: =BF18+BF13+BF8+BF3 -> 30 | BH21: =BH18+BH13+BH8+BH3 -> 64 | BJ21: =BJ18+BJ13+BJ8+BJ3 -> 19 | BL21: =BL18+BL13+BL8+BL3 -> 16 | BN21: =BN18+BN13+BN8+BN3 -> 27 | BP21: =BP18+BP13+BP8+BP3 -> 20 | BR21: =BR18+BR13+BR8+BR3 -> 25
AU22: Order Open | AV22: =COUNTIFS('List Order'!R:R,"Close",'List Order'!C:C,"2024",'List Order'!B:B,"Januari") -> 29 | AX22: =COUNTIFS('List Order'!R:R,"Close",'List Order'!C:C,"2024",'List Order'!B:B,"Februari") -> 24 | AZ22: =COUNTIFS('List Order'!R:R,"Close",'List Order'!C:C,"2024",'List Order'!B:B,"Maret") -> 21 | BB22: =COUNTIFS('List Order'!R:R,"Close",'List Order'!C:C,"2024",'List Order'!B:B,"April") -> 14 | BD22: =COUNTIFS('List Order'!R:R,"Close",'List Order'!C:C,"2024",'List Order'!B:B,"Mei") -> 34 | BF22: =COUNTIFS('List Order'!R:R,"Close",'List Order'!C:C,"2024",'List Order'!B:B,"Juni") -> 9 | BH22: =COUNTIFS('List Order'!R:R,"Close",'List Order'!C:C,"2024",'List Order'!B:B,"Juli") -> 23 | BJ22: =COUNTIFS('List Order'!R:R,"Close",'List Order'!C:C,"2024",'List Order'!B:B,"Agustus") -> 4 | BL22: =COUNTIFS('List Order'!R:R,"Close",'List Order'!C:C,"2024",'List Order'!B:B,"September") -> 0 | BN22: =COUNTIFS('List Order'!R:R,"Close",'List Order'!C:C,"2024",'List Order'!B:B,"Oktober") -> 13 | BP22: =COUNTIFS('List Order'!R:R,"Close",'List Order'!C:C,"2024",'List Order'!B:B,"November") -> 10 | BR22: =COUNTIFS('List Order'!R:R,"Close",'List Order'!C:C,"2024",'List Order'!B:B,"Desember") -> 10
AF23: Januari | AG23: Februari | AH23: Maret | AI23: April | AJ23: Mei | AK23: Juni | AL23: Juli | AM23: Agustus | AN23: September | AO23: Oktober | AP23: November | AQ23: Desember | AU23: Order Close | AV23: =COUNTIFS('List Order'!R:R,"Open",'List Order'!C:C,"2024",'List Order'!B:B,"Januari") -> 0 | AX23: =COUNTIFS('List Order'!R:R,"Open",'List Order'!C:C,"2024",'List Order'!B:B,"Februari") -> 0 | AZ23: =COUNTIFS('List Order'!R:R,"Open",'List Order'!C:C,"2024",'List Order'!B:B,"Maret") -> 0 | BB23: =COUNTIFS('List Order'!R:R,"Open",'List Order'!C:C,"2024",'List Order'!B:B,"April") -> 0 | BD23: =COUNTIFS('List Order'!R:R,"Open",'List Order'!C:C,"2024",'List Order'!B:B,"Mei") -> 0 | BF23: =COUNTIFS('List Order'!R:R,"Open",'List Order'!C:C,"2024",'List Order'!B:B,"Juni") -> 0 | BH23: =COUNTIFS('List Order'!R:R,"Open",'List Order'!C:C,"2024",'List Order'!B:B,"Juli") -> 0 | BJ23: =COUNTIFS('List Order'!R:R,"Open",'List Order'!C:C,"2024",'List Order'!B:B,"Agustus") -> 0 | BL23: =COUNTIFS('List Order'!R:R,"Open",'List Order'!C:C,"2024",'List Order'!B:B,"September") -> 0 | BN23: =COUNTIFS('List Order'!R:R,"Open",'List Order'!C:C,"2024",'List Order'!B:B,"Oktober") -> 13 | BP23: =COUNTIFS('List Order'!R:R,"Open",'List Order'!C:C,"2024",'List Order'!B:B,"November") -> 6 | BR23: =COUNTIFS('List Order'!R:R,"Open",'List Order'!C:C,"2024",'List Order'!B:B,"Desember") -> 10
AE24: Penambahan Cost | AF24: =AW4+AW5+AW6+AW9+AW10+AW14+AW15+AW19 -> 99815027 | AG24: =AY4+AY5+AY6+AY9+AY10+AY14+AY15+AY19 -> 35490500 | AH24: =BA4+BA5+BA6+BA9+BA10+BA14+BA15+BA19 -> 326868030 | AI24: =BC4+BC5+BC6+BC9+BC10+BC14+BC15+BC19 -> 140305130 | AJ24: =BE4+BE5+BE6+BE9+BE10+BE14+BE15+BE19 -> 3993000 | AK24: =BG4+BG5+BG6+BG9+BG10+BG14+BG15+BG19 -> 0 | AL24: =BI4+BI5+BI6+BI9+BI10+BI14+BI15+BI19 -> 0 | AM24: =BK4+BK5+BK6+BK9+BK10+BK14+BK15+BK19 -> 0 | AN24: =BM4+BM5+BM6+BM9+BM10+BM14+BM15+BM19 -> 0 | AO24: =BO4+BO5+BO6+BO9+BO10+BO14+BO15+BO19 -> 48700000 | AP24: =BQ4+BQ5+BQ6+BQ9+BQ10+BQ14+BQ15+BQ19 -> 16889100 | AQ24: =BS4+BS5+BS6+BS9+BS10+BS14+BS15+BS19 -> 31543400 | AR24: =SUM(AF24:AQ24) -> 703604187
AE25: Pengurangan Cost | AF25: =AW7+AW11+AW12+AW16+AW17+AW20 -> 8308750 | AG25: =AY7+AY11+AY12+AY16+AY17+AY20 -> 74918070 | AH25: =BA7+BA11+BA12+BA16+BA17+BA20 -> 125790000 | AI25: =BC7+BC11+BC12+BC16+BC17+BC20 -> 6950000 | AJ25: =BE7+BE11+BE12+BE16+BE17+BE20 -> 13522000 | AK25: =BG7+BG11+BG12+BG16+BG17+BG20 -> 0 | AL25: =BI7+BI11+BI12+BI16+BI17+BI20 -> 384210277 | AM25: =BK7+BK11+BK12+BK16+BK17+BK20 -> 0 | AN25: =BM7+BM11+BM12+BM16+BM17+BM20 -> 0 | AO25: =BO7+BO11+BO12+BO16+BO17+BO20 -> 41074523 | AP25: =BQ7+BQ11+BQ12+BQ16+BQ17+BQ20 -> 13466450 | AQ25: =BS7+BS11+BS12+BS16+BS17+BS20 -> 1160000 | AR25: =SUM(AF25:AQ25) -> 669400070 | AS25: =AR24-AR25 -> 34204117
AE26: Penambahan Item | AF26: =AV4+AV5+AV6+AV9+AV10+AV14+AV15+AV19 -> 24 | AG26: =AX4+AX5+AX6+AX9+AX10+AX14+AX15+AX19 -> 17 | AH26: =AZ4+AZ5+AZ6+AZ9+AZ10+AZ14+AZ15+AZ19 -> 14 | AI26: =BB4+BB5+BB6+BB9+BB10+BB14+BB15+BB19 -> 10 | AJ26: =BD4+BD5+BD6+BD9+BD10+BD14+BD15+BD19 -> 22 | AK26: =BF4+BF5+BF6+BF9+BF10+BF14+BF15+BF19 -> 15 | AL26: =BH4+BH5+BH6+BH9+BH10+BH14+BH15+BH19 -> 32 | AM26: =BJ4+BJ5+BJ6+BJ9+BJ10+BJ14+BJ15+BJ19 -> 5 | AN26: =BL4+BL5+BL6+BL9+BL10+BL14+BL15+BL19 -> 7 | AO26: =BN4+BN5+BN6+BN9+BN10+BN14+BN15+BN19 -> 19 | AP26: =BP4+BP5+BP6+BP9+BP10+BP14+BP15+BP19 -> 13 | AQ26: =BR4+BR5+BR6+BR9+BR10+BR14+BR15+BR19 -> 20
AE27: Pengurangan Item | AF27: =AV7+AV11+AV12+AV16+AV17+AV20 -> 5 | AG27: =AX7+AX11+AX12+AX16+AX17+AX20 -> 8 | AH27: =AZ7+AZ11+AZ12+AZ16+AZ17+AZ20 -> 6 | AI27: =BB7+BB11+BB12+BB16+BB17+BB20 -> 4 | AJ27: =BD7+BD11+BD12+BD16+BD17+BD20 -> 12 | AK27: =BF7+BF11+BF12+BF16+BF17+BF20 -> 12 | AL27: =BH7+BH11+BH12+BH16+BH17+BH20 -> 12 | AM27: =BJ7+BJ11+BJ12+BJ16+BJ17+BJ20 -> 5 | AN27: =BL7+BL11+BL12+BL16+BL17+BL20 -> 5 | AO27: =BN7+BN11+BN12+BN16+BN17+BN20 -> 7 | AP27: =BP7+BP11+BP12+BP16+BP17+BP20 -> 7 | AQ27: =BR7+BR11+BR12+BR16+BR17+BR20 -> 4
AF29: Januari | AG29: Februari | AH29: Maret | AI29: April | AJ29: Mei | AK29: Juni | AL29: Juli | AM29: Agustus | AN29: September | AO29: Oktober | AP29: November | AQ29: Desember
AE30: Perkiraan Tagihan | AL30: =AK31+AK24-AK25 -> 3401034395 | AM30: =AL30+AL24-AL25 -> 3016824118 | AN30: =AM30+AM24-AM25 -> 3016824118 | AO30: =AN30+AN24-AN25 -> 3016824118 | AP30: =AO30+AO24-AO25 -> 3024449595 | AQ30: =AP30+AP24-AP25 -> 3027872245 | AR30: =SUM(AL30:AQ30) -> 18503828589
AE31: Realisasi Tagihan | AF31: 3158763225 | AG31: 3348353510 | AH31: 3267507386 | AI31: 3494786883 | AJ31: 5220740536 | AK31: 3401034395 | AL31: 3325959237 | AM31: 3357649748 | AN31: 3778396919 | AO31: 3467967803 | AP31: 2993969434 | AR31: =SUM(AF31:AQ31) -> 38815129076
AE32: Penambahan Item | AF32: =AF26 -> 24 | AG32: =AG26 -> 17 | AH32: =AH26 -> 14 | AI32: =AI26 -> 10 | AJ32: =AJ26 -> 22 | AK32: =AK26 -> 15 | AL32: =AL26 -> 32 | AM32: =AM26 -> 5 | ... AQ32: =AQ26 -> 20
AE33: Pengurangan Item | AF33: =AF27 -> 5 | AG33: =AG27 -> 8 | AH33: =AH27 -> 6 | AI33: =AI27 -> 4 | AJ33: =AJ27 -> 12 | AK33: =AK27 -> 12 | AL33: =AL27 -> 12 | AM33: =AM27 -> 5 | ... AQ33: =AQ27 -> 4
AO35: Jumlah
AN36: Sudah BA | AO36: =COUNTIFS('List Order'!C:C,"2024",'List Order'!W:W,"file") -> 132
AN37: Belum BA | AO37: =COUNTIFS('List Order'!C:C,"2024",'List Order'!W:W,"") -> 201

Sheet Sum 2025
AF1: Januari | AG1: Februari | AH1: Maret | AI1: April | AJ1: Mei | AK1: Juni | AL1: Juli | AM1: Agustus | AN1: September | AO1: Oktober | AP1: November | AQ1: Desember | AU1: 2025 | AV1: JANUARI | AX1: FEBRUARI | AZ1: MARET | BB1: APRIL | BD1: MAY | BF1: JUNI | BH1: JULI | BJ1: AGUSTUS | BL1: SEPTEMBER | BN1: OKTOBER | BP1: NOVEMBER | BR1: Desember
B2: Total Project | D2: =COUNTIFS('List Project'!C:C,"2025",'List Project'!P:P,"Done")+COUNTIFS('List Project'!C:C,"2025",'List Project'!P:P,"OGP") -> 119 | AE2: Revenue Project | AF2: =SUMIFS('List Project'!I:I,'List Project'!D:D,"Januari",'List Project'!C:C,"2025") -> 55157828477 | AG2: =SUMIFS('List Project'!I:I,'List Project'!D:D,"Februari",'List Project'!C:C,"2025") -> 13464557806 | AH2: =SUMIFS('List Project'!I:I,'List Project'!D:D,"Maret",'List Project'!C:C,"2025") -> 12525655865 | AI2: =SUMIFS('List Project'!I:I,'List Project'!D:D,"April",'List Project'!C:C,"2025") -> 4546519554 | AJ2: =SUMIFS('List Project'!I:I,'List Project'!D:D,"Mei",'List Project'!C:C,"2025") -> 1492660000 | AK2: =SUMIFS('List Project'!I:I,'List Project'!D:D,"Juni",'List Project'!C:C,"2025") -> 22674005152 | AL2: =SUMIFS('List Project'!I:I,'List Project'!D:D,"Juli",'List Project'!C:C,"2025") -> 19665001612 | AM2: =SUMIFS('List Project'!I:I,'List Project'!D:D,"Agustus",'List Project'!C:C,"2025") -> 22572928806 | AN2: =SUMIFS('List Project'!I:I,'List Project'!D:D,"September",'List Project'!C:C,"2025") -> 1.2642228e+11 | AO2: =SUMIFS('List Project'!I:I,'List Project'!D:D,"Oktober",'List Project'!C:C,"2025") -> 2.6911277e+11 | AP2: =SUMIFS('List Project'!I:I,'List Project'!D:D,"November",'List Project'!C:C,"2025") -> 39966893707 | AQ2: =SUMIFS('List Project'!I:I,'List Project'!D:D,"Desember",'List Project'!C:C,"2025") -> 972717736854 | AR2: =SUM(AF2:AQ2) -> 1.5603188e+12 | AU2: Klasifikasi order | AV2: JUMLAH | AW2: TOTAL TAGIHAN | AX2: JUMLAH | AY2: TOTAL TAGIHAN | AZ2: JUMLAH | BA2: TOTAL TAGIHAN | BB2: JUMLAH | BC2: TOTAL TAGIHAN | BD2: JUMLAH | BE2: TOTAL TAGIHAN | BF2: JUMLAH | BG2: TOTAL TAGIHAN | BH2: JUMLAH | BI2: TOTAL TAGIHAN | BJ2: JUMLAH | BK2: TOTAL TAGIHAN | BL2: JUMLAH | BM2: TOTAL TAGIHAN | BN2: JUMLAH | BO2: TOTAL TAGIHAN | BP2: JUMLAH | BQ2: TOTAL TAGIHAN | BR2: JUMLAH | BS2: TOTAL TAGIHAN
AE3: Adi | AF3: =COUNTIFS('List Project'!D:D,"Januari",'List Project'!O:O,"Adi",'List Project'!C:C,"2025") -> 1 | AG3: =COUNTIFS('List Project'!D:D,"Februari",'List Project'!O:O,"Adi",'List Project'!C:C,"2025") -> 0 | AH3: =COUNTIFS('List Project'!D:D,"Maret",'List Project'!O:O,"Adi",'List Project'!C:C,"2025") -> 0 | AI3: =COUNTIFS('List Project'!D:D,"April",'List Project'!O:O,"Adi",'List Project'!C:C,"2025") -> 0 | AJ3: =COUNTIFS('List Project'!D:D,"Mei",'List Project'!O:O,"Adi",'List Project'!C:C,"2025") -> 0 | AK3: =COUNTIFS('List Project'!D:D,"Juni",'List Project'!O:O,"Adi",'List Project'!C:C,"2025") -> 0 | AL3: =COUNTIFS('List Project'!D:D,"Juli",'List Project'!O:O,"Adi",'List Project'!C:C,"2025") -> 0 | AM3: =COUNTIFS('List Project'!D:D,"Agustus",'List Project'!O:O,"Adi",'List Project'!C:C,"2025") -> 0 | AN3: =COUNTIFS('List Project'!D:D,"September",'List Project'!O:O,"Adi",'List Project'!C:C,"2025") -> 1 | AO3: =COUNTIFS('List Project'!D:D,"Oktober",'List Project'!O:O,"Adi",'List Project'!C:C,"2025") -> 2 | AP3: =COUNTIFS('List Project'!D:D,"November",'List Project'!O:O,"Adi",'List Project'!C:C,"2025") -> 0 | AQ3: =COUNTIFS('List Project'!D:D,"Desember",'List Project'!O:O,"Adi",'List Project'!C:C,"2025") -> 0 | AR3: =SUM(AF3:AQ3) -> 4 | AS3: =SUMIFS('List Project'!W:W,'List Project'!AC:AC,"Adi",'List Project'!M:M,"2025") -> 0 | AU3: NOMOR AKSES | AV3: =COUNTIFS('List Order'!B:B,"Januari",'List Order'!I:I,"Nomor Akses",'List Order'!C:C,"2025") -> 15 | AW3: =SUM(AW4:AW6) -> 16740000 | AX3: =COUNTIFS('List Order'!B:B,"Februari",'List Order'!I:I,"Nomor Akses",'List Order'!C:C,"2025") -> 11 | AY3: =SUM(AY4:AY6) -> 4240000 | AZ3: =COUNTIFS('List Order'!B:B,"Maret",'List Order'!I:I,"Nomor Akses",'List Order'!C:C,"2025") -> 7 | BA3: =SUM(BA4:BA6) -> 8080000 | BB3: =COUNTIFS('List Order'!B:B,"April",'List Order'!I:I,"Nomor Akses",'List Order'!C:C,"2025") -> 12 | BC3: =SUM(BC4:BC6) -> 12320000 | BD3: =COUNTIFS('List Order'!B:B,"Mei",'List Order'!I:I,"Nomor Akses",'List Order'!C:C,"2025") -> 5 | BE3: =SUM(BE4:BE6) -> 0 | BF3: =COUNTIFS('List Order'!B:B,"Juni",'List Order'!I:I,"Nomor Akses",'List Order'!C:C,"2025") -> 8 | BG3: =SUM(BG4:BG6) -> 10000000 | BH3: =COUNTIFS('List Order'!B:B,"Juli",'List Order'!I:I,"Nomor Akses",'List Order'!C:C,"2025") -> 20 | BI3: =SUM(BI4:BI6) -> 20150000 | BJ3: =COUNTIFS('List Order'!B:B,"Agustus",'List Order'!I:I,"Nomor Akses",'List Order'!C:C,"2025") -> 10 | BK3: =SUM(BK4:BK6) -> 2900000 | BL3: =COUNTIFS('List Order'!B:B,"September",'List Order'!I:I,"Nomor Akses",'List Order'!C:C,"2025") -> 7 | BM3: =SUM(BM4:BM6) -> 8080000 | BN3: =COUNTIFS('List Order'!B:B,"Oktober",'List Order'!I:I,"Nomor Akses",'List Order'!C:C,"2025") -> 13 | BO3: =SUM(BO4:BO6) -> 2320000 | BP3: =COUNTIFS('List Order'!B:B,"November",'List Order'!I:I,"Nomor Akses",'List Order'!C:C,"2025") -> 3 | BQ3: =SUM(BQ4:BQ6) -> 0 | BR3: =COUNTIFS('List Order'!B:B,"Desember",'List Order'!I:I,"Nomor Akses",'List Order'!C:C,"2025") -> 15 | BS3: =SUM(BS4:BS6) -> 0
B4: Total Revenue | D4: =SUMIF('List Project'!C:C,"2025",'List Project'!I:I) -> 1.5603188e+12 | AE4: Dwi | AF4: =COUNTIFS('List Project'!D:D,"Januari",'List Project'!O:O,"Dwi",'List Project'!C:C,"2025") -> 4 | AG4: =COUNTIFS('List Project'!D:D,"Februari",'List Project'!O:O,"Dwi",'List Project'!C:C,"2025") -> 3 | AH4: =COUNTIFS('List Project'!D:D,"Maret",'List Project'!O:O,"Dwi",'List Project'!C:C,"2025") -> 3 | AI4: =COUNTIFS('List Project'!D:D,"April",'List Project'!O:O,"Dwi",'List Project'!C:C,"2025") -> 5 | AJ4: =COUNTIFS('List Project'!D:D,"Mei",'List Project'!O:O,"Dwi",'List Project'!C:C,"2025") -> 0 | AK4: =COUNTIFS('List Project'!D:D,"Juni",'List Project'!O:O,"Dwi",'List Project'!C:C,"2025") -> 3 | AL4: =COUNTIFS('List Project'!D:D,"Juli",'List Project'!O:O,"Dwi",'List Project'!C:C,"2025") -> 3 | AM4: =COUNTIFS('List Project'!D:D,"Agustus",'List Project'!O:O,"Dwi",'List Project'!C:C,"2025") -> 0 | AN4: =COUNTIFS('List Project'!D:D,"September",'List Project'!O:O,"Dwi",'List Project'!C:C,"2025") -> 1 | AO4: =COUNTIFS('List Project'!D:D,"Oktober",'List Project'!O:O,"Dwi",'List Project'!C:C,"2025") -> 2 | AP4: =COUNTIFS('List Project'!D:D,"November",'List Project'!O:O,"Dwi",'List Project'!C:C,"2025") -> 7 | AQ4: =COUNTIFS('List Project'!D:D,"Desember",'List Project'!O:O,"Dwi",'List Project'!C:C,"2025") -> 2 | AR4: =SUM(AF4:AQ4) -> 33 | AS4: =SUMIFS('List Project'!W:W,'List Project'!AC:AC,"Dwi",'List Project'!M:M,"2025") -> 0 | AU4: Aktivasi | AV4: =COUNTIFS('List Order'!C:C,"2025",'List Order'!B:B,"Januari",'List Order'!H:H,"Aktivasi",'List Order'!I:I,"Nomor Akses") -> 9 | AW4: =SUMIFS('List Order'!T:T,'List Order'!C:C,"2025",'List Order'!B:B,"Januari",'List Order'!H:H,"Aktivasi",'List Order'!I:I,"Nomor Akses") -> 16740000 | AX4: =COUNTIFS('List Order'!C:C,"2025",'List Order'!B:B,"Februari",'List Order'!H:H,"Aktivasi",'List Order'!I:I,"Nomor Akses") -> 4 | AY4: =SUMIFS('List Order'!T:T,'List Order'!C:C,"2025",'List Order'!B:B,"Februari",'List Order'!H:H,"Aktivasi",'List Order'!I:I,"Nomor Akses") -> 4240000 | AZ4: =COUNTIFS('List Order'!C:C,"2025",'List Order'!B:B,"Maret",'List Order'!H:H,"Aktivasi",'List Order'!I:I,"Nomor Akses") -> 4 | BA4: =SUMIFS('List Order'!T:T,'List Order'!C:C,"2025",'List Order'!B:B,"Maret",'List Order'!H:H,"Aktivasi",'List Order'!I:I,"Nomor Akses") -> 8080000 | BB4: =COUNTIFS('List Order'!C:C,"2025",'List Order'!B:B,"April",'List Order'!H:H,"Aktivasi",'List Order'!I:I,"Nomor Akses") -> 9 | BC4: =SUMIFS('List Order'!T:T,'List Order'!C:C,"2025",'List Order'!B:B,"April",'List Order'!H:H,"Aktivasi",'List Order'!I:I,"Nomor Akses") -> 12320000 | BD4: =COUNTIFS('List Order'!C:C,"2025",'List Order'!B:B,"Mei",'List Order'!H:H,"Aktivasi",'List Order'!I:I,"Nomor Akses") -> 0 | BE4: =SUMIFS('List Order'!T:T,'List Order'!C:C,"2025",'List Order'!B:B,"Mei",'List Order'!H:H,"Aktivasi",'List Order'!I:I,"Nomor Akses") -> 0 | BF4: =COUNTIFS('List Order'!C:C,"2025",'List Order'!B:B,"Juni",'List Order'!H:H,"Aktivasi",'List Order'!I:I,"Nomor Akses") -> 3 | BG4: =SUMIFS('List Order'!T:T,'List Order'!C:C,"2025",'List Order'!B:B,"Juni",'List Order'!H:H,"Aktivasi",'List Order'!I:I,"Nomor Akses") -> 6000000 | BH4: =COUNTIFS('List Order'!C:C,"2025",'List Order'!B:B,"Juli",'List Order'!H:H,"Aktivasi",'List Order'!I:I,"Nomor Akses") -> 13 | BI4: =SUMIFS('List Order'!T:T,'List Order'!C:C,"2025",'List Order'!B:B,"Juli",'List Order'!H:H,"Aktivasi",'List Order'!I:I,"Nomor Akses") -> 6850000 | BJ4: =COUNTIFS('List Order'!C:C,"2025",'List Order'!B:B,"Agustus",'List Order'!H:H,"Aktivasi",'List Order'!I:I,"Nomor Akses") -> 6 | BK4: =SUMIFS('List Order'!T:T,'List Order'!C:C,"2025",'List Order'!B:B,"Agustus",'List Order'!H:H,"Aktivasi",'List Order'!I:I,"Nomor Akses") -> 2900000 | BL4: =COUNTIFS('List Order'!C:C,"2025",'List Order'!B:B,"September",'List Order'!H:H,"Aktivasi",'List Order'!I:I,"Nomor Akses") -> 4 | BM4: =SUMIFS('List Order'!T:T,'List Order'!C:C,"2025",'List Order'!B:B,"September",'List Order'!H:H,"Aktivasi",'List Order'!I:I,"Nomor Akses") -> 8080000 | BN4: =COUNTIFS('List Order'!C:C,"2025",'List Order'!B:B,"Oktober",'List Order'!H:H,"Aktivasi",'List Order'!I:I,"Nomor Akses") -> 7 | BO4: =SUMIFS('List Order'!T:T,'List Order'!C:C,"2025",'List Order'!B:B,"Oktober",'List Order'!H:H,"Aktivasi",'List Order'!I:I,"Nomor Akses") -> 1740000 | BP4: =COUNTIFS('List Order'!C:C,"2025",'List Order'!B:B,"November",'List Order'!H:H,"Aktivasi",'List Order'!I:I,"Nomor Akses") -> 2 | BQ4: =SUMIFS('List Order'!T:T,'List Order'!C:C,"2025",'List Order'!B:B,"November",'List Order'!H:H,"Aktivasi",'List Order'!I:I,"Nomor Akses") -> 0 | BR4: =COUNTIFS('List Order'!C:C,"2025",'List Order'!B:B,"Desember",'List Order'!H:H,"Aktivasi",'List Order'!I:I,"Nomor Akses") -> 5 | BS4: =SUMIFS('List Order'!T:T,'List Order'!C:C,"2025",'List Order'!B:B,"Desember",'List Order'!H:H,"Aktivasi") -> 0
AE5: Duta | AF5: =COUNTIFS('List Project'!D:D,"Januari",'List Project'!O:O,"Duta",'List Project'!C:C,"2025") -> 9 | AG5: =COUNTIFS('List Project'!D:D,"Februari",'List Project'!O:O,"Duta",'List Project'!C:C,"2025") -> 5 | AH5: =COUNTIFS('List Project'!D:D,"Maret",'List Project'!O:O,"Duta",'List Project'!C:C,"2025") -> 3 | AI5: =COUNTIFS('List Project'!D:D,"April",'List Project'!O:O,"Duta",'List Project'!C:C,"2025") -> 3 | AJ5: =COUNTIFS('List Project'!D:D,"Mei",'List Project'!O:O,"Duta",'List Project'!C:C,"2025") -> 5 | AK5: =COUNTIFS('List Project'!D:D,"Juni",'List Project'!O:O,"Duta",'List Project'!C:C,"2025") -> 4 | AL5: =COUNTIFS('List Project'!D:D,"Juli",'List Project'!O:O,"Duta",'List Project'!C:C,"2025") -> 3 | AM5: =COUNTIFS('List Project'!D:D,"Agustus",'List Project'!O:O,"Duta",'List Project'!C:C,"2025") -> 7 | AN5: =COUNTIFS('List Project'!D:D,"September",'List Project'!O:O,"Duta",'List Project'!C:C,"2025") -> 2 | AO5: =COUNTIFS('List Project'!D:D,"Oktober",'List Project'!O:O,"Duta",'List Project'!C:C,"2025") -> 4 | AP5: =COUNTIFS('List Project'!D:D,"November",'List Project'!O:O,"Duta",'List Project'!C:C,"2025") -> 6 | AQ5: =COUNTIFS('List Project'!D:D,"Desember",'List Project'!O:O,"Duta",'List Project'!C:C,"2025") -> 2 | AR5: =SUM(AF5:AQ5) -> 53 | AS5: =SUMIFS('List Project'!W:W,'List Project'!AC:AC,"Duta",'List Project'!M:M,"2025") -> 0 | AU5: Novasi | AV5: =COUNTIFS('List Order'!C:C,"2025",'List Order'!B:B,"Januari",'List Order'!H:H,"Novasi",'List Order'!I:I,"Nomor Akses") -> 1 | AW5: =SUMIFS('List Order'!T:T,'List Order'!C:C,"2025",'List Order'!B:B,"Januari",'List Order'!H:H,"Novasi",'List Order'!I:I,"Nomor Akses") -> 0 | AX5: =COUNTIFS('List Order'!C:C,"2025",'List Order'!B:B,"Februari",'List Order'!H:H,"Novasi",'List Order'!I:I,"Nomor Akses") -> 0 | AY5: =SUMIFS('List Order'!T:T,'List Order'!C:C,"2025",'List Order'!B:B,"Februari",'List Order'!H:H,"Novasi",'List Order'!I:I,"Nomor Akses") -> 0 | AZ5: =COUNTIFS('List Order'!C:C,"2025",'List Order'!B:B,"Maret",'List Order'!H:H,"Novasi",'List Order'!I:I,"Nomor Akses") -> 0 | BA5: =SUMIFS('List Order'!T:T,'List Order'!C:C,"2025",'List Order'!B:B,"Maret",'List Order'!H:H,"Novasi",'List Order'!I:I,"Nomor Akses") -> 0 | BB5: =COUNTIFS('List Order'!C:C,"2025",'List Order'!B:B,"April",'List Order'!H:H,"Novasi",'List Order'!I:I,"Nomor Akses") -> 0 | BC5: =SUMIFS('List Order'!T:T,'List Order'!C:C,"2025",'List Order'!B:B,"April",'List Order'!H:H,"Novasi",'List Order'!I:I,"Nomor Akses") -> 0 | BD5: =COUNTIFS('List Order'!C:C,"2025",'List Order'!B:B,"Mei",'List Order'!H:H,"Novasi",'List Order'!I:I,"Nomor Akses") -> 0 | BE5: =SUMIFS('List Order'!T:T,'List Order'!C:C,"2025",'List Order'!B:B,"Mei",'List Order'!H:H,"Novasi",'List Order'!I:I,"Nomor Akses") -> 0 | BF5: =COUNTIFS('List Order'!C:C,"2025",'List Order'!B:B,"Juni",'List Order'!H:H,"Novasi",'List Order'!I:I,"Nomor Akses") -> 3 | BG5: =SUMIFS('List Order'!T:T,'List Order'!C:C,"2025",'List Order'!B:B,"Juni",'List Order'!H:H,"Novasi",'List Order'!I:I,"Nomor Akses") -> 4000000 | BH5: =COUNTIFS('List Order'!C:C,"2025",'List Order'!B:B,"Juli",'List Order'!H:H,"Novasi",'List Order'!I:I,"Nomor Akses") -> 3 | BI5: =SUMIFS('List Order'!T:T,'List Order'!C:C,"2025",'List Order'!B:B,"Juli",'List Order'!H:H,"Novasi",'List Order'!I:I,"Nomor Akses") -> 7500000 | BJ5: =COUNTIFS('List Order'!C:C,"2025",'List Order'!B:B,"Agustus",'List Order'!H:H,"Novasi",'List Order'!I:I,"Nomor Akses") -> 1 | BK5: =SUMIFS('List Order'!T:T,'List Order'!C:C,"2025",'List Order'!B:B,"Agustus",'List Order'!H:H,"Novasi",'List Order'!I:I,"Nomor Akses") -> 0 | BL5: =COUNTIFS('List Order'!C:C,"2025",'List Order'!B:B,"September",'List Order'!H:H,"Novasi",'List Order'!I:I,"Nomor Akses") -> 0 | BM5: =SUMIFS('List Order'!T:T,'List Order'!C:C,"2025",'List Order'!B:B,"September",'List Order'!H:H,"Novasi",'List Order'!I:I,"Nomor Akses") -> 0 | BN5: =COUNTIFS('List Order'!C:C,"2025",'List Order'!B:B,"Oktober",'List Order'!H:H,"Novasi",'List Order'!I:I,"Nomor Akses") -> 1 | BO5: =SUMIFS('List Order'!T:T,'List Order'!C:C,"2025",'List Order'!B:B,"Oktober",'List Order'!H:H,"Novasi",'List Order'!I:I,"Nomor Akses") -> 580000 | BP5: =COUNTIFS('List Order'!C:C,"2025",'List Order'!B:B,"November",'List Order'!H:H,"Novasi",'List Order'!I:I,"Nomor Akses") -> 0 | BQ5: =SUMIFS('List Order'!T:T,'List Order'!C:C,"2025",'List Order'!B:B,"November",'List Order'!H:H,"Novasi",'List Order'!I:I,"Nomor Akses") -> 0 | BR5: =COUNTIFS('List Order'!C:C,"2025",'List Order'!B:B,"Desember",'List Order'!H:H,"Novasi",'List Order'!I:I,"Nomor Akses") -> 0 | BS5: =SUMIFS('List Order'!T:T,'List Order'!C:C,"2025",'List Order'!B:B,"Desember",'List Order'!H:H,"Novasi") -> 0
AE6: Gugum | AF6: =COUNTIFS('List Project'!D:D,"Januari",'List Project'!O:O,"Gugum",'List Project'!C:C,"2025") -> 6 | AG6: =COUNTIFS('List Project'!D:D,"Februari",'List Project'!O:O,"Gugum",'List Project'!C:C,"2025") -> 0 | AH6: =COUNTIFS('List Project'!D:D,"Maret",'List Project'!O:O,"Gugum",'List Project'!C:C,"2025") -> 0 | AI6: =COUNTIFS('List Project'!D:D,"April",'List Project'!O:O,"Gugum",'List Project'!C:C,"2025") -> 0 | AJ6: =COUNTIFS('List Project'!D:D,"Mei",'List Project'!O:O,"Gugum",'List Project'!C:C,"2025") -> 0 | AK6: =COUNTIFS('List Project'!D:D,"Juni",'List Project'!O:O,"Gugum",'List Project'!C:C,"2025") -> 0 | AL6: =COUNTIFS('List Project'!D:D,"Juli",'List Project'!O:O,"Gugum",'List Project'!C:C,"2025") -> 10 | AM6: =COUNTIFS('List Project'!D:D,"Agustus",'List Project'!O:O,"Gugum",'List Project'!C:C,"2025") -> 3 | AN6: =COUNTIFS('List Project'!D:D,"September",'List Project'!O:O,"Gugum",'List Project'!C:C,"2025") -> 4 | AO6: =COUNTIFS('List Project'!D:D,"Oktober",'List Project'!O:O,"Gugum",'List Project'!C:C,"2025") -> 4 | AP6: =COUNTIFS('List Project'!D:D,"November",'List Project'!O:O,"Gugum",'List Project'!C:C,"2025") -> 0 | AQ6: =COUNTIFS('List Project'!D:D,"Desember",'List Project'!O:O,"Gugum",'List Project'!C:C,"2025") -> 5 | AR6: =SUM(AF6:AQ6) -> 32 | AS6: =SUMIFS('List Project'!W:W,'List Project'!AC:AC,"Gugum",'List Project'!M:M,"2025") -> 0 | AU6: Modified | AV6: =COUNTIFS('List Order'!C:C,"2025",'List Order'!B:B,"Januari",'List Order'!H:H,"Modified",'List Order'!I:I,"Nomor Akses") -> 2 | AW6: =SUMIFS('List Order'!T:T,'List Order'!C:C,"2025",'List Order'!B:B,"Januari",'List Order'!H:H,"Modified",'List Order'!I:I,"Nomor Akses") -> 0 | AX6: =COUNTIFS('List Order'!C:C,"2025",'List Order'!B:B,"Februari",'List Order'!H:H,"Modified",'List Order'!I:I,"Nomor Akses") -> 0 | AY6: =SUMIFS('List Order'!T:T,'List Order'!C:C,"2025",'List Order'!B:B,"Februari",'List Order'!H:H,"Modified",'List Order'!I:I,"Nomor Akses") -> 0 | AZ6: =COUNTIFS('List Order'!C:C,"2025",'List Order'!B:B,"Maret",'List Order'!H:H,"Modified",'List Order'!I:I,"Nomor Akses") -> 1 | BA6: =SUMIFS('List Order'!T:T,'List Order'!C:C,"2025",'List Order'!B:B,"Maret",'List Order'!H:H,"Modified",'List Order'!I:I,"Nomor Akses") -> 0 | BB6: =COUNTIFS('List Order'!C:C,"2025",'List Order'!B:B,"April",'List Order'!H:H,"Modified",'List Order'!I:I,"Nomor Akses") -> 0 | BC6: =SUMIFS('List Order'!T:T,'List Order'!C:C,"2025",'List Order'!B:B,"April",'List Order'!H:H,"Modified",'List Order'!I:I,"Nomor Akses") -> 0 | BD6: =COUNTIFS('List Order'!C:C,"2025",'List Order'!B:B,"Mei",'List Order'!H:H,"Modified",'List Order'!I:I,"Nomor Akses") -> 0 | BE6: =SUMIFS('List Order'!T:T,'List Order'!C:C,"2025",'List Order'!B:B,"Mei",'List Order'!H:H,"Modified",'List Order'!I:I,"Nomor Akses") -> 0 | BF6: =COUNTIFS('List Order'!C:C,"2025",'List Order'!B:B,"Juni",'List Order'!H:H,"Modified",'List Order'!I:I,"Nomor Akses") -> 0 | BG6: =SUMIFS('List Order'!T:T,'List Order'!C:C,"2025",'List Order'!B:B,"Juni",'List Order'!H:H,"Modified",'List Order'!I:I,"Nomor Akses") -> 0 | BH6: =COUNTIFS('List Order'!C:C,"2025",'List Order'!B:B,"Juni",'List Order'!H:H,"Modified",'List Order'!I:I,"Nomor Akses") -> 0 | BI6: =SUMIFS('List Order'!T:T,'List Order'!C:C,"2025",'List Order'!B:B,"Juli",'List Order'!H:H,"Modified",'List Order'!I:I,"Nomor Akses") -> 5800000 | BJ6: =COUNTIFS('List Order'!C:C,"2025",'List Order'!B:B,"Agustus",'List Order'!H:H,"Modified",'List Order'!I:I,"Nomor Akses") -> 0 | BK6: =SUMIFS('List Order'!T:T,'List Order'!C:C,"2025",'List Order'!B:B,"Agustus",'List Order'!H:H,"Modified",'List Order'!I:I,"Nomor Akses") -> 0 | BL6: =COUNTIFS('List Order'!C:C,"2025",'List Order'!B:B,"September",'List Order'!H:H,"Modified",'List Order'!I:I,"Nomor Akses") -> 0 | BM6: =SUMIFS('List Order'!T:T,'List Order'!C:C,"2025",'List Order'!B:B,"September",'List Order'!H:H,"Modified",'List Order'!I:I,"Nomor Akses") -> 0 | BN6: =COUNTIFS('List Order'!C:C,"2025",'List Order'!B:B,"Oktober",'List Order'!H:H,"Modified",'List Order'!I:I,"Nomor Akses") -> 0 | BO6: =SUMIFS('List Order'!T:T,'List Order'!C:C,"2025",'List Order'!B:B,"Oktober",'List Order'!H:H,"Modified",'List Order'!I:I,"Nomor Akses") -> 0 | BP6: =COUNTIFS('List Order'!C:C,"2025",'List Order'!B:B,"November",'List Order'!H:H,"Modified",'List Order'!I:I,"Nomor Akses") -> 0 | BQ6: =SUMIFS('List Order'!T:T,'List Order'!C:C,"2025",'List Order'!B:B,"November",'List Order'!H:H,"Modified",'List Order'!I:I,"Nomor Akses") -> 0 | BR6: =COUNTIFS('List Order'!C:C,"2025",'List Order'!B:B,"Desember",'List Order'!H:H,"Modified",'List Order'!I:I,"Nomor Akses") -> 0 | BS6: =SUMIFS('List Order'!T:T,'List Order'!C:C,"2025",'List Order'!B:B,"Desember",'List Order'!H:H,"Modified") -> 0
AE7: CRM Revenue | AF7: =SUMIFS('List Project'!I:I,'List Project'!D:D,"Januari",'List Project'!F:F,"CRM",'List Project'!C:C,"2025") -> 53579916441 | AG7: =SUMIFS('List Project'!I:I,'List Project'!D:D,"Februari",'List Project'!F:F,"CRM",'List Project'!C:C,"2025") -> 5080908001 | AH7: =SUMIFS('List Project'!I:I,'List Project'!D:D,"Maret",'List Project'!F:F,"CRM",'List Project'!C:C,"2025") -> 12525655865 | AI7: =SUMIFS('List Project'!I:I,'List Project'!D:D,"April",'List Project'!F:F,"CRM",'List Project'!C:C,"2025") -> 4081099554 | AJ7: =SUMIFS('List Project'!I:I,'List Project'!D:D,"Mei",'List Project'!F:F,"CRM",'List Project'!C:C,"2025") -> 109600000 | AK7: =SUMIFS('List Project'!I:I,'List Project'!D:D,"Juni",'List Project'!F:F,"CRM",'List Project'!C:C,"2025") -> 22521005152 | AL7: =SUMIFS('List Project'!I:I,'List Project'!D:D,"Juli",'List Project'!F:F,"CRM",'List Project'!C:C,"2025") -> 18173661612 | AM7: =SUMIFS('List Project'!I:I,'List Project'!D:D,"Agustus",'List Project'!F:F,"CRM",'List Project'!C:C,"2025") -> 22172428806 | AN7: =SUMIFS('List Project'!I:I,'List Project'!D:D,"September",'List Project'!F:F,"CRM",'List Project'!C:C,"2025") -> 1.2605968e+11 | AO7: =SUMIFS('List Project'!I:I,'List Project'!D:D,"Oktober",'List Project'!F:F,"CRM",'List Project'!C:C,"2025") -> 2.6845629e+11 | AP7: =SUMIFS('List Project'!I:I,'List Project'!D:D,"November",'List Project'!F:F,"CRM",'List Project'!C:C,"2025") -> 39966893707 | AQ7: =SUMIFS('List Project'!I:I,'List Project'!D:D,"Desember",'List Project'!F:F,"CRM",'List Project'!C:C,"2025") -> 972546536854 | AR7: =SUM(AF7:AQ7) -> 1.5452737e+12 | AU7: Dismentle | AV7: =COUNTIFS('List Order'!C:C,"2025",'List Order'!B:B,"Januari",'List Order'!H:H,"Dismantle",'List Order'!I:I,"Nomor Akses") -> 3 | AW7: =SUMIFS('List Order'!T:T,'List Order'!C:C,"2025",'List Order'!B:B,"Januari",'List Order'!H:H,"Dismantle",'List Order'!I:I,"Nomor Akses") -> 4500000 | AX7: =COUNTIFS('List Order'!C:C,"2025",'List Order'!B:B,"Februari",'List Order'!H:H,"Dismantle",'List Order'!I:I,"Nomor Akses") -> 7 | AY7: =SUMIFS('List Order'!T:T,'List Order'!C:C,"2025",'List Order'!B:B,"Februari",'List Order'!H:H,"Dismantle",'List Order'!I:I,"Nomor Akses") -> 10160000 | AZ7: =COUNTIFS('List Order'!C:C,"2025",'List Order'!B:B,"Maret",'List Order'!H:H,"Dismantle",'List Order'!I:I,"Nomor Akses") -> 2 | BA7: =SUMIFS('List Order'!T:T,'List Order'!C:C,"2025",'List Order'!B:B,"Maret",'List Order'!H:H,"Dismantle",'List Order'!I:I,"Nomor Akses") -> 5000000 | BB7: =COUNTIFS('List Order'!C:C,"2025",'List Order'!B:B,"April",'List Order'!H:H,"Dismantle",'List Order'!I:I,"Nomor Akses") -> 2 | BC7: =SUMIFS('List Order'!T:T,'List Order'!C:C,"2025",'List Order'!B:B,"April",'List Order'!H:H,"Dismantle",'List Order'!I:I,"Nomor Akses") -> 4000000 | BD7: =COUNTIFS('List Order'!C:C,"2025",'List Order'!B:B,"Mei",'List Order'!H:H,"Dismantle",'List Order'!I:I,"Nomor Akses") -> 5 | BE7: =SUMIFS('List Order'!T:T,'List Order'!C:C,"2025",'List Order'!B:B,"Mei",'List Order'!H:H,"Dismantle",'List Order'!I:I,"Nomor Akses") -> 12500000 | BF7: =COUNTIFS('List Order'!C:C,"2025",'List Order'!B:B,"Juni",'List Order'!H:H,"Dismantle",'List Order'!I:I,"Nomor Akses") -> 2 | BG7: =SUMIFS('List Order'!T:T,'List Order'!C:C,"2025",'List Order'!B:B,"Juni",'List Order'!H:H,"Dismantle",'List Order'!I:I,"Nomor Akses") -> 4000000 | BH7: =COUNTIFS('List Order'!C:C,"2025",'List Order'!B:B,"Juli",'List Order'!H:H,"Dismantle",'List Order'!I:I,"Nomor Akses") -> 2 | BI7: =SUMIFS('List Order'!T:T,'List Order'!C:C,"2025",'List Order'!B:B,"Juli",'List Order'!H:H,"Dismantle",'List Order'!I:I,"Nomor Akses") -> 0 | BJ7: =COUNTIFS('List Order'!C:C,"2025",'List Order'!B:B,"Agustus",'List Order'!H:H,"Dismantle",'List Order'!I:I,"Nomor Akses") -> 3 | BK7: =SUMIFS('List Order'!T:T,'List Order'!C:C,"2025",'List Order'!B:B,"Agustus",'List Order'!H:H,"Dismantle",'List Order'!I:I,"Nomor Akses") -> 5000000 | BL7: =COUNTIFS('List Order'!C:C,"2025",'List Order'!B:B,"September",'List Order'!H:H,"Dismantle",'List Order'!I:I,"Nomor Akses") -> 2 | BM7: =SUMIFS('List Order'!T:T,'List Order'!C:C,"2025",'List Order'!B:B,"September",'List Order'!H:H,"Dismantle",'List Order'!I:I,"Nomor Akses") -> 5000000 | BN7: =COUNTIFS('List Order'!C:C,"2025",'List Order'!B:B,"Oktober",'List Order'!H:H,"Dismantle",'List Order'!I:I,"Nomor Akses") -> 4 | BO7: =SUMIFS('List Order'!T:T,'List Order'!C:C,"2025",'List Order'!B:B,"Oktober",'List Order'!H:H,"Dismantle",'List Order'!I:I,"Nomor Akses") -> 2500000 | BP7: =COUNTIFS('List Order'!C:C,"2025",'List Order'!B:B,"November",'List Order'!H:H,"Dismantle",'List Order'!I:I,"Nomor Akses") -> 0 | BQ7: =SUMIFS('List Order'!T:T,'List Order'!C:C,"2025",'List Order'!B:B,"November",'List Order'!H:H,"Dismantle",'List Order'!I:I,"Nomor Akses") -> 0 | BR7: =COUNTIFS('List Order'!C:C,"2025",'List Order'!B:B,"Desember",'List Order'!H:H,"Dismantle",'List Order'!I:I,"Nomor Akses") -> 9 | BS7: =SUMIFS('List Order'!T:T,'List Order'!C:C,"2025",'List Order'!B:B,"Desember",'List Order'!H:H,"Dismantle") -> 0
AE8: SSO Revenue | AF8: =SUMIFS('List Project'!I:I,'List Project'!D:D,"Januari",'List Project'!F:F,"SSO",'List Project'!C:C,"2025") -> 0 | AG8: =SUMIFS('List Project'!I:I,'List Project'!D:D,"Februari",'List Project'!F:F,"SSO",'List Project'!C:C,"2025") -> 5970050205 | AH8: =SUMIFS('List Project'!I:I,'List Project'!D:D,"Maret",'List Project'!F:F,"SSO",'List Project'!C:C,"2025") -> 0 | AI8: =SUMIFS('List Project'!I:I,'List Project'!D:D,"April",'List Project'!F:F,"SSO",'List Project'!C:C,"2025") -> 0 | AJ8: =SUMIFS('List Project'!I:I,'List Project'!D:D,"Mei",'List Project'!F:F,"SSO",'List Project'!C:C,"2025") -> 0 | AK8: =SUMIFS('List Project'!I:I,'List Project'!D:D,"Juni",'List Project'!F:F,"SSO",'List Project'!C:C,"2025") -> 0 | AL8: =SUMIFS('List Project'!I:I,'List Project'!D:D,"Juli",'List Project'!F:F,"SSO",'List Project'!C:C,"2025") -> 0 | AM8: =SUMIFS('List Project'!I:I,'List Project'!D:D,"Agustus",'List Project'!F:F,"SSO",'List Project'!C:C,"2025") -> 0 | AN8: =SUMIFS('List Project'!I:I,'List Project'!D:D,"September",'List Project'!F:F,"SSO",'List Project'!C:C,"2025") -> 0 | AO8: =SUMIFS('List Project'!I:I,'List Project'!D:D,"Oktober",'List Project'!F:F,"SSO",'List Project'!C:C,"2025") -> 0 | AP8: =SUMIFS('List Project'!I:I,'List Project'!D:D,"November",'List Project'!F:F,"SSO",'List Project'!C:C,"2025") -> 0 | AQ8: =SUMIFS('List Project'!I:I,'List Project'!D:D,"Desember",'List Project'!F:F,"SSO",'List Project'!C:C,"2025") -> 0 | AR8: =SUM(AF8:AQ8) -> 5970050205 | AU8: CONNECTIVITY | AV8: =COUNTIFS('List Order'!B:B,"Januari",'List Order'!I:I,"Connectivity",'List Order'!C:C,"2025") -> 9 | AW8: =SUM(AW9:AW10) -> 22544200 | AX8: =COUNTIFS('List Order'!B:B,"Februari",'List Order'!I:I,"Connectivity",'List Order'!C:C,"2025") -> 27 | AY8: =SUM(AY9:AY10) -> 61971700 | AZ8: =COUNTIFS('List Order'!B:B,"Maret",'List Order'!I:I,"Connectivity",'List Order'!C:C,"2025") -> 31 | BA8: =SUM(BA9:BA10) -> 1649000 | BB8: =COUNTIFS('List Order'!B:B,"April",'List Order'!I:I,"Connectivity",'List Order'!C:C,"2025") -> 23 | BC8: =SUM(BC9:BC10) -> 120157866 | BD8: =COUNTIFS('List Order'!B:B,"Mei",'List Order'!I:I,"Connectivity",'List Order'!C:C,"2025") -> 31 | BE8: =SUM(BE9:BE10) -> 44624166 | BF8: =COUNTIFS('List Order'!B:B,"Juni",'List Order'!I:I,"Connectivity",'List Order'!C:C,"2025") -> 15 | BG8: =SUM(BG9:BG10) -> 5474000 | BH8: =COUNTIFS('List Order'!B:B,"Juli",'List Order'!I:I,"Connectivity",'List Order'!C:C,"2025") -> 12 | BI8: =SUM(BI9:BI10) -> 3704000 | BJ8: =COUNTIFS('List Order'!B:B,"Agustus",'List Order'!I:I,"Connectivity",'List Order'!C:C,"2025") -> 14 | BK8: =SUM(BK9:BK10) -> 2059000 | BL8: =COUNTIFS('List Order'!B:B,"September",'List Order'!I:I,"Connectivity",'List Order'!C:C,"2025") -> 17 | BM8: =SUM(BM9:BM10) -> 9116400 | BN8: =COUNTIFS('List Order'!B:B,"Oktober",'List Order'!I:I,"Connectivity",'List Order'!C:C,"2025") -> 21 | BO8: =SUM(BO9:BO10) -> 0 | BP8: =COUNTIFS('List Order'!B:B,"November",'List Order'!I:I,"Connectivity",'List Order'!C:C,"2025") -> 24 | BQ8: =SUM(BQ9:BQ10) -> 0 | BR8: =COUNTIFS('List Order'!B:B,"Desember",'List Order'!I:I,"Connectivity",'List Order'!C:C,"2025") -> 20 | BS8: =SUM(BS9:BS10) -> 0
AE9: Nomor Akses Revenue | AF9: =SUMIFS('List Project'!I:I,'List Project'!D:D,"Januari",'List Project'!F:F,"Nomor Akses",'List Project'!C:C,"2025") -> 1577912036 | AG9: =SUMIFS('List Project'!I:I,'List Project'!D:D,"Februari",'List Project'!F:F,"Nomor Akses",'List Project'!C:C,"2025") -> 2413599600 | AH9: =SUMIFS('List Project'!I:I,'List Project'!D:D,"Maret",'List Project'!F:F,"Nomor Akses",'List Project'!C:C,"2025") -> 0 | AI9: =SUMIFS('List Project'!I:I,'List Project'!D:D,"April",'List Project'!F:F,"Nomor Akses",'List Project'!C:C,"2025") -> 465420000 | AJ9: =SUMIFS('List Project'!I:I,'List Project'!D:D,"Mei",'List Project'!F:F,"Nomor Akses",'List Project'!C:C,"2025") -> 1383060000 | AK9: =SUMIFS('List Project'!I:I,'List Project'!D:D,"Juni",'List Project'!F:F,"Nomor Akses",'List Project'!C:C,"2025") -> 153000000 | AL9: =SUMIFS('List Project'!I:I,'List Project'!D:D,"Juli",'List Project'!F:F,"Nomor Akses",'List Project'!C:C,"2025") -> 1491340000 | AM9: =SUMIFS('List Project'!I:I,'List Project'!D:D,"Agustus",'List Project'!F:F,"Nomor Akses",'List Project'!C:C,"2025") -> 400500000 | AN9: =SUMIFS('List Project'!I:I,'List Project'!D:D,"September",'List Project'!F:F,"Nomor Akses",'List Project'!C:C,"2025") -> 362600000 | AO9: =SUMIFS('List Project'!I:I,'List Project'!D:D,"Oktober",'List Project'!F:F,"Nomor Akses",'List Project'!C:C,"2025") -> 656488000 | AP9: =SUMIFS('List Project'!I:I,'List Project'!D:D,"November",'List Project'!F:F,"Nomor Akses",'List Project'!C:C,"2025") -> 0 | AQ9: =SUMIFS('List Project'!I:I,'List Project'!D:D,"Desember",'List Project'!F:F,"Nomor Akses",'List Project'!C:C,"2025") -> 171200000 | AR9: =SUM(AF9:AQ9) -> 9075119636 | AU9: PSB | AV9: =COUNTIFS('List Order'!C:C,"2025",'List Order'!B:B,"Januari",'List Order'!H:H,"PSB",'List Order'!I:I,"Connectivity") -> 5 | AW9: =SUMIFS('List Order'!T:T,'List Order'!C:C,"2025",'List Order'!B:B,"Januari",'List Order'!H:H,"PSB",'List Order'!I:I,"Connectivity") -> 4871200 | AX9: =COUNTIFS('List Order'!C:C,"2025",'List Order'!B:B,"Februari",'List Order'!H:H,"PSB",'List Order'!I:I,"Connectivity") -> 8 | AY9: =SUMIFS('List Order'!T:T,'List Order'!C:C,"2025",'List Order'!B:B,"Februari",'List Order'!H:H,"PSB",'List Order'!I:I,"Connectivity") -> 36761800 | AZ9: =COUNTIFS('List Order'!C:C,"2025",'List Order'!B:B,"Maret",'List Order'!H:H,"PSB",'List Order'!I:I,"Connectivity") -> 2 | BA9: =SUMIFS('List Order'!T:T,'List Order'!C:C,"2025",'List Order'!B:B,"Maret",'List Order'!H:H,"PSB",'List Order'!I:I,"Connectivity") -> 1649000 | BB9: =COUNTIFS('List Order'!C:C,"2025",'List Order'!B:B,"April",'List Order'!H:H,"PSB",'List Order'!I:I,"Connectivity") -> 7 | BC9: =SUMIFS('List Order'!T:T,'List Order'!C:C,"2025",'List Order'!B:B,"April",'List Order'!H:H,"PSB",'List Order'!I:I,"Connectivity") -> 7912000 | BD9: =COUNTIFS('List Order'!C:C,"2025",'List Order'!B:B,"Mei",'List Order'!H:H,"PSB",'List Order'!I:I,"Connectivity") -> 10 | BE9: =SUMIFS('List Order'!T:T,'List Order'!C:C,"2025",'List Order'!B:B,"Mei",'List Order'!H:H,"PSB",'List Order'!I:I,"Connectivity") -> 22976000 | BF9: =COUNTIFS('List Order'!C:C,"2025",'List Order'!B:B,"Juni",'List Order'!H:H,"PSB",'List Order'!I:I,"Connectivity") -> 8 | BG9: =SUMIFS('List Order'!T:T,'List Order'!C:C,"2025",'List Order'!B:B,"Juni",'List Order'!H:H,"PSB",'List Order'!I:I,"Connectivity") -> 2903000 | BH9: =COUNTIFS('List Order'!C:C,"2025",'List Order'!B:B,"Juli",'List Order'!H:H,"PSB",'List Order'!I:I,"Connectivity") -> 6 | BI9: =SUMIFS('List Order'!T:T,'List Order'!C:C,"2025",'List Order'!B:B,"Juli",'List Order'!H:H,"PSB",'List Order'!I:I,"Connectivity") -> 3704000 | BJ9: =COUNTIFS('List Order'!C:C,"2025",'List Order'!B:B,"Agustus",'List Order'!H:H,"PSB",'List Order'!I:I,"Connectivity") -> 7 | BK9: =SUMIFS('List Order'!T:T,'List Order'!C:C,"2025",'List Order'!B:B,"Agustus",'List Order'!H:H,"PSB",'List Order'!I:I,"Connectivity") -> 2059000 | BL9: =COUNTIFS('List Order'!C:C,"2025",'List Order'!B:B,"September",'List Order'!H:H,"PSB",'List Order'!I:I,"Connectivity") -> 10 | BM9: =SUMIFS('List Order'!T:T,'List Order'!C:C,"2025",'List Order'!B:B,"September",'List Order'!H:H,"PSB",'List Order'!I:I,"Connectivity") -> 9116400 | BN9: =COUNTIFS('List Order'!C:C,"2025",'List Order'!B:B,"Oktober",'List Order'!H:H,"PSB",'List Order'!I:I,"Connectivity") -> 7 | BO9: =SUMIFS('List Order'!T:T,'List Order'!C:C,"2025",'List Order'!B:B,"Oktober",'List Order'!H:H,"PSB",'List Order'!I:I,"Connectivity") -> 0 | BP9: =COUNTIFS('List Order'!C:C,"2025",'List Order'!B:B,"November",'List Order'!H:H,"PSB",'List Order'!I:I,"Connectivity") -> 10 | BQ9: =SUMIFS('List Order'!T:T,'List Order'!C:C,"2025",'List Order'!B:B,"November",'List Order'!H:H,"PSB",'List Order'!I:I,"Connectivity") -> 0 | BR9: =COUNTIFS('List Order'!C:C,"2025",'List Order'!B:B,"Desember",'List Order'!H:H,"PSB",'List Order'!I:I,"Connectivity") -> 4 | BS9: =SUMIFS('List Order'!T:T,'List Order'!C:C,"2025",'List Order'!B:B,"Desember",'List Order'!H:H,"PSB",'List Order'!I:I,"Connectivity") -> 0
AU10: Upgrade | AV10: =COUNTIFS('List Order'!C:C,"2025",'List Order'!B:B,"Januari",'List Order'!H:H,"Upgrade",'List Order'!I:I,"Connectivity") -> 1 | AW10: =SUMIFS('List Order'!T:T,'List Order'!C:C,"2025",'List Order'!B:B,"Januari",'List Order'!H:H,"Upgrade",'List Order'!I:I,"Connectivity") -> 17673000 | AX10: =COUNTIFS('List Order'!C:C,"2025",'List Order'!B:B,"Februari",'List Order'!H:H,"Upgrade",'List Order'!I:I,"Connectivity") -> 6 | AY10: =SUMIFS('List Order'!T:T,'List Order'!C:C,"2025",'List Order'!B:B,"Februari",'List Order'!H:H,"Upgrade",'List Order'!I:I,"Connectivity") -> 25209900 | AZ10: =COUNTIFS('List Order'!C:C,"2025",'List Order'!B:B,"Maret",'List Order'!H:H,"Upgrade",'List Order'!I:I,"Connectivity") -> 3 | BA10: =SUMIFS('List Order'!T:T,'List Order'!C:C,"2025",'List Order'!B:B,"Maret",'List Order'!H:H,"Upgrade",'List Order'!I:I,"Connectivity") -> 0 | BB10: =COUNTIFS('List Order'!C:C,"2025",'List Order'!B:B,"April",'List Order'!H:H,"Upgrade",'List Order'!I:I,"Connectivity") -> 9 | BC10: =SUMIFS('List Order'!T:T,'List Order'!C:C,"2025",'List Order'!B:B,"April",'List Order'!H:H,"Upgrade",'List Order'!I:I,"Connectivity") -> 112245866 | BD10: =COUNTIFS('List Order'!C:C,"2025",'List Order'!B:B,"Mei",'List Order'!H:H,"Upgrade",'List Order'!I:I,"Connectivity") -> 3 | BE10: =SUMIFS('List Order'!T:T,'List Order'!C:C,"2025",'List Order'!B:B,"Mei",'List Order'!H:H,"Upgrade",'List Order'!I:I,"Connectivity") -> 21648166 | BF10: =COUNTIFS('List Order'!C:C,"2025",'List Order'!B:B,"Juni",'List Order'!H:H,"Upgrade",'List Order'!I:I,"Connectivity") -> 2 | BG10: =SUMIFS('List Order'!T:T,'List Order'!C:C,"2025",'List Order'!B:B,"Juni",'List Order'!H:H,"Upgrade",'List Order'!I:I,"Connectivity") -> 2571000 | BH10: =COUNTIFS('List Order'!C:C,"2025",'List Order'!B:B,"Juli",'List Order'!H:H,"Upgrade",'List Order'!I:I,"Connectivity") -> 0 | BI10: =SUMIFS('List Order'!T:T,'List Order'!C:C,"2025",'List Order'!B:B,"Juli",'List Order'!H:H,"Upgrade",'List Order'!I:I,"Connectivity") -> 0 | BJ10: =COUNTIFS('List Order'!C:C,"2025",'List Order'!B:B,"Agustus",'List Order'!H:H,"Upgrade",'List Order'!I:I,"Connectivity") -> 1 | BK10: =SUMIFS('List Order'!T:T,'List Order'!C:C,"2025",'List Order'!B:B,"Agustus",'List Order'!H:H,"Upgrade",'List Order'!I:I,"Connectivity") -> 0 | BL10: =COUNTIFS('List Order'!C:C,"2025",'List Order'!B:B,"September",'List Order'!H:H,"Upgrade",'List Order'!I:I,"Connectivity") -> 1 | BM10: =SUMIFS('List Order'!T:T,'List Order'!C:C,"2025",'List Order'!B:B,"September",'List Order'!H:H,"Upgrade",'List Order'!I:I,"Connectivity") -> 0 | BN10: =COUNTIFS('List Order'!C:C,"2025",'List Order'!B:B,"Oktober",'List Order'!H:H,"Upgrade",'List Order'!I:I,"Connectivity") -> 4 | BO10: =SUMIFS('List Order'!T:T,'List Order'!C:C,"2025",'List Order'!B:B,"Oktober",'List Order'!H:H,"Upgrade",'List Order'!I:I,"Connectivity") -> 0 | BP10: =COUNTIFS('List Order'!C:C,"2025",'List Order'!B:B,"November",'List Order'!H:H,"Upgrade",'List Order'!I:I,"Connectivity") -> 4 | BQ10: =SUMIFS('List Order'!T:T,'List Order'!C:C,"2025",'List Order'!B:B,"November",'List Order'!H:H,"Upgrade",'List Order'!I:I,"Connectivity") -> 0 | BR10: =COUNTIFS('List Order'!C:C,"2025",'List Order'!B:B,"Desember",'List Order'!H:H,"Upgrade",'List Order'!I:I,"Connectivity") -> 0 | BS10: =SUMIFS('List Order'!T:T,'List Order'!C:C,"2025",'List Order'!B:B,"Desember",'List Order'!H:H,"Upgrade",'List Order'!I:I,"Connectivity") -> 0
AF11: Januari | AG11: Februari | AH11: Maret | AI11: April | AJ11: Mei | AK11: Juni | AL11: Juli | AM11: Agustus | AN11: September | AO11: Oktober | AP11: November | AQ11: Desember | AU11: Downgrade | AV11: =COUNTIFS('List Order'!C:C,"2025",'List Order'!B:B,"Januari",'List Order'!H:H,"Downgrade",'List Order'!I:I,"Connectivity") -> 0 | AW11: =SUMIFS('List Order'!T:T,'List Order'!C:C,"2025",'List Order'!B:B,"Januari",'List Order'!H:H,"Downgrade",'List Order'!I:I,"Connectivity") -> 0 | AX11: =COUNTIFS('List Order'!C:C,"2025",'List Order'!B:B,"Februari",'List Order'!H:H,"Downgrade",'List Order'!I:I,"Connectivity") -> 3 | AY11: =SUMIFS('List Order'!T:T,'List Order'!C:C,"2025",'List Order'!B:B,"Februari",'List Order'!H:H,"Downgrade",'List Order'!I:I,"Connectivity") -> 8935200 | AZ11: =COUNTIFS('List Order'!C:C,"2025",'List Order'!B:B,"Maret",'List Order'!H:H,"Downgrade",'List Order'!I:I,"Connectivity") -> 0 | BA11: =SUMIFS('List Order'!T:T,'List Order'!C:C,"2025",'List Order'!B:B,"Maret",'List Order'!H:H,"Downgrade",'List Order'!I:I,"Connectivity") -> 0 | BB11: =COUNTIFS('List Order'!C:C,"2025",'List Order'!B:B,"April",'List Order'!H:H,"Downgrade",'List Order'!I:I,"Connectivity") -> 1 | BC11: =SUMIFS('List Order'!T:T,'List Order'!C:C,"2025",'List Order'!B:B,"April",'List Order'!H:H,"Downgrade",'List Order'!I:I,"Connectivity") -> 1094400 | BD11: =COUNTIFS('List Order'!C:C,"2025",'List Order'!B:B,"Mei",'List Order'!H:H,"Downgrade",'List Order'!I:I,"Connectivity") -> 1 | BE11: =SUMIFS('List Order'!T:T,'List Order'!C:C,"2025",'List Order'!B:B,"Mei",'List Order'!H:H,"Downgrade",'List Order'!I:I,"Connectivity") -> 0 | BF11: =COUNTIFS('List Order'!C:C,"2025",'List Order'!B:B,"Juni",'List Order'!H:H,"Downgrade",'List Order'!I:I,"Connectivity") -> 0 | BG11: =SUMIFS('List Order'!T:T,'List Order'!C:C,"2025",'List Order'!B:B,"Juni",'List Order'!H:H,"Downgrade",'List Order'!I:I,"Connectivity") -> 0 | BH11: =COUNTIFS('List Order'!C:C,"2025",'List Order'!B:B,"Juli",'List Order'!H:H,"Downgrade",'List Order'!I:I,"Connectivity") -> 0 | BI11: =SUMIFS('List Order'!T:T,'List Order'!C:C,"2025",'List Order'!B:B,"Juli",'List Order'!H:H,"Downgrade",'List Order'!I:I,"Connectivity") -> 0 | BJ11: =COUNTIFS('List Order'!C:C,"2025",'List Order'!B:B,"Agustus",'List Order'!H:H,"Downgrade",'List Order'!I:I,"Connectivity") -> 0 | BK11: =SUMIFS('List Order'!T:T,'List Order'!C:C,"2025",'List Order'!B:B,"Agustus",'List Order'!H:H,"Downgrade",'List Order'!I:I,"Connectivity") -> 0 | BL11: =COUNTIFS('List Order'!C:C,"2025",'List Order'!B:B,"September",'List Order'!H:H,"Downgrade",'List Order'!I:I,"Connectivity") -> 0 | BM11: =SUMIFS('List Order'!T:T,'List Order'!C:C,"2025",'List Order'!B:B,"September",'List Order'!H:H,"Downgrade",'List Order'!I:I,"Connectivity") -> 0 | BN11: =COUNTIFS('List Order'!C:C,"2025",'List Order'!B:B,"Oktober",'List Order'!H:H,"Downgrade",'List Order'!I:I,"Connectivity") -> 0 | BO11: =SUMIFS('List Order'!T:T,'List Order'!C:C,"2025",'List Order'!B:B,"Oktober",'List Order'!H:H,"Downgrade",'List Order'!I:I,"Connectivity") -> 0 | BP11: =COUNTIFS('List Order'!C:C,"2025",'List Order'!B:B,"November",'List Order'!H:H,"Downgrade",'List Order'!I:I,"Connectivity") -> 0 | BQ11: =SUMIFS('List Order'!T:T,'List Order'!C:C,"2025",'List Order'!B:B,"November",'List Order'!H:H,"Downgrade",'List Order'!I:I,"Connectivity") -> 0 | BR11: =COUNTIFS('List Order'!C:C,"2025",'List Order'!B:B,"Desember",'List Order'!H:H,"Downgrade",'List Order'!I:I,"Connectivity") -> 1 | BS11: =SUMIFS('List Order'!T:T,'List Order'!C:C,"2025",'List Order'!B:B,"Desember",'List Order'!H:H,"Downgrade",'List Order'!I:I,"Connectivity") -> 0
AE12: Revenue Project | AF12: =SUMIFS('List Project'!I:I,'List Project'!D:D,"Januari",'List Project'!C:C,"2025") -> 55157828477 | AG12: =SUMIFS('List Project'!I:I,'List Project'!D:D,"Februari",'List Project'!C:C,"2025") -> 13464557806 | AH12: =SUMIFS('List Project'!I:I,'List Project'!D:D,"Maret",'List Project'!C:C,"2025") -> 12525655865 | AI12: =SUMIFS('List Project'!I:I,'List Project'!D:D,"April",'List Project'!C:C,"2025") -> 4546519554 | AJ12: =SUMIFS('List Project'!I:I,'List Project'!D:D,"Mei",'List Project'!C:C,"2025") -> 1492660000 | AK12: =SUMIFS('List Project'!I:I,'List Project'!D:D,"Juni",'List Project'!C:C,"2025") -> 22674005152 | AL12: =SUMIFS('List Project'!I:I,'List Project'!D:D,"Juli",'List Project'!C:C,"2025") -> 19665001612 | AM12: =SUMIFS('List Project'!I:I,'List Project'!D:D,"Agustus",'List Project'!C:C,"2025") -> 22572928806 | AN12: =SUMIFS('List Project'!I:I,'List Project'!D:D,"September",'List Project'!C:C,"2025") -> 1.2642228e+11 | AO12: =SUMIFS('List Project'!I:I,'List Project'!D:D,"Oktober",'List Project'!C:C,"2025") -> 2.6911277e+11 | AP12: =SUMIFS('List Project'!I:I,'List Project'!D:D,"November",'List Project'!C:C,"2025") -> 39966893707 | AQ12: =SUMIFS('List Project'!I:I,'List Project'!D:D,"Desember",'List Project'!C:C,"2025") -> 972717736854 | AU12: Dismentle | AV12: =COUNTIFS('List Order'!C:C,"2025",'List Order'!B:B,"Januari",'List Order'!H:H,"Dismantle",'List Order'!I:I,"Connectivity") -> 3 | AW12: =SUMIFS('List Order'!T:T,'List Order'!C:C,"2025",'List Order'!B:B,"Januari",'List Order'!H:H,"Dismantle",'List Order'!I:I,"Connectivity") -> 13323200 | AX12: =COUNTIFS('List Order'!C:C,"2025",'List Order'!B:B,"Februari",'List Order'!H:H,"Dismantle",'List Order'!I:I,"Connectivity") -> 8 | AY12: =SUMIFS('List Order'!T:T,'List Order'!C:C,"2025",'List Order'!B:B,"Februari",'List Order'!H:H,"Dismantle",'List Order'!I:I,"Connectivity") -> 16100000 | AZ12: =COUNTIFS('List Order'!C:C,"2025",'List Order'!B:B,"Maret",'List Order'!H:H,"Dismantle",'List Order'!I:I,"Connectivity") -> 25 | BA12: =SUMIFS('List Order'!T:T,'List Order'!C:C,"2025",'List Order'!B:B,"Maret",'List Order'!H:H,"Dismantle",'List Order'!I:I,"Connectivity") -> 126799950 | BB12: =COUNTIFS('List Order'!C:C,"2025",'List Order'!B:B,"April",'List Order'!H:H,"Dismantle",'List Order'!I:I,"Connectivity") -> 5 | BC12: =SUMIFS('List Order'!T:T,'List Order'!C:C,"2025",'List Order'!B:B,"April",'List Order'!H:H,"Dismantle",'List Order'!I:I,"Connectivity") -> 7100000 | BD12: =COUNTIFS('List Order'!C:C,"2025",'List Order'!B:B,"Mei",'List Order'!H:H,"Dismantle",'List Order'!I:I,"Connectivity") -> 16 | BE12: =SUMIFS('List Order'!T:T,'List Order'!C:C,"2025",'List Order'!B:B,"Mei",'List Order'!H:H,"Dismantle",'List Order'!I:I,"Connectivity") -> 90424000 | BF12: =COUNTIFS('List Order'!C:C,"2025",'List Order'!B:B,"Juni",'List Order'!H:H,"Dismantle",'List Order'!I:I,"Connectivity") -> 5 | BG12: =SUMIFS('List Order'!T:T,'List Order'!C:C,"2025",'List Order'!B:B,"Juni",'List Order'!H:H,"Dismantle",'List Order'!I:I,"Connectivity") -> 6480500 | BH12: =COUNTIFS('List Order'!C:C,"2025",'List Order'!B:B,"Juli",'List Order'!H:H,"Dismantle",'List Order'!I:I,"Connectivity") -> 4 | BI12: =SUMIFS('List Order'!T:T,'List Order'!C:C,"2025",'List Order'!B:B,"Juli",'List Order'!H:H,"Dismantle",'List Order'!I:I,"Connectivity") -> 0 | BJ12: =COUNTIFS('List Order'!C:C,"2025",'List Order'!B:B,"Agustus",'List Order'!H:H,"Dismantle",'List Order'!I:I,"Connectivity") -> 3 | BK12: =SUMIFS('List Order'!T:T,'List Order'!C:C,"2025",'List Order'!B:B,"Agustus",'List Order'!H:H,"Dismantle",'List Order'!I:I,"Connectivity") -> 9112000 | BL12: =COUNTIFS('List Order'!C:C,"2025",'List Order'!B:B,"September",'List Order'!H:H,"Dismantle",'List Order'!I:I,"Connectivity") -> 2 | BM12: =SUMIFS('List Order'!T:T,'List Order'!C:C,"2025",'List Order'!B:B,"September",'List Order'!H:H,"Dismantle",'List Order'!I:I,"Connectivity") -> 0 | BN12: =COUNTIFS('List Order'!C:C,"2025",'List Order'!B:B,"Oktober",'List Order'!H:H,"Dismantle",'List Order'!I:I,"Connectivity") -> 6 | BO12: =SUMIFS('List Order'!T:T,'List Order'!C:C,"2025",'List Order'!B:B,"Oktober",'List Order'!H:H,"Dismantle",'List Order'!I:I,"Connectivity") -> 0 | BP12: =COUNTIFS('List Order'!C:C,"2025",'List Order'!B:B,"November",'List Order'!H:H,"Dismantle",'List Order'!I:I,"Connectivity") -> 9 | BQ12: =SUMIFS('List Order'!T:T,'List Order'!C:C,"2025",'List Order'!B:B,"November",'List Order'!H:H,"Dismantle",'List Order'!I:I,"Connectivity") -> 0 | BR12: =COUNTIFS('List Order'!C:C,"2025",'List Order'!B:B,"Desember",'List Order'!H:H,"Dismantle",'List Order'!I:I,"Connectivity") -> 12 | BS12: =SUMIFS('List Order'!T:T,'List Order'!C:C,"2025",'List Order'!B:B,"Desember",'List Order'!H:H,"Dismantle",'List Order'!I:I,"Connectivity") -> 0
AE13: CRM | AF13: =COUNTIFS('List Project'!C:C,"2025",'List Project'!D:D,"Januari",'List Project'!F:F,"CRM") -> 11 | AG13: =COUNTIFS('List Project'!C:C,"2025",'List Project'!D:D,"Februari",'List Project'!F:F,"CRM") -> 5 | AH13: =COUNTIFS('List Project'!C:C,"2025",'List Project'!D:D,"Maret",'List Project'!F:F,"CRM") -> 6 | AI13: =COUNTIFS('List Project'!C:C,"2025",'List Project'!D:D,"April",'List Project'!F:F,"CRM") -> 6 | AJ13: =COUNTIFS('List Project'!C:C,"2025",'List Project'!D:D,"Mei",'List Project'!F:F,"CRM") -> 2 | AK13: =COUNTIFS('List Project'!C:C,"2025",'List Project'!D:D,"Juni",'List Project'!F:F,"CRM") -> 5 | AL13: =COUNTIFS('List Project'!C:C,"2025",'List Project'!D:D,"Juli",'List Project'!F:F,"CRM") -> 11 | AM13: =COUNTIFS('List Project'!C:C,"2025",'List Project'!D:D,"Agustus",'List Project'!F:F,"CRM") -> 7 | AN13: =COUNTIFS('List Project'!C:C,"2025",'List Project'!D:D,"September",'List Project'!F:F,"CRM") -> 5 | AO13: =COUNTIFS('List Project'!C:C,"2025",'List Project'!D:D,"Oktober",'List Project'!F:F,"CRM") -> 10 | AP13: =COUNTIFS('List Project'!C:C,"2025",'List Project'!D:D,"November",'List Project'!F:F,"CRM") -> 10 | AQ13: =COUNTIFS('List Project'!C:C,"2025",'List Project'!D:D,"Desember",'List Project'!F:F,"CRM") -> 8 | AU13: IPPBX SIP TRUNK | AV13: =COUNTIFS('List Order'!B:B,"Januari",'List Order'!I:I,"IPPBX",'List Order'!C:C,"2025") -> 0 | AX13: =COUNTIFS('List Order'!B:B,"Februari",'List Order'!I:I,"IPPBX",'List Order'!C:C,"2025") -> 0 | AZ13: =COUNTIFS('List Order'!B:B,"Maret",'List Order'!I:I,"IPPBX",'List Order'!C:C,"2025") -> 1 | BB13: =COUNTIFS('List Order'!B:B,"April",'List Order'!I:I,"IPPBX",'List Order'!C:C,"2025") -> 0 | BD13: =COUNTIFS('List Order'!B:B,"Mei",'List Order'!I:I,"IPPBX",'List Order'!C:C,"2025") -> 1 | BF13: =COUNTIFS('List Order'!B:B,"Juni",'List Order'!I:I,"IPPBX",'List Order'!C:C,"2025") -> 0 | BH13: =COUNTIFS('List Order'!B:B,"Juli",'List Order'!I:I,"IPPBX",'List Order'!C:C,"2025") -> 1 | BJ13: =COUNTIFS('List Order'!B:B,"Agustus",'List Order'!I:I,"IPPBX",'List Order'!C:C,"2025") -> 2 | BL13: =COUNTIFS('List Order'!B:B,"September",'List Order'!I:I,"IPPBX",'List Order'!C:C,"2025") -> 0 | BN13: =COUNTIFS('List Order'!B:B,"Oktober",'List Order'!I:I,"IPPBX",'List Order'!C:C,"2025") -> 2 | BP13: =COUNTIFS('List Order'!B:B,"November",'List Order'!I:I,"IPPBX",'List Order'!C:C,"2025") -> 3 | BR13: =COUNTIFS('List Order'!B:B,"Desember",'List Order'!I:I,"IPPBX",'List Order'!C:C,"2025") -> 0
AE14: SSO | AF14: =COUNTIFS('List Project'!C:C,"2025",'List Project'!D:D,"Januari",'List Project'!F:F,"SSO") -> 0 | AG14: =COUNTIFS('List Project'!C:C,"2025",'List Project'!D:D,"Februari",'List Project'!F:F,"SSO") -> 1 | AH14: =COUNTIFS('List Project'!C:C,"2025",'List Project'!D:D,"Maret",'List Project'!F:F,"SSO") -> 0 | AI14: =COUNTIFS('List Project'!C:C,"2025",'List Project'!D:D,"April",'List Project'!F:F,"SSO") -> 0 | AJ14: =COUNTIFS('List Project'!C:C,"2025",'List Project'!D:D,"Mei",'List Project'!F:F,"SSO") -> 0 | AK14: =COUNTIFS('List Project'!C:C,"2025",'List Project'!D:D,"Juni",'List Project'!F:F,"SSO") -> 0 | AL14: =COUNTIFS('List Project'!C:C,"2025",'List Project'!D:D,"Juli",'List Project'!F:F,"SSO") -> 0 | AM14: =COUNTIFS('List Project'!C:C,"2025",'List Project'!D:D,"Agustus",'List Project'!F:F,"SSO") -> 0 | AN14: =COUNTIFS('List Project'!C:C,"2025",'List Project'!D:D,"September",'List Project'!F:F,"SSO") -> 0 | AO14: =COUNTIFS('List Project'!C:C,"2025",'List Project'!D:D,"Oktober",'List Project'!F:F,"SSO") -> 0 | AP14: =COUNTIFS('List Project'!C:C,"2025",'List Project'!D:D,"November",'List Project'!F:F,"SSO") -> 0 | AQ14: =COUNTIFS('List Project'!C:C,"2025",'List Project'!D:D,"Desember",'List Project'!F:F,"SSO") -> 0 | AU14: PSB | AV14: =COUNTIFS('List Order'!C:C,"2025",'List Order'!B:B,"Januari",'List Order'!H:H,"PSB",'List Order'!I:I,"IPPBX") -> 0 | AW14: =SUMIFS('List Order'!T:T,'List Order'!C:C,"2025",'List Order'!B:B,"Januari",'List Order'!H:H,"PSB",'List Order'!I:I,"IPPBX") -> 0 | AX14: =COUNTIFS('List Order'!C:C,"2025",'List Order'!B:B,"Februari",'List Order'!H:H,"PSB",'List Order'!I:I,"IPPBX") -> 0 | AY14: =SUMIFS('List Order'!T:T,'List Order'!C:C,"2025",'List Order'!B:B,"Februari",'List Order'!H:H,"PSB",'List Order'!I:I,"IPPBX") -> 0 | AZ14: =COUNTIFS('List Order'!C:C,"2025",'List Order'!B:B,"Maret",'List Order'!H:H,"PSB",'List Order'!I:I,"IPPBX") -> 0 | BA14: =SUMIFS('List Order'!T:T,'List Order'!C:C,"2025",'List Order'!B:B,"Maret",'List Order'!H:H,"PSB",'List Order'!I:I,"IPPBX") -> 0 | BB14: =COUNTIFS('List Order'!C:C,"2025",'List Order'!B:B,"April",'List Order'!H:H,"PSB",'List Order'!I:I,"IPPBX") -> 0 | BC14: =SUMIFS('List Order'!T:T,'List Order'!C:C,"2025",'List Order'!B:B,"April",'List Order'!H:H,"PSB",'List Order'!I:I,"IPPBX") -> 0 | BD14: =COUNTIFS('List Order'!C:C,"2025",'List Order'!B:B,"Mei",'List Order'!H:H,"PSB",'List Order'!I:I,"IPPBX") -> 0 | BE14: =SUMIFS('List Order'!T:T,'List Order'!C:C,"2025",'List Order'!B:B,"Mei",'List Order'!H:H,"PSB",'List Order'!I:I,"IPPBX") -> 0 | BF14: =COUNTIFS('List Order'!C:C,"2025",'List Order'!B:B,"Juni",'List Order'!H:H,"PSB",'List Order'!I:I,"IPPBX") -> 0 | BG14: =SUMIFS('List Order'!T:T,'List Order'!C:C,"2025",'List Order'!B:B,"Juni",'List Order'!H:H,"PSB",'List Order'!I:I,"IPPBX") -> 0 | BH14: =COUNTIFS('List Order'!C:C,"2025",'List Order'!B:B,"Juli",'List Order'!H:H,"PSB",'List Order'!I:I,"IPPBX") -> 0 | BI14: =SUMIFS('List Order'!T:T,'List Order'!C:C,"2025",'List Order'!B:B,"Juli",'List Order'!H:H,"PSB",'List Order'!I:I,"IPPBX") -> 0 | BJ14: =COUNTIFS('List Order'!C:C,"2025",'List Order'!B:B,"Agustus",'List Order'!H:H,"PSB",'List Order'!I:I,"IPPBX") -> 0 | BK14: =SUMIFS('List Order'!T:T,'List Order'!C:C,"2025",'List Order'!B:B,"Agustus",'List Order'!H:H,"PSB",'List Order'!I:I,"IPPBX") -> 0 | BL14: =COUNTIFS('List Order'!C:C,"2025",'List Order'!B:B,"September",'List Order'!H:H,"PSB",'List Order'!I:I,"IPPBX") -> 0 | BM14: =SUMIFS('List Order'!T:T,'List Order'!C:C,"2025",'List Order'!B:B,"September",'List Order'!H:H,"PSB",'List Order'!I:I,"IPPBX") -> 0 | BN14: =COUNTIFS('List Order'!C:C,"2025",'List Order'!B:B,"Oktober",'List Order'!H:H,"PSB",'List Order'!I:I,"IPPBX") -> 0 | BO14: =SUMIFS('List Order'!T:T,'List Order'!C:C,"2025",'List Order'!B:B,"Oktober",'List Order'!H:H,"PSB",'List Order'!I:I,"IPPBX") -> 0 | BP14: =COUNTIFS('List Order'!C:C,"2025",'List Order'!B:B,"November",'List Order'!H:H,"PSB",'List Order'!I:I,"IPPBX") -> 0 | BQ14: =SUMIFS('List Order'!T:T,'List Order'!C:C,"2025",'List Order'!B:B,"November",'List Order'!H:H,"PSB",'List Order'!I:I,"IPPBX") -> 0 | BR14: =COUNTIFS('List Order'!C:C,"2025",'List Order'!B:B,"Desember",'List Order'!H:H,"PSB",'List Order'!I:I,"IPPBX") -> 0 | BS14: =SUMIFS('List Order'!T:T,'List Order'!C:C,"2025",'List Order'!B:B,"Desember",'List Order'!H:H,"PSB",'List Order'!I:I,"IPPBX") -> 0
AE15: Nomor Akses | AF15: =COUNTIFS('List Project'!C:C,"2025",'List Project'!D:D,"Januari",'List Project'!F:F,"Nomor Akses") -> 9 | AG15: =COUNTIFS('List Project'!C:C,"2025",'List Project'!D:D,"Februari",'List Project'!F:F,"Nomor Akses") -> 3 | AH15: =COUNTIFS('List Project'!C:C,"2025",'List Project'!D:D,"Maret",'List Project'!F:F,"Nomor Akses") -> 0 | AI15: =COUNTIFS('List Project'!C:C,"2025",'List Project'!D:D,"April",'List Project'!F:F,"Nomor Akses") -> 2 | AJ15: =COUNTIFS('List Project'!C:C,"2025",'List Project'!D:D,"Mei",'List Project'!F:F,"Nomor Akses") -> 4 | AK15: =COUNTIFS('List Project'!C:C,"2025",'List Project'!D:D,"Juni",'List Project'!F:F,"Nomor Akses") -> 2 | AL15: =COUNTIFS('List Project'!C:C,"2025",'List Project'!D:D,"Juli",'List Project'!F:F,"Nomor Akses") -> 6 | AM15: =COUNTIFS('List Project'!C:C,"2025",'List Project'!D:D,"Agustus",'List Project'!F:F,"Nomor Akses") -> 3 | AN15: =COUNTIFS('List Project'!C:C,"2025",'List Project'!D:D,"September",'List Project'!F:F,"Nomor Akses") -> 3 | AO15: =COUNTIFS('List Project'!C:C,"2025",'List Project'!D:D,"Oktober",'List Project'!F:F,"Nomor Akses") -> 2 | AP15: =COUNTIFS('List Project'!C:C,"2025",'List Project'!D:D,"November",'List Project'!F:F,"Nomor Akses") -> 0 | AQ15: =COUNTIFS('List Project'!C:C,"2025",'List Project'!D:D,"Desember",'List Project'!F:F,"Nomor Akses") -> 1 | AU15: Upgrade | AV15: =COUNTIFS('List Order'!C:C,"2025",'List Order'!B:B,"Januari",'List Order'!H:H,"Upgrade",'List Order'!I:I,"IPPBX") -> 0 | AW15: =SUMIFS('List Order'!T:T,'List Order'!C:C,"2025",'List Order'!B:B,"Januari",'List Order'!H:H,"Upgrade",'List Order'!I:I,"IPPBX") -> 0 | AX15: =COUNTIFS('List Order'!C:C,"2025",'List Order'!B:B,"Februari",'List Order'!H:H,"Upgrade",'List Order'!I:I,"IPPBX") -> 0 | AY15: =SUMIFS('List Order'!T:T,'List Order'!C:C,"2025",'List Order'!B:B,"Februari",'List Order'!H:H,"Upgrade",'List Order'!I:I,"IPPBX") -> 0 | AZ15: =COUNTIFS('List Order'!C:C,"2025",'List Order'!B:B,"Maret",'List Order'!H:H,"Upgrade",'List Order'!I:I,"IPPBX") -> 0 | BA15: =SUMIFS('List Order'!T:T,'List Order'!C:C,"2025",'List Order'!B:B,"Maret",'List Order'!H:H,"Upgrade",'List Order'!I:I,"IPPBX") -> 0 | BB15: =COUNTIFS('List Order'!C:C,"2025",'List Order'!B:B,"April",'List Order'!H:H,"Upgrade",'List Order'!I:I,"IPPBX") -> 0 | BC15: =SUMIFS('List Order'!T:T,'List Order'!C:C,"2025",'List Order'!B:B,"April",'List Order'!H:H,"Upgrade",'List Order'!I:I,"IPPBX") -> 0 | BD15: =COUNTIFS('List Order'!C:C,"2025",'List Order'!B:B,"Mei",'List Order'!H:H,"Upgrade",'List Order'!I:I,"IPPBX") -> 0 | BE15: =SUMIFS('List Order'!T:T,'List Order'!C:C,"2025",'List Order'!B:B,"Mei",'List Order'!H:H,"Upgrade",'List Order'!I:I,"IPPBX") -> 0 | BF15: =COUNTIFS('List Order'!C:C,"2025",'List Order'!B:B,"Juni",'List Order'!H:H,"Upgrade",'List Order'!I:I,"IPPBX") -> 0 | BG15: =SUMIFS('List Order'!T:T,'List Order'!C:C,"2025",'List Order'!B:B,"Juni",'List Order'!H:H,"Upgrade",'List Order'!I:I,"IPPBX") -> 0 | BH15: =COUNTIFS('List Order'!C:C,"2025",'List Order'!B:B,"Juli",'List Order'!H:H,"Upgrade",'List Order'!I:I,"IPPBX") -> 0 | BI15: =SUMIFS('List Order'!T:T,'List Order'!C:C,"2025",'List Order'!B:B,"Juli",'List Order'!H:H,"Upgrade",'List Order'!I:I,"IPPBX") -> 0 | BJ15: =COUNTIFS('List Order'!C:C,"2025",'List Order'!B:B,"Agustus",'List Order'!H:H,"Upgrade",'List Order'!I:I,"IPPBX") -> 0 | BK15: =SUMIFS('List Order'!T:T,'List Order'!C:C,"2025",'List Order'!B:B,"Agustus",'List Order'!H:H,"Upgrade",'List Order'!I:I,"IPPBX") -> 0 | BL15: =COUNTIFS('List Order'!C:C,"2025",'List Order'!B:B,"September",'List Order'!H:H,"Upgrade",'List Order'!I:I,"IPPBX") -> 0 | BM15: =SUMIFS('List Order'!T:T,'List Order'!C:C,"2025",'List Order'!B:B,"September",'List Order'!H:H,"Upgrade",'List Order'!I:I,"IPPBX") -> 0 | BN15: =COUNTIFS('List Order'!C:C,"2025",'List Order'!B:B,"Oktober",'List Order'!H:H,"Upgrade",'List Order'!I:I,"IPPBX") -> 0 | BO15: =SUMIFS('List Order'!T:T,'List Order'!C:C,"2025",'List Order'!B:B,"Oktober",'List Order'!H:H,"Upgrade",'List Order'!I:I,"IPPBX") -> 0 | BP15: =COUNTIFS('List Order'!C:C,"2025",'List Order'!B:B,"November",'List Order'!H:H,"Upgrade",'List Order'!I:I,"IPPBX") -> 0 | BQ15: =SUMIFS('List Order'!T:T,'List Order'!C:C,"2025",'List Order'!B:B,"November",'List Order'!H:H,"Upgrade",'List Order'!I:I,"IPPBX") -> 0 | BR15: =COUNTIFS('List Order'!C:C,"2025",'List Order'!B:B,"Desember",'List Order'!H:H,"Upgrade",'List Order'!I:I,"IPPBX") -> 0 | BS15: =SUMIFS('List Order'!T:T,'List Order'!C:C,"2025",'List Order'!B:B,"Desember",'List Order'!H:H,"Upgrade",'List Order'!I:I,"IPPBX") -> 0
AU16: Downgrade | AV16: =COUNTIFS('List Order'!C:C,"2025",'List Order'!B:B,"Januari",'List Order'!H:H,"Downgrade",'List Order'!I:I,"IPPBX") -> 0 | AW16: =SUMIFS('List Order'!T:T,'List Order'!C:C,"2025",'List Order'!B:B,"Januari",'List Order'!H:H,"Downgrade",'List Order'!I:I,"IPPBX") -> 0 | AX16: =COUNTIFS('List Order'!C:C,"2025",'List Order'!B:B,"Februari",'List Order'!H:H,"Downgrade",'List Order'!I:I,"IPPBX") -> 0 | AY16: =SUMIFS('List Order'!T:T,'List Order'!C:C,"2025",'List Order'!B:B,"Februari",'List Order'!H:H,"Downgrade",'List Order'!I:I,"IPPBX") -> 0 | AZ16: =COUNTIFS('List Order'!C:C,"2025",'List Order'!B:B,"Maret",'List Order'!H:H,"Downgrade",'List Order'!I:I,"IPPBX") -> 0 | BA16: =SUMIFS('List Order'!T:T,'List Order'!C:C,"2025",'List Order'!B:B,"Maret",'List Order'!H:H,"Downgrade",'List Order'!I:I,"IPPBX") -> 0 | BB16: =COUNTIFS('List Order'!C:C,"2025",'List Order'!B:B,"April",'List Order'!H:H,"Downgrade",'List Order'!I:I,"IPPBX") -> 0 | BC16: =SUMIFS('List Order'!T:T,'List Order'!C:C,"2025",'List Order'!B:B,"April",'List Order'!H:H,"Downgrade",'List Order'!I:I,"IPPBX") -> 0 | BD16: =COUNTIFS('List Order'!C:C,"2025",'List Order'!B:B,"Mei",'List Order'!H:H,"Downgrade",'List Order'!I:I,"IPPBX") -> 0 | BE16: =SUMIFS('List Order'!T:T,'List Order'!C:C,"2025",'List Order'!B:B,"Mei",'List Order'!H:H,"Downgrade",'List Order'!I:I,"IPPBX") -> 0 | BF16: =COUNTIFS('List Order'!C:C,"2025",'List Order'!B:B,"Juni",'List Order'!H:H,"Downgrade",'List Order'!I:I,"IPPBX") -> 0 | BG16: =SUMIFS('List Order'!T:T,'List Order'!C:C,"2025",'List Order'!B:B,"Juni",'List Order'!H:H,"Downgrade",'List Order'!I:I,"IPPBX") -> 0 | BH16: =COUNTIFS('List Order'!C:C,"2025",'List Order'!B:B,"Juli",'List Order'!H:H,"Downgrade",'List Order'!I:I,"IPPBX") -> 0 | BI16: =SUMIFS('List Order'!T:T,'List Order'!C:C,"2025",'List Order'!B:B,"Juli",'List Order'!H:H,"Downgrade",'List Order'!I:I,"IPPBX") -> 0 | BJ16: =COUNTIFS('List Order'!C:C,"2025",'List Order'!B:B,"Agustus",'List Order'!H:H,"Downgrade",'List Order'!I:I,"IPPBX") -> 0 | BK16: =SUMIFS('List Order'!T:T,'List Order'!C:C,"2025",'List Order'!B:B,"Agustus",'List Order'!H:H,"Downgrade",'List Order'!I:I,"IPPBX") -> 0 | BL16: =COUNTIFS('List Order'!C:C,"2025",'List Order'!B:B,"September",'List Order'!H:H,"Downgrade",'List Order'!I:I,"IPPBX") -> 0 | BM16: =SUMIFS('List Order'!T:T,'List Order'!C:C,"2025",'List Order'!B:B,"September",'List Order'!H:H,"Downgrade",'List Order'!I:I,"IPPBX") -> 0 | BN16: =COUNTIFS('List Order'!C:C,"2025",'List Order'!B:B,"Oktober",'List Order'!H:H,"Downgrade",'List Order'!I:I,"IPPBX") -> 0 | BO16: =SUMIFS('List Order'!T:T,'List Order'!C:C,"2025",'List Order'!B:B,"Oktober",'List Order'!H:H,"Downgrade",'List Order'!I:I,"IPPBX") -> 0 | BP16: =COUNTIFS('List Order'!C:C,"2025",'List Order'!B:B,"November",'List Order'!H:H,"Downgrade",'List Order'!I:I,"IPPBX") -> 0 | BQ16: =SUMIFS('List Order'!T:T,'List Order'!C:C,"2025",'List Order'!B:B,"November",'List Order'!H:H,"Downgrade",'List Order'!I:I,"IPPBX") -> 0 | BR16: =COUNTIFS('List Order'!C:C,"2025",'List Order'!B:B,"Desember",'List Order'!H:H,"Downgrade",'List Order'!I:I,"IPPBX") -> 0 | BS16: =SUMIFS('List Order'!T:T,'List Order'!C:C,"2025",'List Order'!B:B,"Desember",'List Order'!H:H,"Downgrade",'List Order'!I:I,"IPPBX") -> 0
AF17: Total Project | AG17: Done | AH17: OGP | AI17: Revenue | AL17: Adi | AM17: Dwi | AN17: Duta | AO17: Gugum | AU17: Dismentle | AV17: =COUNTIFS('List Order'!C:C,"2025",'List Order'!B:B,"Januari",'List Order'!H:H,"Dismantle",'List Order'!I:I,"IPPBX") -> 0 | AW17: =SUMIFS('List Order'!T:T,'List Order'!C:C,"2025",'List Order'!B:B,"Januari",'List Order'!H:H,"Dismantle",'List Order'!I:I,"IPPBX") -> 0 | AX17: =COUNTIFS('List Order'!C:C,"2025",'List Order'!B:B,"Februari",'List Order'!H:H,"Dismantle",'List Order'!I:I,"IPPBX") -> 0 | AY17: =SUMIFS('List Order'!T:T,'List Order'!C:C,"2025",'List Order'!B:B,"Februari",'List Order'!H:H,"Dismantle",'List Order'!I:I,"IPPBX") -> 0 | AZ17: =COUNTIFS('List Order'!C:C,"2025",'List Order'!B:B,"Maret",'List Order'!H:H,"Dismantle",'List Order'!I:I,"IPPBX") -> 1 | BA17: =SUMIFS('List Order'!T:T,'List Order'!C:C,"2025",'List Order'!B:B,"Maret",'List Order'!H:H,"Dismantle",'List Order'!I:I,"IPPBX") -> 9981375 | BB17: =COUNTIFS('List Order'!C:C,"2025",'List Order'!B:B,"April",'List Order'!H:H,"Dismantle",'List Order'!I:I,"IPPBX") -> 0 | BC17: =SUMIFS('List Order'!T:T,'List Order'!C:C,"2025",'List Order'!B:B,"April",'List Order'!H:H,"Dismantle",'List Order'!I:I,"IPPBX") -> 0 | BD17: =COUNTIFS('List Order'!C:C,"2025",'List Order'!B:B,"Mei",'List Order'!H:H,"Dismantle",'List Order'!I:I,"IPPBX") -> 0 | BE17: =SUMIFS('List Order'!T:T,'List Order'!C:C,"2025",'List Order'!B:B,"Mei",'List Order'!H:H,"Dismantle",'List Order'!I:I,"IPPBX") -> 0 | BF17: =COUNTIFS('List Order'!C:C,"2025",'List Order'!B:B,"Juni",'List Order'!H:H,"Dismantle",'List Order'!I:I,"IPPBX") -> 0 | BG17: =SUMIFS('List Order'!T:T,'List Order'!C:C,"2025",'List Order'!B:B,"Juni",'List Order'!H:H,"Dismantle",'List Order'!I:I,"IPPBX") -> 0 | BH17: =COUNTIFS('List Order'!C:C,"2025",'List Order'!B:B,"Juli",'List Order'!H:H,"Dismantle",'List Order'!I:I,"IPPBX") -> 0 | BI17: =SUMIFS('List Order'!T:T,'List Order'!C:C,"2025",'List Order'!B:B,"Juli",'List Order'!H:H,"Dismantle",'List Order'!I:I,"IPPBX") -> 0 | BJ17: =COUNTIFS('List Order'!C:C,"2025",'List Order'!B:B,"Agustus",'List Order'!H:H,"Dismantle",'List Order'!I:I,"IPPBX") -> 1 | BK17: =SUMIFS('List Order'!T:T,'List Order'!C:C,"2025",'List Order'!B:B,"Agustus",'List Order'!H:H,"Dismantle",'List Order'!I:I,"IPPBX") -> 0 | BL17: =COUNTIFS('List Order'!C:C,"2025",'List Order'!B:B,"September",'List Order'!H:H,"Dismantle",'List Order'!I:I,"IPPBX") -> 0 | BM17: =SUMIFS('List Order'!T:T,'List Order'!C:C,"2025",'List Order'!B:B,"September",'List Order'!H:H,"Dismantle",'List Order'!I:I,"IPPBX") -> 0 | BN17: =COUNTIFS('List Order'!C:C,"2025",'List Order'!B:B,"Oktober",'List Order'!H:H,"Dismantle",'List Order'!I:I,"IPPBX") -> 0 | BO17: =SUMIFS('List Order'!T:T,'List Order'!C:C,"2025",'List Order'!B:B,"Oktober",'List Order'!H:H,"Dismantle",'List Order'!I:I,"IPPBX") -> 0 | BP17: =COUNTIFS('List Order'!C:C,"2025",'List Order'!B:B,"November",'List Order'!H:H,"Dismantle",'List Order'!I:I,"IPPBX") -> 2 | BQ17: =SUMIFS('List Order'!T:T,'List Order'!C:C,"2025",'List Order'!B:B,"November",'List Order'!H:H,"Dismantle",'List Order'!I:I,"IPPBX") -> 0 | BR17: =COUNTIFS('List Order'!C:C,"2025",'List Order'!B:B,"Desember",'List Order'!H:H,"Dismantle",'List Order'!I:I,"IPPBX") -> 0 | BS17: =SUMIFS('List Order'!T:T,'List Order'!C:C,"2025",'List Order'!B:B,"Desember",'List Order'!H:H,"Dismantle",'List Order'!I:I,"IPPBX") -> 0
AE18: Adi | AF18: =SUM(AF3:AQ3) -> 4 | AG18: =COUNTIFS('List Project'!C:C,"2025",'List Project'!P:P,"Done",'List Project'!O:O,"Adi") -> 3 | AH18: =COUNTIFS('List Project'!C:C,"2025",'List Project'!P:P,"OGP",'List Project'!O:O,"Adi") -> 1 | AI18: =SUMIFS('List Project'!I:I,'List Project'!O:O,"Adi",'List Project'!C:C,"2025") -> 49261735490 | AK18: Project | AL18: =AF18 -> 4 | AM18: =AF19 -> 33 | AN18: =AF20 -> 53 | AO18: =AF21 -> 32 | AU18: Colocation/ cndc | AV18: =COUNTIFS('List Order'!B:B,"Januari",'List Order'!I:I,"Colocation",'List Order'!C:C,"2025") -> 0 | AX18: =COUNTIFS('List Order'!B:B,"Februari",'List Order'!I:I,"Colocation",'List Order'!C:C,"2025") -> 0 | AZ18: =COUNTIFS('List Order'!B:B,"Maret",'List Order'!I:I,"Colocation",'List Order'!C:C,"2025") -> 0 | BB18: =COUNTIFS('List Order'!B:B,"April",'List Order'!I:I,"Colocation",'List Order'!C:C,"2025") -> 0 | BD18: =COUNTIFS('List Order'!B:B,"Mei",'List Order'!I:I,"Colocation",'List Order'!C:C,"2025") -> 0 | BF18: =COUNTIFS('List Order'!B:B,"Juni",'List Order'!I:I,"Colocation",'List Order'!C:C,"2025") -> 0 | BH18: =COUNTIFS('List Order'!B:B,"Juli",'List Order'!I:I,"Colocation",'List Order'!C:C,"2025") -> 0 | BJ18: =COUNTIFS('List Order'!B:B,"Agustus",'List Order'!I:I,"Colocation",'List Order'!C:C,"2025") -> 0 | BL18: =COUNTIFS('List Order'!B:B,"September",'List Order'!I:I,"Colocation",'List Order'!C:C,"2025") -> 0 | BN18: =COUNTIFS('List Order'!B:B,"Oktober",'List Order'!I:I,"Colocation",'List Order'!C:C,"2025") -> 1 | BP18: =COUNTIFS('List Order'!B:B,"November",'List Order'!I:I,"Colocation",'List Order'!C:C,"2025") -> 1 | BR18: =COUNTIFS('List Order'!B:B,"Desember",'List Order'!I:I,"Colocation",'List Order'!C:C,"2025") -> 0
